Workbook

Sheet Ответы на вопросы
A1: Ответы на вопросы
A2: 1. Достаточно ли инвестиций в 80 млн для выхода сервиса на операционную прибыль и доработку?
A3: Нет. В начале второго года бизнес уходит в минус (конкретный месяц плавает из-за случайной величины, которую я добавила для симуляции реальных показателей. Можно потыкать на ширину какого-нибудь столбца и в реальном времени увидеть, какой примерно прогноз ждет сервис, если не опираться на конкретные значения). Сервис выходит на операционную прибыль только ближе к середине-концу третьего года работы. | C3: *можно было бы добавить больше случайности или регулируемый показатель дисперсии, но я поленилась
A5: 2. Как быстро с заложенными темпами роста компания сможет выйти на 3000 пользователей?
A6: За три года, которые смоделированы в этом документе, сервис не выходит на 3000 пользователей. Мы закладываем бюджет маркетинга до 3 млн рублей и примерный отток в 5-7%, и со временем прирост и отток начинают выравниваться, из-за чего активная база начинает выходить на "плато". Нужно масштабировать расходы на удержание клиентов и привлечение новых клиентов, поскольку сейчас клиенты приходят и не остаются.
A8: 3. Какой будет среднемесячная прибыль компании через 2 года?
A9: Среднемесячная прибыль компании за 1 и 2 год равна | B9: =SUM('ОПИУ (расчеты)'!C34:Z34)/24 -> -4696135.2
A10: Среднемесячная прибыль компании за 2 год равна | B10: =SUM('ОПИУ (расчеты)'!O34:Z34)/12 -> -3095746.1
A20: там справа графики - - - - - >

Sheet ОПИУ (расчеты)
B1: ВХОДНЫЕ ДАННЫЕ для формул
B3: Базовый тариф | C3: 3900 | D3: 0.8
B4: Премиум-тариф | C4: 9900 | D4: 0.2
B5: Расширенный пакет | C5: 1900
B6: Сопр. фин. эксперта | C6: 30000
B7: Ежегодная индексация | C7: +3% | D7: 1.03
B8: Бюджет на маркетинг | C8: 1000000 | D8: +100к ежемесячно
B9: Конверсия в демонстрацию работы | C9: 0.25
B10: Конверсия в покупку после демонстрации | C10: 0.33
B11: Цена лида с рекламы | C11: 1800
B12: Аренда | C12: 350000
B13: Комиссии | C13: 0.02
B14: ФОТ административный персонал | C14: 1350000
B15: ФОТ продажи | C15: 600000 | D15: +3% от выручки
B16: ФОТ поддержка | C16: 60000
B17: Налоги | C17: 0.1
B18: Хостинг | C18: 333000
B19: Прочие операционные расходы | C19: 250000
B20: ИТ-инфраструктура | C20: 1000000
B23: ОПИУ | C23: 1 год | O23: 2 год | AA23: 3 год
B24: Статья | C24: Январь | D24: Февраль | E24: Март | F24: Апрель | G24: Май | H24: Июнь | I24: Июль | J24: Август | K24: Сентябрь | L24: Октябрь | M24: Ноябрь | N24: Декабрь | O24: Январь | P24: Февраль | Q24: Март | R24: Апрель | S24: Май | T24: Июнь | U24: Июль | V24: Август | W24: Сентябрь | X24: Октябрь | Y24: Ноябрь | Z24: Декабрь | AA24: Январь | AB24: Февраль | AC24: Март | AD24: Апрель | AE24: Май | AF24: Июнь | AG24: Июль | AH24: Август | AI24: Сентябрь | AJ24: Октябрь | AK24: Ноябрь | AL24: Декабрь
B26: Выручка от реализации (за минусом возвратов) | C26: =SUM(C27:C30) -> 152700 | D26: =SUM(D27:D30) -> 429551.36 | E26: =SUM(E27:E30) -> 677255.07 | F26: =SUM(F27:F30) -> 952579.82 | G26: =SUM(G27:G30) -> 1262382.1 | H26: =SUM(H27:H30) -> 1587559.5 | I26: =SUM(I27:I30) -> 1927097.2 | J26: =SUM(J27:J30) -> 2247855.4 | ... AL26: =SUM(AL27:AL30) -> 12172365
B27: Базовый тариф | C27: =$C$3*C73 -> 117000 | D27: =$C$3*D73 -> 254325.32 | E27: =$C$3*E73 -> 377192.66 | F27: =$C$3*F73 -> 513760.74 | G27: =$C$3*G73 -> 667430.54 | H27: =$C$3*H73 -> 828726.81 | I27: =$C$3*I73 -> 997146.15 | J27: =$C$3*J73 -> 1156250.4 | ... N27: =$C$3*N73 -> 1947546.4 | O27: =$C$3*$D$7*O73 -> 2200250.3 | P27: =$C$3*$D$7*P73 -> 2427895.9 | Q27: =$C$3*$D$7*Q73 -> 2666442.8 | R27: =$C$3*$D$7*R73 -> 2883079.9 | S27: =$C$3*$D$7*S73 -> 3045098.3 | T27: =$C$3*$D$7*T73 -> 3329192.8 | U27: =$C$3*$D$7*U73 -> 3546341.3 | V27: =$C$3*$D$7*V73 -> 3756013.3 | ... Z27: =$C$3*$D$7*Z73 -> 4500263.6 | AA27: =$C$3*$D$7*$D$7*AA73 -> 4857285.1 | AB27: =$C$3*$D$7*$D$7*AB73 -> 5001296.9 | AC27: =$C$3*$D$7*$D$7*AC73 -> 5125333 | AD27: =$C$3*$D$7*$D$7*AD73 -> 5289939.8 | AE27: =$C$3*$D$7*$D$7*AE73 -> 5432612.8 | AF27: =$C$3*$D$7*$D$7*AF73 -> 5644599 | AG27: =$C$3*$D$7*$D$7*AG73 -> 5795539 | AH27: =$C$3*$D$7*$D$7*AH73 -> 5885530.1 | ... AL27: =$C$3*$D$7*$D$7*AL73 -> 6148072.1
B28: Премиум-тариф | C28: =$C$4*C74 -> 0 | D28: =$C$4*D74 -> 87148.76 | E28: =$C$4*E74 -> 165122.26 | F28: =$C$4*F74 -> 251790.47 | G28: =$C$4*G74 -> 349311.69 | H28: =$C$4*H74 -> 451672.78 | I28: =$C$4*I74 -> 558554.29 | J28: =$C$4*J74 -> 659524.27 | ... N28: =$C$4*N74 -> 1161692.9 | O28: =$C$4*$D$7*O74 -> 1319835.2 | P28: =$C$4*$D$7*P74 -> 1464302.6 | Q28: =$C$4*$D$7*Q74 -> 1615688.1 | R28: =$C$4*$D$7*R74 -> 1753169.3 | S28: =$C$4*$D$7*S74 -> 1855988.7 | T28: =$C$4*$D$7*T74 -> 2036279.5 | U28: =$C$4*$D$7*U74 -> 2174085.3 | V28: =$C$4*$D$7*V74 -> 2307146.3 | ... Z28: =$C$4*$D$7*Z74 -> 2779459 | AA28: =$C$4*$D$7*$D$7*AA74 -> 3003736 | AB28: =$C$4*$D$7*$D$7*AB74 -> 3095128.1 | AC28: =$C$4*$D$7*$D$7*AC74 -> 3173843.4 | AD28: =$C$4*$D$7*$D$7*AD74 -> 3278305.4 | AE28: =$C$4*$D$7*$D$7*AE74 -> 3368847.8 | AF28: =$C$4*$D$7*$D$7*AF74 -> 3503377.6 | AG28: =$C$4*$D$7*$D$7*AG74 -> 3599166.4 | AH28: =$C$4*$D$7*$D$7*AH74 -> 3656276.1 | ... AL28: =$C$4*$D$7*$D$7*AL74 -> 3822889.3
B29: Расширенный пакет | C29: =$C$5*(C75/10) -> 5700 | D29: =$C$5*(D75/10) -> 14062.76 | E29: =$C$5*(E75/10) -> 21545.066 | F29: =$C$5*(F75/10) -> 29861.712 | G29: =$C$5*(G75/10) -> 39219.808 | H29: =$C$5*(H75/10) -> 49042.338 | I29: =$C$5*(I75/10) -> 59298.644 | J29: =$C$5*(J75/10) -> 68987.682 | ... AL29: =$C$5*(AL75/10) -> 351484.63
B30: Сопр. финансового эксперта | C30: =$C$6*(C75/30) -> 30000 | D30: =$C$6*(D75/30) -> 74014.525 | E30: =$C$6*(E75/30) -> 113395.08 | F30: =$C$6*(F75/30) -> 157166.9 | G30: =$C$6*(G75/30) -> 206420.04 | H30: =$C$6*(H75/30) -> 258117.57 | I30: =$C$6*(I75/30) -> 312098.12 | J30: =$C$6*(J75/30) -> 363093.06 | ... AL30: =$C$6*(AL75/30) -> 1849919.1
B31: Прирост выручки (% к прошлому месяцу) | C31: 0 | D31: =(D26/C26)-1 -> 1.813041 | E31: =(E26/D26)-1 -> 0.57665677 | F31: =(F26/E26)-1 -> 0.40653037 | G31: =(G26/F26)-1 -> 0.32522446 | H31: =(H26/G26)-1 -> 0.25759033 | I31: =(I26/H26)-1 -> 0.21387401 | J31: =(J26/I26)-1 -> 0.16644628 | K31: =(K26/J26)-1 -> 0.13515324 | ... AL31: =(AL26/AK26)-1 -> 0.011855745
B32: Расходы | C32: =C41+C48+C61 -> 8065905 | D32: =D41+D48+D61 -> 8207432.7 | E32: =E41+E48+E61 -> 8404588.3 | F32: =F41+F48+F61 -> 8545887 | G32: =G41+G48+G61 -> 8852357.3 | H32: =H41+H48+H61 -> 9001133.9 | I32: =I41+I48+I61 -> 7212064.6 | J32: =J41+J48+J61 -> 7360178.3 | ... AL32: =AL41+AL48+AL61 -> 11848855
B33: Прирост расходов (% к прошлому месяцу) | C33: 1 | D33: =D32/C32 -> 1.0175464 | E33: =E32/D32 -> 1.0240216 | F33: =F32/E32 -> 1.0168121 | G33: =G32/F32 -> 1.0358617 | H33: =H32/G32 -> 1.0168064 | I33: =I32/H32 -> 0.80123956 | J33: =J32/I32 -> 1.0205369 | K33: =K32/J32 -> 1.0415168 | ... AL33: =AL32/AK32 -> 1.0018088
B34: Чистая прибыль | C34: =C26-C32 -> -7913205 | D34: =D26-D32 -> -7777881.3 | E34: =E26-E32 -> -7727333.2 | F34: =F26-F32 -> -7593307.2 | G34: =G26-G32 -> -7589975.2 | H34: =H26-H32 -> -7413574.4 | I34: =I26-I32 -> -5284967.4 | J34: =J26-J32 -> -5112322.9 | ... AL34: =AL26-AL32 -> 323510.34
B35: Прибыль нарастающим итогом | C35: =C34 -> -7913205 | D35: =D34+C34 -> -15691086 | E35: =E34+D34 -> -15505215 | F35: =F34+E34 -> -15320640 | G35: =G34+F34 -> -15183282 | H35: =H34+G34 -> -15003550 | I35: =I34+H34 -> -12698542 | J35: =J34+I34 -> -10397290 | K35: =K34+J34 -> -10226412 | ... AL35: =AL34+AK34 -> 525792.34
B36: Рентабельность чистой прибыли (%) | C36: =C34/C26 -> -51.821906 | D36: =D34/D26 -> -18.106988 | E36: =E34/E26 -> -11.409783 | F36: =F34/F26 -> -7.971308 | G36: =G34/G26 -> -6.0124232 | H36: =H34/H26 -> -4.6697931 | I36: =I34/I26 -> -2.7424498 | J36: =J34/J26 -> -2.2743113 | ... AL36: =AL34/AL26 -> 0.026577443
B37: Маржинальная прибыль | C37: =C26-C41 -> -1614935 | D37: =D26-D41 -> -1351926.2 | E37: =E26-E41 -> -1176607.7 | F37: =F26-F41 -> -915049.17 | G37: =G26-G41 -> -780737.03 | H37: =H26-H41 -> -471818.48 | I37: =I26-I41 -> -209257.66 | J37: =J26-J41 -> 95462.603 | ... AL37: =AL26-AL41 -> 7823746.8
B38: Рентабельность маржинальной прибыли (%) | C38: =C37/C26 -> -10.575868 | D38: =D37/D26 -> -3.1472981 | E38: =E37/E26 -> -1.7373184 | F38: =F37/F26 -> -0.96060105 | G38: =G37/G26 -> -0.61846333 | H38: =H37/H26 -> -0.29719736 | I38: =I37/I26 -> -0.10858698 | J38: =J37/J26 -> 0.042468303 | ... AL38: =AL37/AL26 -> 0.64274665
B40: РАСХОДЫ
B41: Переменные расходы | C41: =SUM(C42:C45) -> 1767635 | D41: =SUM(D42:D45) -> 1781477.6 | E41: =SUM(E42:E45) -> 1853862.8 | F41: =SUM(F42:F45) -> 1867629 | G41: =SUM(G42:G45) -> 2043119.1 | H41: =SUM(H42:H45) -> 2059378 | I41: =SUM(I42:I45) -> 2136354.9 | J41: =SUM(J42:J45) -> 2152392.8 | ... AL41: =SUM(AL42:AL45) -> 4348618.3
B42: ФОТ менеджеров поддержки | C42: =ROUNDUP(C75 / 100, 0)*$C$16 -> 60000 | D42: =ROUNDUP(D75 / 100, 0)*$C$16 -> 60000 | E42: =ROUNDUP(E75 / 100, 0)*$C$16 -> 120000 | F42: =ROUNDUP(F75 / 100, 0)*$C$16 -> 120000 | G42: =ROUNDUP(G75 / 100, 0)*$C$16 -> 180000 | H42: =ROUNDUP(H75 / 100, 0)*$C$16 -> 180000 | I42: =ROUNDUP(I75 / 100, 0)*$C$16 -> 240000 | J42: =ROUNDUP(J75 / 100, 0)*$C$16 -> 240000 | ... AL42: =ROUNDUP(AL75 / 100, 0)*$C$16 -> 1140000
B43: ФОТ отдел продаж | C43: =$C$15+(C26*3%) -> 604581 | D43: =$C$15+(D26*3%) -> 612886.54 | E43: =$C$15+(E26*3%) -> 620317.65 | F43: =$C$15+(F26*3%) -> 628577.39 | G43: =$C$15+(G26*3%) -> 637871.46 | H43: =$C$15+(H26*3%) -> 647626.78 | I43: =$C$15+(I26*3%) -> 657812.92 | J43: =$C$15+(J26*3%) -> 667435.66 | ... AL43: =$C$15+(AL26*3%) -> 965170.95
B44: ИТ-инфраструктура | C44: =ROUNDUP(C75 / 200, 0)*100000+$C$20 -> 1100000 | D44: =ROUNDUP(D75 / 200, 0)*100000+$C$20 -> 1100000 | E44: =ROUNDUP(E75 / 200, 0)*100000+$C$20 -> 1100000 | F44: =ROUNDUP(F75 / 200, 0)*100000+$C$20 -> 1100000 | G44: =ROUNDUP(G75 / 200, 0)*100000+$C$20 -> 1200000 | H44: =ROUNDUP(H75 / 200, 0)*100000+$C$20 -> 1200000 | I44: =ROUNDUP(I75 / 200, 0)*100000+$C$20 -> 1200000 | J44: =ROUNDUP(J75 / 200, 0)*100000+$C$20 -> 1200000 | ... AL44: =ROUNDUP(AL75 / 200, 0)*100000+$C$20 -> 2000000
B45: Комиссии | C45: =C26*$C$13 -> 3054 | D45: =D26*$C$13 -> 8591.0273 | E45: =E26*$C$13 -> 13545.101 | F45: =F26*$C$13 -> 19051.596 | G45: =G26*$C$13 -> 25247.642 | H45: =H26*$C$13 -> 31751.19 | I45: =I26*$C$13 -> 38541.944 | J45: =J26*$C$13 -> 44957.107 | ... AL45: =AL26*$C$13 -> 243447.3
B46: Прирост перем. расходов (% к прошлому месяцу) | C46: 1 | D46: =D41/C41 -> 1.0078311 | E46: =E41/D41 -> 1.0406321 | F46: =F41/E41 -> 1.0074257 | G46: =G41/F41 -> 1.0939641 | H46: =H41/G41 -> 1.0079579 | I46: =I41/H41 -> 1.0373787 | J46: =J41/I41 -> 1.0075071 | K46: =K41/J41 -> 1.0813933 | ... AL46: =AL41/AK41 -> 1.0016425
B47: Доля переменных расходов в расходах (%) | C47: =C41/C32 -> 0.219149 | D47: =D41/D32 -> 0.21705662 | E47: =E41/E32 -> 0.22057746 | F47: =F41/F32 -> 0.21854127 | G47: =G41/G32 -> 0.23079944 | H47: =H41/H32 -> 0.22879095 | I47: =I41/I32 -> 0.2962196 | J47: =J41/J32 -> 0.29243758 | ... AL47: =AL41/AL32 -> 0.36700747
B48: Постоянные расходы | C48: =SUM(C49:C54) -> 6283000 | D48: =SUM(D49:D54) -> 6383000 | E48: =SUM(E49:E54) -> 6483000 | F48: =SUM(F49:F54) -> 6583000 | G48: =SUM(G49:G54) -> 6683000 | H48: =SUM(H49:H54) -> 6783000 | I48: =SUM(I49:I54) -> 4883000 | J48: =SUM(J49:J54) -> 4983000 | ... AL48: =SUM(AL49:AL54) -> 6283000
B49: Аренда | C49: =$C$12 -> 350000 | D49: =$C$12 -> 350000 | E49: =$C$12 -> 350000 | F49: =$C$12 -> 350000 | G49: =$C$12 -> 350000 | H49: =$C$12 -> 350000 | I49: =$C$12 -> 350000 | J49: =$C$12 -> 350000 | ... AL49: =$C$12 -> 350000
B50: ФОТ разработка | C50: 3000000 | D50: 3000000 | E50: 3000000 | F50: 3000000 | G50: 3000000 | H50: 3000000 | I50: 1000000 | J50: 1000000 | K50: 1000000 | L50: 1000000 | M50: 1000000 | N50: 1000000 | O50: 1000000 | P50: 1000000 | Q50: 1000000 | R50: 1000000 | S50: 1000000 | T50: 1000000 | U50: 1000000 | V50: 1000000 | W50: 1000000 | X50: 1000000 | Y50: 1000000 | Z50: 1000000 | AA50: 1000000 | AB50: 1000000 | AC50: 1000000 | AD50: 1000000 | AE50: 1000000 | AF50: 1000000 | AG50: 1000000 | AH50: 1000000 | AI50: 1000000 | AJ50: 1000000 | AK50: 1000000 | AL50: 1000000
B51: ФОТ административный персонал | C51: =$C$14 -> 1350000 | D51: =$C$14 -> 1350000 | E51: =$C$14 -> 1350000 | F51: =$C$14 -> 1350000 | G51: =$C$14 -> 1350000 | H51: =$C$14 -> 1350000 | I51: =$C$14 -> 1350000 | J51: =$C$14 -> 1350000 | ... AL51: =$C$14 -> 1350000
B52: Хостинг, лицензии, ИТ, связь | C52: =$C$18 -> 333000 | D52: =$C$18 -> 333000 | E52: =$C$18 -> 333000 | F52: =$C$18 -> 333000 | G52: =$C$18 -> 333000 | H52: =$C$18 -> 333000 | I52: =$C$18 -> 333000 | J52: =$C$18 -> 333000 | ... AL52: =$C$18 -> 333000
B53: Бюджет на маркетинг | C53: =C8 -> 1000000 | D53: ='ОПИУ (расчеты)'!C53 +100000 -> 1100000 | E53: ='ОПИУ (расчеты)'!D53 +100000 -> 1200000 | F53: ='ОПИУ (расчеты)'!E53 +100000 -> 1300000 | G53: ='ОПИУ (расчеты)'!F53 +100000 -> 1400000 | H53: ='ОПИУ (расчеты)'!G53 +100000 -> 1500000 | I53: ='ОПИУ (расчеты)'!H53 +100000 -> 1600000 | J53: ='ОПИУ (расчеты)'!I53 +100000 -> 1700000 | K53: ='ОПИУ (расчеты)'!J53 +100000 -> 1800000 | ... W53: ='ОПИУ (расчеты)'!V53 +100000 -> 3000000 | X53: =3000000 -> 3000000 | Y53: =3000000 -> 3000000 | Z53: =3000000 -> 3000000 | AA53: =3000000 -> 3000000 | AB53: =3000000 -> 3000000 | AC53: =3000000 -> 3000000 | AD53: =3000000 -> 3000000 | AE53: =3000000 -> 3000000 | ... AL53: =3000000 -> 3000000
B54: Прочие операционные расходы | C54: =$C$19 -> 250000 | D54: =$C$19 -> 250000 | E54: =$C$19 -> 250000 | F54: =$C$19 -> 250000 | G54: =$C$19 -> 250000 | H54: =$C$19 -> 250000 | I54: =$C$19 -> 250000 | J54: =$C$19 -> 250000 | ... AL54: =$C$19 -> 250000
B55: Прирост пост. расходов (% к прошлому месяцу) | C55: 1 | D55: =E48/D48 -> 1.0156666 | E55: =F48/E48 -> 1.015425 | F55: =G48/F48 -> 1.0151906 | G55: =H48/G48 -> 1.0149633 | H55: =I48/H48 -> 0.71988796 | I55: =J48/I48 -> 1.0204792 | J55: =K48/J48 -> 1.0200682 | K55: =L48/K48 -> 1.0196734 | ... AL55: =AM48/AL48 -> 0
B56: Доля постоянных расходов в расходах (%) | C56: =C48/C32 -> 0.77895785 | D56: =D48/D32 -> 0.7777097 | E56: =E48/E32 -> 0.77136438 | F56: =F48/F32 -> 0.77031208 | G56: =G48/G32 -> 0.75494015 | H56: =H48/H32 -> 0.75357172 | I56: =I48/I32 -> 0.67705994 | J56: =J48/J32 -> 0.67702164 | ... AL56: =AL48/AL32 -> 0.53026222
B57: Операционная прибыль | C57: =C26-C41-C48 -> -7897935 | D57: =D26-D41-D48 -> -7734926.2 | E57: =E26-E41-E48 -> -7659607.7 | F57: =F26-F41-F48 -> -7498049.2 | G57: =G26-G41-G48 -> -7463737 | H57: =H26-H41-H48 -> -7254818.5 | I57: =I26-I41-I48 -> -5092257.7 | J57: =J26-J41-J48 -> -4887537.4 | ... AL57: =AL26-AL41-AL48 -> 1540746.8
B58: Операционная прибыль нарастающим итогом | C58: =C57 -> -7897935 | D58: =D57+C57 -> -15632861 | E58: =E57+D57 -> -15394534 | F58: =F57+E57 -> -15157657 | G58: =G57+F57 -> -14961786 | H58: =H57+G57 -> -14718556 | I58: =I57+H57 -> -12347076 | J58: =J57+I57 -> -9979795.1 | K58: =K57+J57 -> -9746460.1 | ... AL58: =AL57+AK57 -> 2946003.2
B59: Рентабельность EBITDA (% от общей выручки) | C59: =C57/C26 -> -51.721906 | D59: =D57/D26 -> -18.006988 | E59: =E57/E26 -> -11.309783 | F59: =F57/F26 -> -7.871308 | G59: =G57/G26 -> -5.9124232 | H59: =H57/H26 -> -4.5697931 | I59: =I57/I26 -> -2.6424498 | J59: =J57/J26 -> -2.1743113 | ... AL59: =AL57/AL26 -> 0.12657744
B60: Прочие расходы
B61: Налоговая нагрузка | C61: =$C$17*C26 -> 15270 | D61: =$C$17*D26 -> 42955.136 | E61: =$C$17*E26 -> 67725.507 | F61: =$C$17*F26 -> 95257.982 | G61: =$C$17*G26 -> 126238.21 | H61: =$C$17*H26 -> 158755.95 | I61: =$C$17*I26 -> 192709.72 | J61: =$C$17*J26 -> 224785.54 | ... AL61: =$C$17*AL26 -> 1217236.5
B63: ПРОДАЖИ
B64: Воронка продаж
B65: Бюджет на маркетинг | C65: =C8 -> 1000000 | D65: =C65 +100000 -> 1100000 | E65: =D65 +100000 -> 1200000 | F65: =E65 +100000 -> 1300000 | G65: =F65 +100000 -> 1400000 | H65: =G65 +100000 -> 1500000 | I65: =H65 +100000 -> 1600000 | J65: =I65 +100000 -> 1700000 | K65: =J65 +100000 -> 1800000 | ... W65: =V65 +100000 -> 3000000 | X65: =W65 -> 3000000 | Y65: =X65 -> 3000000 | Z65: =Y65 -> 3000000 | AA65: =Z65 -> 3000000 | AB65: =AA65 -> 3000000 | AC65: =AB65 -> 3000000 | AD65: =AC65 -> 3000000 | AE65: =AD65 -> 3000000 | ... AL65: =AK65 -> 3000000
B66: Конверсия в демонстрацию работы | C66: =$C$9 -> 0.25 | D66: =RANDBETWEEN(22, 28)/100 -> 0.24 | E66: =RANDBETWEEN(22, 28)/100 -> 0.24 | F66: =RANDBETWEEN(22, 28)/100 -> 0.24 | G66: =RANDBETWEEN(22, 28)/100 -> 0.25 | H66: =RANDBETWEEN(22, 28)/100 -> 0.26 | I66: =RANDBETWEEN(22, 28)/100 -> 0.26 | J66: =RANDBETWEEN(22, 28)/100 -> 0.23 | K66: =RANDBETWEEN(22, 28)/100 -> 0.27 | ... AL66: =RANDBETWEEN(22, 28)/100 -> 0.22
B67: Конверсия в покупку после демонстрации | C67: =$C$10 -> 0.33 | D67: =RANDBETWEEN(30,36)/100 -> 0.3 | E67: =RANDBETWEEN(30,36)/100 -> 0.32 | F67: =RANDBETWEEN(30,36)/100 -> 0.34 | G67: =RANDBETWEEN(30,36)/100 -> 0.33 | H67: =RANDBETWEEN(30,36)/100 -> 0.32 | I67: =RANDBETWEEN(30,36)/100 -> 0.3 | J67: =RANDBETWEEN(30,36)/100 -> 0.32 | K67: =RANDBETWEEN(30,36)/100 -> 0.35 | ... AL67: =RANDBETWEEN(30,36)/100 -> 0.34
B68: Цена перехода на сайт | C68: =$C11 -> 1800 | D68: =$C11 -> 1800 | E68: =$C11 -> 1800 | F68: =$C11 -> 1800 | G68: =$C11 -> 1800 | H68: =$C11 -> 1800 | I68: =$C11 -> 1800 | J68: =$C11 -> 1800 | ... AL68: =$C11 -> 1800
B69: Лиды | C69: =C65/C68 -> 555.55556 | D69: =D65/D68 -> 611.11111 | E69: =E65/E68 -> 666.66667 | F69: =F65/F68 -> 722.22222 | G69: =G65/G68 -> 777.77778 | H69: =H65/H68 -> 833.33333 | I69: =I65/I68 -> 888.88889 | J69: =J65/J68 -> 944.44444 | ... AL69: =AL65/AL68 -> 1666.6667
B70: Лиды в демо | C70: =C69*C66 -> 138.88889 | D70: =D69*D66 -> 146.66667 | E70: =E69*E66 -> 160 | F70: =F69*F66 -> 173.33333 | G70: =G69*G66 -> 194.44444 | H70: =H69*H66 -> 216.66667 | I70: =I69*I66 -> 231.11111 | J70: =J69*J66 -> 217.22222 | ... AL70: =AL69*AL66 -> 366.66667
B71: Демо в покупку | C71: =C70*C67 -> 45.833333 | D71: =D70*D67 -> 44 | E71: =E70*E67 -> 51.2 | F71: =F70*F67 -> 58.933333 | G71: =G70*G67 -> 64.166667 | H71: =H70*H67 -> 69.333333 | I71: =I70*I67 -> 69.333333 | J71: =J70*J67 -> 69.511111 | ... AL71: =AL70*AL67 -> 124.66667
B72: Отток | C72: 1.8188079 | D72: 4.619443 | E72: 7.4281794 | F72: 9.6801923 | G72: 12.469144 | H72: 15.352775 | I72: 18.338394 | J72: 21.211439 | K72: 23.835978 | L72: 25.583984 | M72: 31.092521 | N72: 34.045216 | O72: 38.672915 | P72: 43.069577 | Q72: 46.987411 | R72: 53.750182 | S72: 57.196185 | T72: 57.978266 | U72: 61.688141 | V72: 65.656109 | W72: 68.329362 | X72: 72.791374 | Y72: 75.595864 | Z72: 81.426564 | AA72: 84.492018 | AB72: 87.193615 | AC72: 89.769969 | AD72: 94.396476 | AE72: 99.289314 | AF72: 98.3989 | AG72: 101.97909 | AH72: 104.45894 | AI72: 107.75322 | AJ72: 111.24429 | AK72: 113.3926 | AL72: 113.30409
B73: Активная база на минимальном тарифе | C73: 30 | D73: =((C71*$D3)+(C73-(C72*$D$3))) -> 65.21162 | E73: =((D71*$D3)+(D73-(D72*$D$3))) -> 96.716066 | F73: =((E71*$D3)+(E73-(E72*$D$3))) -> 131.73352 | G73: =((F71*$D3)+(F73-(F72*$D$3))) -> 171.13604 | H73: =((G71*$D3)+(G73-(G72*$D$3))) -> 212.49405 | I73: =((H71*$D3)+(H73-(H72*$D$3))) -> 255.6785 | J73: =((I71*$D3)+(I73-(I72*$D$3))) -> 296.47445 | K73: =((J71*$D3)+(J73-(J72*$D$3))) -> 335.11419 | ... AL73: =((AK71*$D3)+(AK73-(AK72*$D$3))) -> 1485.9353
B74: Активная база на премиум тарифе | C74: 0 | D74: =((C71*$D4)+(C74-(C72*$D$4))) -> 8.8029051 | E74: =((D71*$D4)+(D74-(D72*$D$4))) -> 16.679016 | F74: =((E71*$D4)+(E74-(E72*$D$4))) -> 25.433381 | G74: =((F71*$D4)+(F74-(F72*$D$4))) -> 35.284009 | H74: =((G71*$D4)+(G74-(G72*$D$4))) -> 45.623513 | I74: =((H71*$D4)+(H74-(H72*$D$4))) -> 56.419625 | J74: =((I71*$D4)+(I74-(I72*$D$4))) -> 66.618613 | K74: =((J71*$D4)+(J74-(J72*$D$4))) -> 76.278547 | ... AL74: =((AK71*$D4)+(AK74-(AK72*$D$4))) -> 363.98382
B75: Общая активная клиентская база | C75: =SUM(C73:C74) -> 30 | D75: =SUM(D73:D74) -> 74.014525 | E75: =SUM(E73:E74) -> 113.39508 | F75: =SUM(F73:F74) -> 157.1669 | G75: =SUM(G73:G74) -> 206.42004 | H75: =SUM(H73:H74) -> 258.11757 | I75: =SUM(I73:I74) -> 312.09812 | J75: =SUM(J73:J74) -> 363.09306 | ... AL75: =SUM(AL73:AL74) -> 1849.9191

Sheet ОДДС (хватит ли 80 млн)
B2: ОДДС 2025 | C2: 1 год | O2: 2 год | AA2: 3 год
B3: Статья | C3: Январь | D3: Февраль | E3: Март | F3: Апрель | G3: Май | H3: Июнь | I3: Июль | J3: Август | K3: Сентябрь | L3: Октябрь | M3: Ноябрь | N3: Декабрь | O3: Январь | P3: Февраль | Q3: Март | R3: Апрель | S3: Май | T3: Июнь | U3: Июль | V3: Август | W3: Сентябрь | X3: Октябрь | Y3: Ноябрь | Z3: Декабрь | AA3: Январь | AB3: Февраль | AC3: Март | AD3: Апрель | AE3: Май | AF3: Июнь | AG3: Июль | AH3: Август | AI3: Сентябрь | AJ3: Октябрь | AK3: Ноябрь | AL3: Декабрь
B5: Деньги на начало | C5: 0 | D5: =C28 -> 72102065 | E5: =D28 -> 64367139 | F5: =E28 -> 56707531 | G5: =F28 -> 49209482 | H5: =G28 -> 41745745 | I5: =H28 -> 34490926 | J5: =I28 -> 29398669 | K5: =J28 -> 24511131 | ... AL5: =AK28 -> -15356212
B6: Операционный денежный поток, итого | C6: =C7-C13-C18 -> -7897935 | D6: =D7-D13-D18 -> -7734926.2 | E6: =E7-E13-E18 -> -7659607.7 | F6: =F7-F13-F18 -> -7498049.2 | G6: =G7-G13-G18 -> -7463737 | H6: =H7-H13-H18 -> -7254818.5 | I6: =I7-I13-I18 -> -5092257.7 | J6: =J7-J13-J18 -> -4887537.4 | ... AL6: =AL7-AL13-AL18 -> 1540746.8
B7: Приток по основной деятельности | C7: ='ОПИУ (расчеты)'!C26 -> 152700 | D7: ='ОПИУ (расчеты)'!D26 -> 429551.36 | E7: ='ОПИУ (расчеты)'!E26 -> 677255.07 | F7: ='ОПИУ (расчеты)'!F26 -> 952579.82 | G7: ='ОПИУ (расчеты)'!G26 -> 1262382.1 | H7: ='ОПИУ (расчеты)'!H26 -> 1587559.5 | I7: ='ОПИУ (расчеты)'!I26 -> 1927097.2 | J7: ='ОПИУ (расчеты)'!J26 -> 2247855.4 | ... AL7: ='ОПИУ (расчеты)'!AL26 -> 12172365
B8: Базовый тариф | C8: ='ОПИУ (расчеты)'!C27 -> 117000 | D8: ='ОПИУ (расчеты)'!D27 -> 254325.32 | E8: ='ОПИУ (расчеты)'!E27 -> 377192.66 | F8: ='ОПИУ (расчеты)'!F27 -> 513760.74 | G8: ='ОПИУ (расчеты)'!G27 -> 667430.54 | H8: ='ОПИУ (расчеты)'!H27 -> 828726.81 | I8: ='ОПИУ (расчеты)'!I27 -> 997146.15 | J8: ='ОПИУ (расчеты)'!J27 -> 1156250.4 | ... AL8: ='ОПИУ (расчеты)'!AL27 -> 6148072.1
B9: Премиум-тариф | C9: ='ОПИУ (расчеты)'!C28 -> 0 | D9: ='ОПИУ (расчеты)'!D28 -> 87148.76 | E9: ='ОПИУ (расчеты)'!E28 -> 165122.26 | F9: ='ОПИУ (расчеты)'!F28 -> 251790.47 | G9: ='ОПИУ (расчеты)'!G28 -> 349311.69 | H9: ='ОПИУ (расчеты)'!H28 -> 451672.78 | I9: ='ОПИУ (расчеты)'!I28 -> 558554.29 | J9: ='ОПИУ (расчеты)'!J28 -> 659524.27 | ... AL9: ='ОПИУ (расчеты)'!AL28 -> 3822889.3
B10: Расширенный пакет | C10: ='ОПИУ (расчеты)'!C29 -> 5700 | D10: 14635.126 | E10: 23530.373 | F10: 30513.353 | G10: 39351.287 | H10: 48578.635 | I10: 58096.142 | J10: 67321.791 | K10: 75470.785 | L10: 80984.134 | M10: 98360.171 | N10: 107675.88 | O10: 122493.31 | P10: 136544.3 | Q10: 148700.91 | R10: 170035.4 | S10: 181175.35 | T10: 183666.31 | U10: 195383.48 | V10: 208093.99 | W10: 216500.28 | X10: 230476.46 | Y10: 239460.54 | Z10: 257977.62 | AA10: 267476.72 | AB10: 276205.74 | AC10: 284126.32 | AD10: 299028.49 | AE10: 314406.82 | AF10: 311507.36 | AG10: 323035.77 | AH10: 330987.3 | AI10: 341234.19 | AJ10: 352252.81 | AK10: 359103.96 | AL10: 358719
B11: Сопр. финансового эксперта | C11: ='ОПИУ (расчеты)'!C30 -> 30000 | D11: 77026.977 | E11: 123844.07 | F11: 160596.6 | G11: 207112.03 | H11: 255677.03 | I11: 305769.17 | J11: 354325.21 | K11: 397214.66 | L11: 426232.29 | M11: 517685.11 | N11: 566715.15 | O11: 644701.64 | P11: 718654.22 | Q11: 782636.35 | R11: 894923.14 | S11: 953554.47 | T11: 966664.78 | U11: 1028334.1 | V11: 1095231.5 | W11: 1139475.1 | X11: 1213034 | Y11: 1260318.6 | Z11: 1357776.9 | AA11: 1407772.2 | AB11: 1453714.4 | AC11: 1495401.7 | AD11: 1573834.2 | AE11: 1654772.7 | AF11: 1639512.4 | AG11: 1700188.2 | AH11: 1742038.4 | AI11: 1795969.4 | AJ11: 1853962.1 | AK11: 1890020.9 | AL11: 1887994.7
B12: Потрачено с Р/с по основной деятельности | C12: ='ОПИУ (расчеты)'!C32 -> 8065905 | D12: ='ОПИУ (расчеты)'!D32 -> 8207432.7 | E12: ='ОПИУ (расчеты)'!E32 -> 8404588.3 | F12: ='ОПИУ (расчеты)'!F32 -> 8545887 | G12: ='ОПИУ (расчеты)'!G32 -> 8852357.3 | H12: ='ОПИУ (расчеты)'!H32 -> 9001133.9 | I12: ='ОПИУ (расчеты)'!I32 -> 7212064.6 | J12: ='ОПИУ (расчеты)'!J32 -> 7360178.3 | ... AL12: ='ОПИУ (расчеты)'!AL32 -> 11848855
B13: Переменные расходы | C13: ='ОПИУ (расчеты)'!C41 -> 1767635 | D13: ='ОПИУ (расчеты)'!D41 -> 1781477.6 | E13: ='ОПИУ (расчеты)'!E41 -> 1853862.8 | F13: ='ОПИУ (расчеты)'!F41 -> 1867629 | G13: ='ОПИУ (расчеты)'!G41 -> 2043119.1 | H13: ='ОПИУ (расчеты)'!H41 -> 2059378 | I13: ='ОПИУ (расчеты)'!I41 -> 2136354.9 | J13: ='ОПИУ (расчеты)'!J41 -> 2152392.8 | ... AL13: ='ОПИУ (расчеты)'!AL41 -> 4348618.3
B14: ФОТ менеджеров поддержки | C14: ='ОПИУ (расчеты)'!C42 -> 60000 | D14: ='ОПИУ (расчеты)'!D42 -> 60000 | E14: ='ОПИУ (расчеты)'!E42 -> 120000 | F14: ='ОПИУ (расчеты)'!F42 -> 120000 | G14: ='ОПИУ (расчеты)'!G42 -> 180000 | H14: ='ОПИУ (расчеты)'!H42 -> 180000 | I14: ='ОПИУ (расчеты)'!I42 -> 240000 | J14: ='ОПИУ (расчеты)'!J42 -> 240000 | ... AL14: ='ОПИУ (расчеты)'!AL42 -> 1140000
B15: ФОТ отдел продаж | C15: ='ОПИУ (расчеты)'!C43 -> 604581 | D15: ='ОПИУ (расчеты)'!D43 -> 612886.54 | E15: ='ОПИУ (расчеты)'!E43 -> 620317.65 | F15: ='ОПИУ (расчеты)'!F43 -> 628577.39 | G15: ='ОПИУ (расчеты)'!G43 -> 637871.46 | H15: ='ОПИУ (расчеты)'!H43 -> 647626.78 | I15: ='ОПИУ (расчеты)'!I43 -> 657812.92 | J15: ='ОПИУ (расчеты)'!J43 -> 667435.66 | ... AL15: ='ОПИУ (расчеты)'!AL43 -> 965170.95
B16: ИТ-инфраструктура | C16: ='ОПИУ (расчеты)'!C44 -> 1100000 | D16: ='ОПИУ (расчеты)'!D44 -> 1100000 | E16: ='ОПИУ (расчеты)'!E44 -> 1100000 | F16: ='ОПИУ (расчеты)'!F44 -> 1100000 | G16: ='ОПИУ (расчеты)'!G44 -> 1200000 | H16: ='ОПИУ (расчеты)'!H44 -> 1200000 | I16: ='ОПИУ (расчеты)'!I44 -> 1200000 | J16: ='ОПИУ (расчеты)'!J44 -> 1200000 | ... AL16: ='ОПИУ (расчеты)'!AL44 -> 2000000
B17: Комиссии | C17: ='ОПИУ (расчеты)'!C45 -> 3054 | D17: ='ОПИУ (расчеты)'!D45 -> 8591.0273 | E17: ='ОПИУ (расчеты)'!E45 -> 13545.101 | F17: ='ОПИУ (расчеты)'!F45 -> 19051.596 | G17: ='ОПИУ (расчеты)'!G45 -> 25247.642 | H17: ='ОПИУ (расчеты)'!H45 -> 31751.19 | I17: ='ОПИУ (расчеты)'!I45 -> 38541.944 | J17: ='ОПИУ (расчеты)'!J45 -> 44957.107 | ... AL17: ='ОПИУ (расчеты)'!AL45 -> 243447.3
B18: Постоянные расходы | C18: ='ОПИУ (расчеты)'!C48 -> 6283000 | D18: ='ОПИУ (расчеты)'!D48 -> 6383000 | E18: ='ОПИУ (расчеты)'!E48 -> 6483000 | F18: ='ОПИУ (расчеты)'!F48 -> 6583000 | G18: ='ОПИУ (расчеты)'!G48 -> 6683000 | H18: ='ОПИУ (расчеты)'!H48 -> 6783000 | I18: ='ОПИУ (расчеты)'!I48 -> 4883000 | J18: ='ОПИУ (расчеты)'!J48 -> 4983000 | ... AL18: ='ОПИУ (расчеты)'!AL48 -> 6283000
B19: Аренда | C19: ='ОПИУ (расчеты)'!C49 -> 350000 | D19: ='ОПИУ (расчеты)'!D49 -> 350000 | E19: ='ОПИУ (расчеты)'!E49 -> 350000 | F19: ='ОПИУ (расчеты)'!F49 -> 350000 | G19: ='ОПИУ (расчеты)'!G49 -> 350000 | H19: ='ОПИУ (расчеты)'!H49 -> 350000 | I19: ='ОПИУ (расчеты)'!I49 -> 350000 | J19: ='ОПИУ (расчеты)'!J49 -> 350000 | ... AL19: ='ОПИУ (расчеты)'!AL49 -> 350000
B20: ФОТ разработка | C20: ='ОПИУ (расчеты)'!C50 -> 3000000 | D20: ='ОПИУ (расчеты)'!D50 -> 3000000 | E20: ='ОПИУ (расчеты)'!E50 -> 3000000 | F20: ='ОПИУ (расчеты)'!F50 -> 3000000 | G20: ='ОПИУ (расчеты)'!G50 -> 3000000 | H20: ='ОПИУ (расчеты)'!H50 -> 3000000 | I20: ='ОПИУ (расчеты)'!I50 -> 1000000 | J20: ='ОПИУ (расчеты)'!J50 -> 1000000 | ... AL20: ='ОПИУ (расчеты)'!AL50 -> 1000000
B21: ФОТ административный персонал | C21: ='ОПИУ (расчеты)'!C51 -> 1350000 | D21: ='ОПИУ (расчеты)'!D51 -> 1350000 | E21: ='ОПИУ (расчеты)'!E51 -> 1350000 | F21: ='ОПИУ (расчеты)'!F51 -> 1350000 | G21: ='ОПИУ (расчеты)'!G51 -> 1350000 | H21: ='ОПИУ (расчеты)'!H51 -> 1350000 | I21: ='ОПИУ (расчеты)'!I51 -> 1350000 | J21: ='ОПИУ (расчеты)'!J51 -> 1350000 | ... AL21: ='ОПИУ (расчеты)'!AL51 -> 1350000
B22: Хостинг, лицензии, ИТ, связь | C22: ='ОПИУ (расчеты)'!C52 -> 333000 | D22: ='ОПИУ (расчеты)'!D52 -> 333000 | E22: ='ОПИУ (расчеты)'!E52 -> 333000 | F22: ='ОПИУ (расчеты)'!F52 -> 333000 | G22: ='ОПИУ (расчеты)'!G52 -> 333000 | H22: ='ОПИУ (расчеты)'!H52 -> 333000 | I22: ='ОПИУ (расчеты)'!I52 -> 333000 | J22: ='ОПИУ (расчеты)'!J52 -> 333000 | ... AL22: ='ОПИУ (расчеты)'!AL52 -> 333000
B23: Бюджет на маркетинг | C23: ='ОПИУ (расчеты)'!C53 -> 1000000 | D23: ='ОПИУ (расчеты)'!D53 -> 1100000 | E23: ='ОПИУ (расчеты)'!E53 -> 1200000 | F23: ='ОПИУ (расчеты)'!F53 -> 1300000 | G23: ='ОПИУ (расчеты)'!G53 -> 1400000 | H23: ='ОПИУ (расчеты)'!H53 -> 1500000 | I23: ='ОПИУ (расчеты)'!I53 -> 1600000 | J23: ='ОПИУ (расчеты)'!J53 -> 1700000 | ... AL23: ='ОПИУ (расчеты)'!AL53 -> 3000000
B24: Прочие операционные расходы | C24: ='ОПИУ (расчеты)'!C54 -> 250000 | D24: ='ОПИУ (расчеты)'!D54 -> 250000 | E24: ='ОПИУ (расчеты)'!E54 -> 250000 | F24: ='ОПИУ (расчеты)'!F54 -> 250000 | G24: ='ОПИУ (расчеты)'!G54 -> 250000 | H24: ='ОПИУ (расчеты)'!H54 -> 250000 | I24: ='ОПИУ (расчеты)'!I54 -> 250000 | J24: ='ОПИУ (расчеты)'!J54 -> 250000 | ... AL24: ='ОПИУ (расчеты)'!AL54 -> 250000
B25: Инвестиции | C25: 80000000
B27: Итого движение денег | C27: =C5+C6+C25 -> 72102065 | D27: =D5+D6+D25 -> 64367139 | E27: =E5+E6+E25 -> 56707531 | F27: =F5+F6+F25 -> 49209482 | G27: =G5+G6+G25 -> 41745745 | H27: =H5+H6+H25 -> 34490926 | I27: =I5+I6+I25 -> 29398669 | J27: =J5+J6+J25 -> 24511131 | ... AL27: =AL5+AL6+AL25 -> -13815465
B28: Деньги на конец месяца | C28: =C5+C27 -> 72102065 | D28: =D27 -> 64367139 | E28: =E27 -> 56707531 | F28: =F27 -> 49209482 | G28: =G27 -> 41745745 | H28: =H27 -> 34490926 | I28: =I27 -> 29398669 | J28: =J27 -> 24511131 | K28: =K27 -> 19652209 | ... AL28: =AL27 -> -13815465
