Workbook

Sheet Сводная таблица
A2: Сводная таблица данных по отделам
C5: Отдел маркетинга | E5: Колл-центр | J5: Отдел продаж | O5: Финансы | Q5: Метрики
A6: Дата | B6: День недели | C6: Посещения | D6: Лиды | E6: Обработано | F6: Качественные | G6: % квал. лидов | H6: Назначено встреч | I6: Конверсия Лид-Назначение | J6: Встречи | K6: Конверсия Назначение-Встреча | L6: Договоров | M6: Конверсия Встреча-Договор | N6: Сумма договоров | O6: Реклама | P6: Поступления | Q6: Стоимость лида | R6: ROI рекламы | S6: CPO | T6: Конверсия Лид-Договор | U6: Конверсия Посещение-Лид | V6: Конверсия Лид-Встреча
A7: 42917 | B7: суббота | C7: {=TRANSPOSE('Отдел маркетинга'!C9:AG9)} -> 1559 | D7: {=TRANSPOSE('Отдел маркетинга'!C13:AG13)} -> 81 | E7: {=TRANSPOSE('Кол-центр'!C5:AG5)} -> 78 | F7: {=TRANSPOSE('Кол-центр'!C7:AG7)} -> 47 | G7: =F7/E7 -> 0.6025641 | H7: {=TRANSPOSE('Кол-центр'!C8:AG8)} -> 20 | I7: =H7/D7 -> 0.24691358 | J7: {=TRANSPOSE('Отдел продаж'!C5:AG5)} -> 5 | K7: =J7/H7 -> 0.25 | L7: {=TRANSPOSE('Отдел продаж'!C6:AG6)} -> 1 | M7: =L7/J7 -> 0.2 | N7: {=TRANSPOSE('Отдел продаж'!C7:AG7)} -> 149953.5 | O7: =SUM('Отдел финансов'!C11:E11) -> 34723 | P7: ='Отдел финансов'!F11 -> 504270 | Q7: =O7/D7 -> 428.67901 | R7: =(P7-O7)/O7 -> 13.522651 | S7: =IFERROR(O7/L7,0) -> 34723 | T7: =L7/D7 -> 0.012345679 | U7: =D7/C7 -> 0.051956382 | V7: =J7/D7 -> 0.061728395
A8: 42918 | B8: воскресенье | C8: 1597 | D8: 101 | E8: 112 | F8: 47 | G8: =F8/E8 -> 0.41964286 | H8: 16 | I8: =H8/D8 -> 0.15841584 | J8: 4 | K8: =J8/H8 -> 0.25 | L8: 2 | M8: =L8/J8 -> 0.5 | N8: 570795 | O8: =SUM('Отдел финансов'!C12:E12) -> 31399 | P8: ='Отдел финансов'!F12 -> 149954 | Q8: =O8/D8 -> 310.88119 | R8: =(P8-O8)/O8 -> 3.7757572 | S8: =IFERROR(O8/L8,0) -> 15699.5 | T8: =L8/D8 -> 0.01980198 | U8: =D8/C8 -> 0.063243582 | V8: =J8/D8 -> 0.03960396
A9: 42919 | B9: понедельник | C9: 2197 | D9: 69 | E9: 66 | F9: 18 | G9: =F9/E9 -> 0.27272727 | H9: 16 | I9: =H9/D9 -> 0.23188406 | J9: 13 | K9: =J9/H9 -> 0.8125 | L9: 3 | M9: =L9/J9 -> 0.23076923 | N9: 620925 | O9: =SUM('Отдел финансов'!C13:E13) -> 58774 | P9: ='Отдел финансов'!F13 -> 570795 | Q9: =O9/D9 -> 851.7971 | R9: =(P9-O9)/O9 -> 8.7116922 | S9: =IFERROR(O9/L9,0) -> 19591.333 | T9: =L9/D9 -> 0.043478261 | U9: =D9/C9 -> 0.031406463 | V9: =J9/D9 -> 0.1884058
A10: 42920 | B10: вторник | C10: 1730 | D10: 71 | E10: 68 | F10: 4 | G10: =F10/E10 -> 0.058823529 | H10: 3 | I10: =H10/D10 -> 0.042253521 | J10: 10 | K10: =J10/H10 -> 3.3333333 | L10: 1 | M10: =L10/J10 -> 0.1 | N10: 416134.5 | O10: =SUM('Отдел финансов'!C14:E14) -> 36565 | P10: ='Отдел финансов'!F14 -> 620925 | Q10: =O10/D10 -> 515 | R10: =(P10-O10)/O10 -> 15.981403 | S10: =IFERROR(O10/L10,0) -> 36565 | T10: =L10/D10 -> 0.014084507 | U10: =D10/C10 -> 0.041040462 | V10: =J10/D10 -> 0.14084507
A11: 42921 | B11: среда | C11: 2062 | D11: 105 | E11: 105 | F11: 46 | G11: =F11/E11 -> 0.43809524 | H11: 15 | I11: =H11/D11 -> 0.14285714 | J11: 13 | K11: =J11/H11 -> 0.86666667 | L11: 3 | M11: =L11/J11 -> 0.23076923 | N11: 44640 | O11: =SUM('Отдел финансов'!C15:E15) -> 52868 | P11: ='Отдел финансов'!F15 -> 416134.5 | Q11: =O11/D11 -> 503.50476 | R11: =(P11-O11)/O11 -> 6.8711981 | S11: =IFERROR(O11/L11,0) -> 17622.667 | T11: =L11/D11 -> 0.028571429 | U11: =D11/C11 -> 0.050921436 | V11: =J11/D11 -> 0.12380952
A12: 42922 | B12: четверг | C12: 1950 | D12: 76 | E12: 76 | F12: 10 | G12: =F12/E12 -> 0.13157895 | H12: 12 | I12: =H12/D12 -> 0.15789474 | J12: 6 | K12: =J12/H12 -> 0.5 | L12: 3 | M12: =L12/J12 -> 0.5 | N12: 750255 | O12: =SUM('Отдел финансов'!C16:E16) -> 53764 | P12: ='Отдел финансов'!F16 -> 357450 | Q12: =O12/D12 -> 707.42105 | R12: =(P12-O12)/O12 -> 5.6485009 | S12: =IFERROR(O12/L12,0) -> 17921.333 | T12: =L12/D12 -> 0.039473684 | U12: =D12/C12 -> 0.038974359 | V12: =J12/D12 -> 0.078947368
A13: 42923 | B13: пятница | C13: 1436 | D13: 66 | E13: 66 | F13: 41 | G13: =F13/E13 -> 0.62121212 | H13: 13 | I13: =H13/D13 -> 0.1969697 | J13: 13 | K13: =J13/H13 -> 1 | L13: 2 | M13: =L13/J13 -> 0.15384615 | N13: 439575 | O13: =SUM('Отдел финансов'!C17:E17) -> 35121 | P13: ='Отдел финансов'!F17 -> 479340 | Q13: =O13/D13 -> 532.13636 | R13: =(P13-O13)/O13 -> 12.648245 | S13: =IFERROR(O13/L13,0) -> 17560.5 | T13: =L13/D13 -> 0.03030303 | U13: =D13/C13 -> 0.045961003 | V13: =J13/D13 -> 0.1969697
A14: 42924 | B14: суббота | C14: 768 | D14: 45 | E14: 47 | F14: 26 | G14: =F14/E14 -> 0.55319149 | H14: 15 | I14: =H14/D14 -> 0.33333333 | J14: 11 | K14: =J14/H14 -> 0.73333333 | L14: 0 | M14: =L14/J14 -> 0 | N14: 0 | O14: =SUM('Отдел финансов'!C18:E18) -> 31301 | P14: ='Отдел финансов'!F18 -> 181935 | Q14: =O14/D14 -> 695.57778 | R14: =(P14-O14)/O14 -> 4.8124341 | S14: =IFERROR(O14/L14,0) -> 0 | T14: =L14/D14 -> 0 | U14: =D14/C14 -> 0.05859375 | V14: =J14/D14 -> 0.24444444
A15: 42925 | B15: воскресенье | C15: 1031 | D15: 51 | E15: 53 | F15: 10 | G15: =F15/E15 -> 0.18867925 | H15: 10 | I15: =H15/D15 -> 0.19607843 | J15: 14 | K15: =J15/H15 -> 1.4 | L15: 3 | M15: =L15/J15 -> 0.21428571 | N15: 101640 | O15: =SUM('Отдел финансов'!C19:E19) -> 27647 | P15: ='Отдел финансов'!F19 -> 505125 | Q15: =O15/D15 -> 542.09804 | R15: =(P15-O15)/O15 -> 17.270518 | S15: =IFERROR(O15/L15,0) -> 9215.6667 | T15: =L15/D15 -> 0.058823529 | U15: =D15/C15 -> 0.049466537 | V15: =J15/D15 -> 0.2745098
A16: 42926 | B16: понедельник | C16: 1151 | D16: 76 | E16: 78 | F16: 45 | G16: =F16/E16 -> 0.57692308 | H16: 10 | I16: =H16/D16 -> 0.13157895 | J16: 4 | K16: =J16/H16 -> 0.4 | L16: 1 | M16: =L16/J16 -> 0.25 | N16: 256350 | O16: =SUM('Отдел финансов'!C20:E20) -> 33234 | P16: ='Отдел финансов'!F20 -> 605820 | Q16: =O16/D16 -> 437.28947 | R16: =(P16-O16)/O16 -> 17.228922 | S16: =IFERROR(O16/L16,0) -> 33234 | T16: =L16/D16 -> 0.013157895 | U16: =D16/C16 -> 0.06602954 | V16: =J16/D16 -> 0.052631579
A17: 42927 | B17: вторник | C17: 1236 | D17: 71 | E17: 73 | F17: 39 | G17: =F17/E17 -> 0.53424658 | H17: 12 | I17: =H17/D17 -> 0.16901408 | J17: 12 | K17: =J17/H17 -> 1 | L17: 4 | M17: =L17/J17 -> 0.33333333 | N17: 1497240 | O17: =SUM('Отдел финансов'!C21:E21) -> 25974 | P17: ='Отдел финансов'!F21 -> 431010 | Q17: =O17/D17 -> 365.83099 | R17: =(P17-O17)/O17 -> 15.593902 | S17: =IFERROR(O17/L17,0) -> 6493.5 | T17: =L17/D17 -> 0.056338028 | U17: =D17/C17 -> 0.057443366 | V17: =J17/D17 -> 0.16901408
A18: 42928 | B18: среда | C18: 1095 | D18: 87 | E18: 80 | F18: 44 | G18: =F18/E18 -> 0.55 | H18: 7 | I18: =H18/D18 -> 0.08045977 | J18: 7 | K18: =J18/H18 -> 1 | L18: 1 | M18: =L18/J18 -> 0.14285714 | N18: 266055 | O18: =SUM('Отдел финансов'!C22:E22) -> 40591 | P18: ='Отдел финансов'!F22 -> 366337.5 | Q18: =O18/D18 -> 466.56322 | R18: =(P18-O18)/O18 -> 8.0250918 | S18: =IFERROR(O18/L18,0) -> 40591 | T18: =L18/D18 -> 0.011494253 | U18: =D18/C18 -> 0.079452055 | V18: =J18/D18 -> 0.08045977
A19: 42929 | B19: четверг | C19: 1168 | D19: 49 | E19: 45 | F19: 26 | G19: =F19/E19 -> 0.57777778 | H19: 13 | I19: =H19/D19 -> 0.26530612 | J19: 13 | K19: =J19/H19 -> 1 | L19: 3 | M19: =L19/J19 -> 0.23076923 | N19: 839610 | O19: =SUM('Отдел финансов'!C23:E23) -> 35188 | P19: ='Отдел финансов'!F23 -> 43425 | Q19: =O19/D19 -> 718.12245 | R19: =(P19-O19)/O19 -> 0.23408548 | S19: =IFERROR(O19/L19,0) -> 11729.333 | T19: =L19/D19 -> 0.06122449 | U19: =D19/C19 -> 0.041952055 | V19: =J19/D19 -> 0.26530612
... A37: 42947 | B37: понедельник | C37: 1327 | D37: 50 | E37: 50 | F37: 28 | G37: =F37/E37 -> 0.56 | H37: 16 | I37: =H37/D37 -> 0.32 | J37: 11 | K37: =J37/H37 -> 0.6875 | L37: 3 | M37: =L37/J37 -> 0.27272727 | N37: 727455 | O37: =SUM('Отдел финансов'!C41:E41) -> 40255 | P37: ='Отдел финансов'!F41 -> 0 | Q37: =O37/D37 -> 805.1 | R37: =(P37-O37)/O37 -> -1 | S37: =IFERROR(O37/L37,0) -> 13418.333 | T37: =L37/D37 -> 0.06 | U37: =D37/C37 -> 0.037678975 | V37: =J37/D37 -> 0.22
A39: ИТОГО (сумма/среднее) | C39: =SUM(C7:C37) -> 36756 | D39: =SUM(D7:D37) -> 1925 | E39: =SUM(E7:E37) -> 1971 | F39: =SUM(F7:F37) -> 883 | G39: =F39/E39 -> 0.44799594 | H39: =SUM(H7:H37) -> 346 | I39: =H39/D39 -> 0.17974026 | J39: =SUM(J7:J37) -> 268 | K39: =J39/H39 -> 0.77456647 | L39: =SUM(L7:L37) -> 69 | M39: =L39/J39 -> 0.25746269 | N39: =SUM(N7:N37) -> 13806736 | O39: =SUM(O7:O37) -> 1170460 | P39: =SUM(P7:P37) -> 12598691 | Q39: =AVERAGE(Q7:Q37) -> 659.01886 | R39: =(P39-O39)/O39 -> 9.76388 | S39: =IFERROR(O39/L39,0) -> 16963.188 | T39: =L39/D39 -> 0.035844156 | U39: =D39/C39 -> 0.052372402 | V39: =J39/D39 -> 0.13922078
A40: План | C40: 35000 | D40: 2500 | G40: 0.8 | I40: 0.5 | K40: 0.5 | M40: 0.35 | S40: 300 | T40: 0.05 | U40: 0.05 | V40: 0.25
A41: Относительно плана | C41: =C39/C40 -> 1.0501714 | D41: =D39/D40 -> 0.77 | G41: =G39/G40 -> 0.55999493 | I41: =I39/I40 -> 0.35948052 | K41: =K39/K40 -> 1.5491329 | M41: =M39/M40 -> 0.73560768 | S41: =S39/S40 -> 56.543961 | T41: =T39/T40 -> 0.71688312 | U41: =D41/C41 -> 0.73321362 | V41: =V39/V40 -> 0.55688312
P45: =N39-P39 -> 1208045.5

Sheet ОПИУ
A2: Отчет о прибылях и убытках
A4: Входные данные
A5: Налоговая нагрузка | B5: 0.1
A6: Себестоимость, % от выручки | B6: 0.5
A7: Постоянные расходы | B7: 1500000
A8: ФОТ отдела продаж (фиксированный) | B8: 300000
A9: ФОТ отдела продаж (бонус) | B9: 0.02
A10: ФОТ остальных отделов | B10: 1000000
A13: Показатель | B13: Сумма | C13: % выручки | D13: Комментарий
A14: Выручка | B14: ='Сводная таблица'!P39 -> 12598691 | C14: =B14/$B$14 -> 1 | D14: факт. приход за июль
A15: Выручка по договорам | B15: ='Сводная таблица'!N39 -> 13806736 | C15: =B15/$B$14 -> 1.0958866 | D15: дебиторка 1,2 млн
A16: Себестоимость продаж | B16: =B14*0.5 -> 6299345.5 | C16: =B16/$B$14 -> 0.5 | D16: входные данные
A17: Валовая прибыль | B17: =B14-B16 -> 6299345.5 | C17: =B17/$B$14 -> 0.5
A18: Операционные расходы | B18: =SUM(B19:B27) -> 6652762.9
A19: Реклама - сайт 1 | B19: ='Отдел финансов'!C42 -> 270642 | C19: =B19/$B$14 -> 0.021481756
A20: Реклама - сайт 2 | B20: ='Отдел финансов'!D42 -> 666306 | C20: =B20/$B$14 -> 0.052886923
A21: Реклама - сайт 3 | B21: ='Отдел финансов'!E42 -> 233512 | C21: =B21/$B$14 -> 0.018534624
A22: Итого реклама | B22: =SUM(B19:B21) -> 1170460 | C22: =B22/$B$14 -> 0.092903302
A23: ФОТ отдела продаж | B23: 300000 | C23: =B23/$B$14 -> 0.023811998
A24: ФОТ отдела продаж - бонус | B24: =0.02*B14 -> 251973.82 | C24: =B24/$B$14 -> 0.02
A25: ФОТ остальных отделов | B25: 1000000 | C25: =B25/$B$14 -> 0.079373325
A26: Постоянные расходы | B26: 1500000 | C26: =B26/$B$14 -> 0.11905999
A27: Налоговая нагрузка | B27: =B14*0.1 -> 1259869.1 | C27: =B27/$B$14 -> 0.1
A28: Операционная прибыль | B28: =B17-B18 -> -353417.42

Sheet Ключевые метрики
A2: Ключевые метрики бизнеса
A4: Метрика | B4: План | C4: Факт | D4: % выполнения | E4: Выполнено? | F4: Комментарий
A5: Отдел маркетинга
A6: Посещения сайта | B6: 35000 | C6: 36756 | D6: =C6/B6 -> 1.0501714 | E6: Да
A7: Лиды | B7: 2500 | C7: 1925 | D7: =C7/B7 -> 0.77 | E7: Нет | F7: Заметно меньше плана. Основные потрели на сайтах 1 и 2 во второй половине месяца.
A8: Конверсия посещение-лид | B8: ='Сводная таблица'!U40 -> 0.05 | C8: ='Сводная таблица'!U39 -> 0.052372402 | D8: =C8/B8 -> 1.047448 | E8: Да
A9: Стоимость лида | C9: ='Сводная таблица'!Q39 -> 659.01886 | F9: Возможно, в таблице от Отдела маркетинга под CPO должна была подразумеваться стоимость лида, а не стоимость договора.
A10: Колл-центр
A11: % качественных лидов | B11: ='Сводная таблица'!G40 -> 0.8 | C11: ='Сводная таблица'!G39 -> 0.44799594 | D11: =C11/B11 -> 0.55999493 | E11: Нет | F11: Значительно меньше плана! Половина лидов некачественные!
A12: Конверсия лид-назначение | B12: ='Сводная таблица'!I40 -> 0.5 | C12: ='Сводная таблица'!I39 -> 0.17974026 | D12: =C12/B12 -> 0.35948052 | E12: Нет | F12: Очень узкая точка воронки продаж. Либо переоценили свои силы, либо нужно поработать над скриптами колл-центра.
A13: Конверсие назначение-встреча | B13: ='Сводная таблица'!K40 -> 0.5 | C13: ='Сводная таблица'!K39 -> 0.77456647 | D13: =C13/B13 -> 1.5491329 | E13: Да | F13: Высокий показатель. Клиенты, договорившиеся на визит, чаще всего приходят на встречу.
A14: Отдел продаж
A15: Конверсия встреча-договор | B15: ='Сводная таблица'!M40 -> 0.35 | C15: ='Сводная таблица'!M39 -> 0.25746269 | D15: =C15/B15 -> 0.73560768 | E15: Нет
A16: Конверсия лид-договор | B16: ='Сводная таблица'!T40 -> 0.05 | C16: ='Сводная таблица'!T39 -> 0.035844156 | D16: =C16/B16 -> 0.71688312 | E16: Нет
A17: Договора | C17: ='Сводная таблица'!L39 -> 69
A18: Средняя сумма договора | C18: ='Сводная таблица'!N39/'Сводная таблица'!L39 -> 200097.63
A19: Отдел финансов
A20: Расходы на рекламу | C20: ='Сводная таблица'!O39 -> 1170460 | F20: Примерно 9,3% от выручки. Большую часть занимает Сайт 2 - 57% бюджета.
A21: Доходы | C21: ='Сводная таблица'!P39 -> 12598691 | F21: Разница с суммой договоров - 1 208 045,50 ₽. Дебиторская задолженность.
A22: Стоимость договора | C22: ='Сводная таблица'!S39 -> 16963.188
A23: ROI рекламы | C23: ='Сводная таблица'!R39 -> 9.76388

Sheet Отдел продаж
B2: ОТДЕЛ ПРОДАЖ
B4: По отделу | C4: 42917 | D4: 42918 | E4: 42919 | F4: 42920 | G4: 42921 | H4: 42922 | I4: 42923 | J4: 42924 | K4: 42925 | L4: 42926 | M4: 42927 | N4: 42928 | O4: 42929 | P4: 42930 | Q4: 42931 | R4: 42932 | S4: 42933 | T4: 42934 | U4: 42935 | V4: 42936 | W4: 42937 | X4: 42938 | Y4: 42939 | Z4: 42940 | AA4: 42941 | AB4: 42942 | AC4: 42943 | AD4: 42944 | AE4: 42945 | AF4: 42946 | AG4: 42947
B5: Факт встречи новые | C5: 5 | D5: 4 | E5: 13 | F5: 10 | G5: 13 | H5: 6 | I5: 13 | J5: 11 | K5: 14 | L5: 4 | M5: 12 | N5: 7 | O5: 13 | P5: 5 | Q5: 9 | R5: 4 | S5: 11 | T5: 7 | U5: 12 | V5: 11 | W5: 11 | X5: 5 | Y5: 2 | Z5: 4 | AA5: 6 | AB5: 8 | AC5: 8 | AD5: 6 | AE5: 13 | AF5: 10 | AG5: 11
B6: Договоров штук | C6: 1 | D6: 2 | E6: 3 | F6: 1 | G6: 3 | H6: 3 | I6: 2 | J6: 0 | K6: 3 | L6: 1 | M6: 4 | N6: 1 | O6: 3 | P6: 2 | Q6: 2 | R6: 0 | S6: 1 | T6: 0 | U6: 3 | V6: 5 | W6: 3 | X6: 2 | Y6: 0 | Z6: 0 | AA6: 2 | AB6: 6 | AC6: 2 | AD6: 1 | AE6: 5 | AF6: 5 | AG6: 3
B7: Договора сумма | C7: 149953.5 | D7: 570795 | E7: 620925 | F7: 416134.5 | G7: 44640 | H7: 750255 | I7: 439575 | J7: 0 | K7: 101640 | L7: 256350 | M7: 1497240 | N7: 266055 | O7: 839610 | P7: 462360 | Q7: 513720 | R7: 0 | S7: 499680 | T7: 0 | U7: 634708.5 | V7: 603900 | W7: 159570 | X7: 223680 | Y7: 0 | Z7: 0 | AA7: 212130 | AB7: 1745580 | AC7: 489615 | AD7: 240750 | AE7: 922470 | AF7: 417945 | AG7: 727455
B8: Факт повторные встречи | C8: 0 | D8: 1 | E8: 0 | F8: 0 | G8: 1 | H8: 0 | I8: 0 | J8: 0 | K8: 0 | L8: 2 | M8: 1 | N8: 2 | O8: 1 | P8: 0 | Q8: 0 | R8: 0 | S8: 2 | T8: 0 | U8: 0 | V8: 1 | W8: 0 | X8: 0 | Y8: 1 | Z8: 0 | AA8: 0 | AB8: 1 | AC8: 0 | AD8: 0 | AE8: 0 | AF8: 0 | AG8: 0
B9: Договора с повторных встреч | C9: 0 | D9: 1 | E9: 0 | F9: 0 | G9: 1 | H9: 0 | I9: 0 | J9: 0 | K9: 0 | L9: 1 | M9: 0 | N9: 0 | O9: 0 | P9: 0 | Q9: 0 | R9: 0 | S9: 1 | T9: 0 | U9: 0 | V9: 0 | W9: 0 | X9: 0 | Y9: 0 | Z9: 0 | AA9: 0 | AB9: 0 | AC9: 0 | AD9: 0 | AE9: 0 | AF9: 0 | AG9: 0
B11: Целевая конверсия визит-договор 35%
B12: Целевая конверсия лид-договор 5%

Sheet Отдел маркетинга
B2: ОТДЕЛ МАРКЕТИНГА
B5: KPI | C5: Июль | AI5: Показатели план
C6: Сб. | D6: Вс. | E6: Пн. | F6: Вт. | G6: Ср. | H6: Чт. | I6: Пт. | J6: Сб. | K6: Вс. | L6: Пн. | M6: Вт. | N6: Ср. | O6: Чт. | P6: Пт. | Q6: Сб. | R6: Вс. | S6: Пн. | T6: Вт. | U6: Ср. | V6: Чт. | W6: Пт. | X6: Сб. | Y6: Вс. | Z6: Пн. | AA6: Вт. | AB6: Ср. | AC6: Чт. | AD6: Пт. | AE6: Сб. | AF6: Вс. | AG6: Пн.
C7: 42917 | D7: 42918 | E7: 42919 | F7: 42920 | G7: 42921 | H7: 42922 | I7: 42923 | J7: 42924 | K7: 42925 | L7: 42926 | M7: 42927 | N7: 42928 | O7: 42929 | P7: 42930 | Q7: 42931 | R7: 42932 | S7: 42933 | T7: 42934 | U7: 42935 | V7: 42936 | W7: 42937 | X7: 42938 | Y7: 42939 | Z7: 42940 | AA7: 42941 | AB7: 42942 | AC7: 42943 | AD7: 42944 | AE7: 42945 | AF7: 42946 | AG7: 42947
B8: Отдел маркетинга
B9: Посещения на сайт | C9: =SUM(C10:C12) -> 1559 | D9: =SUM(D10:D12) -> 1597 | E9: =SUM(E10:E12) -> 2197 | F9: =SUM(F10:F12) -> 1730 | G9: =SUM(G10:G12) -> 2062 | H9: =SUM(H10:H12) -> 1950 | I9: =SUM(I10:I12) -> 1436 | J9: =SUM(J10:J12) -> 768 | ... AG9: =SUM(AG10:AG12) -> 1327 | AI9: =IFERROR(AI13/AI22, 0) -> 0
B10: Посещения на сайт: сайт 1 | C10: 689 | D10: 684 | E10: 851 | F10: 716 | G10: 866 | H10: 826 | I10: 485 | J10: 550 | K10: 787 | L10: 787 | M10: 1076 | N10: 1051 | O10: 971 | P10: 899 | Q10: 721 | R10: 354 | S10: 978 | T10: 848 | U10: 779 | V10: 822 | W10: 580 | X10: 505 | Y10: 634 | Z10: 676 | AA10: 586 | AB10: 778 | AC10: 694 | AD10: 784 | AE10: 536 | AF10: 659 | AG10: 940 | AI10: =IFERROR(AI14/AI23, 0) -> 0
B11: Посещения на сайт: сайт 2 | C11: 113 | D11: 169 | E11: 361 | F11: 208 | G11: 349 | H11: 277 | I11: 161 | J11: 26 | K11: 14 | L11: 14 | M11: 11 | N11: 13 | O11: 70 | P11: 53 | Q11: 34 | R11: 26 | S11: 80 | T11: 77 | U11: 76 | V11: 72 | W11: 53 | X11: 43 | Y11: 177 | Z11: 183 | AA11: 192 | AB11: 202 | AC11: 194 | AD11: 187 | AE11: 153 | AF11: 192 | AG11: 171 | AI11: =IFERROR(AI15/AI24, 0) -> 0
B12: Посещения на сайт: сайт 3 | C12: 757 | D12: 744 | E12: 985 | F12: 806 | G12: 847 | H12: 847 | I12: 790 | J12: 192 | K12: 230 | L12: 350 | M12: 149 | N12: 31 | O12: 127 | P12: 124 | Q12: 95 | R12: 72 | S12: 118 | T12: 128 | U12: 116 | V12: 100 | W12: 110 | X12: 110 | Y12: 202 | Z12: 192 | AA12: 265 | AB12: 180 | AC12: 188 | AD12: 192 | AE12: 167 | AF12: 263 | AG12: 216 | AI12: =IFERROR(AI16/AI25, 0) -> 0
B13: Лиды | C13: =SUM(C14:C16)+C17 -> 81 | D13: =SUM(D14:D16)+D17 -> 101 | E13: =SUM(E14:E16)+E17 -> 69 | F13: =SUM(F14:F16)+F17 -> 71 | G13: =SUM(G14:G16)+G17 -> 105 | H13: =SUM(H14:H16)+H17 -> 76 | I13: =SUM(I14:I16)+I17 -> 66 | J13: =SUM(J14:J16)+J17 -> 45 | ... AG13: =SUM(AG14:AG16)+AG17 -> 50 | AI13: 2500
B14: Лиды: сайт 1 | C14: 30 | D14: 46 | E14: 34 | F14: 31 | G14: 30 | H14: 22 | I14: 20 | J14: 15 | K14: 12 | L14: 32 | M14: 15 | N14: 20 | O14: 12 | P14: 3 | Q14: 3 | R14: 0 | S14: 20 | T14: 20 | U14: 9 | V14: 13 | W14: 7 | X14: 4 | Y14: 8 | Z14: 7 | AA14: 8 | AB14: 6 | AC14: 7 | AD14: 4 | AE14: 2 | AF14: 2 | AG14: 7 | AI14: 833
B15: Лиды: сайт 2 | C15: 21 | D15: 5 | E15: 17 | F15: 20 | G15: 37 | H15: 30 | I15: 23 | J15: 22 | K15: 25 | L15: 27 | M15: 39 | N15: 38 | O15: 23 | P15: 32 | Q15: 22 | R15: 18 | S15: 39 | T15: 27 | U15: 30 | V15: 50 | W15: 21 | X15: 12 | Y15: 25 | Z15: 26 | AA15: 29 | AB15: 23 | AC15: 25 | AD15: 17 | AE15: 13 | AF15: 14 | AG15: 20 | AI15: 833
B16: Лиды: сайт 3 | C16: 22 | D16: 4 | E16: 6 | F16: 11 | G16: 19 | H16: 13 | I16: 14 | J16: 4 | K16: 2 | L16: 2 | M16: 2 | N16: 9 | O16: 2 | P16: 6 | Q16: 2 | R16: 1 | S16: 3 | T16: 3 | U16: 2 | V16: 6 | W16: 4 | X16: 7 | Y16: 2 | Z16: 1 | AA16: 4 | AB16: 2 | AC16: 8 | AD16: 4 | AE16: 10 | AF16: 11 | AG16: 4 | AI16: 833
B17: Без номера визита | C17: 8 | D17: 46 | E17: 12 | F17: 9 | G17: 19 | H17: 11 | I17: 9 | J17: 4 | K17: 12 | L17: 15 | M17: 15 | N17: 20 | O17: 12 | P17: 3 | Q17: 3 | R17: 0 | S17: 31 | T17: 23 | U17: 21 | V17: 35 | W17: 29 | X17: 15 | Y17: 29 | Z17: 21 | AA17: 12 | AB17: 14 | AC17: 15 | AD17: 12 | AE17: 20 | AF17: 22 | AG17: 19
B21: План 35 000 посещений/мес
B22: План 2500 лидов/мес
B24: Целевая конверсия посещение-лид 5%
B25: Целевой CPO 300 рублей

Sheet Отдел финансов
B1: ОТДЕЛ ФИНАНСОВ
B3: Налоговая нагрузка — 10% от выручки.
B4: Себестоимость — 50% в среднем.
B5: Постоянные расходы — 1,5 млн рублей.
B6: ФОТ отдела продаж — 300 тыс + 2% с поступлений.
B7: ФОТ остальной компании — 1 млн рублей.
B10: Расход рекламного бюджета | C10: Сайт 1 | D10: Сайт 2 | E10: Сайт 3 | F10: Факт поступления денег | G10: Сумма расходов
B11: 42917 | C11: 5331 | D11: 17559 | E11: 11833 | F11: 504270 | G11: =SUM(C11:E11) -> 34723
B12: 42918 | C12: 5825 | D12: 15155 | E12: 10419 | F12: 149954 | G12: =SUM(C12:E12) -> 31399
B13: 42919 | C13: 17537 | D13: 23675 | E13: 17562 | F13: 570795 | G13: =SUM(C13:E13) -> 58774
B14: 42920 | C14: 7859 | D14: 14252 | E14: 14454 | F14: 620925 | G14: =SUM(C14:E14) -> 36565
B15: 42921 | C15: 16464 | D15: 20033 | E15: 16371 | F15: 416134.5 | G15: =SUM(C15:E15) -> 52868
B16: 42922 | C16: 15559 | D16: 21742 | E16: 16463 | F16: 357450 | G16: =SUM(C16:E16) -> 53764
B17: 42923 | C17: 7703 | D17: 11839 | E17: 15579 | F17: 479340 | G17: =SUM(C17:E17) -> 35121
B18: 42924 | C18: 1210 | D18: 15853 | E18: 14238 | F18: 181935 | G18: =SUM(C18:E18) -> 31301
B19: 42925 | C19: 134 | D19: 21243 | E19: 6270 | F19: 505125 | G19: =SUM(C19:E19) -> 27647
B20: 42926 | C20: 1241 | D20: 25548 | E20: 6445 | F20: 605820 | G20: =SUM(C20:E20) -> 33234
B21: 42927 | C21: 3866 | D21: 18900 | E21: 3208 | F21: 431010 | G21: =SUM(C21:E21) -> 25974
B22: 42928 | C22: 3654 | D22: 33899 | E22: 3038 | F22: 366337.5 | G22: =SUM(C22:E22) -> 40591
... B41: 42947 | C41: 10279 | D41: 28298 | E41: 1678 | F41: 0 | G41: =SUM(C41:E41) -> 40255
C42: =SUM(C11:C41) -> 270642 | D42: =SUM(D11:D41) -> 666306 | E42: =SUM(E11:E41) -> 233512 | F42: =SUM(F11:F41) -> 12598691
C44: =C42/(SUM($C$42:$E$42)) -> 0.23122704 | D44: =D42/(SUM($C$42:$E$42)) -> 0.56926849 | E44: =E42/(SUM($C$42:$E$42)) -> 0.19950447

Sheet Кол-центр
B1: КОЛ-ЦЕНТР
B3: Показатели | C3: Сб. | D3: Вс. | E3: Пн. | F3: Вт. | G3: Ср. | H3: Чт. | I3: Пт. | J3: Сб. | K3: Вс. | L3: Пн. | M3: Вт. | N3: Ср. | O3: Чт. | P3: Пт. | Q3: Сб. | R3: Вс. | S3: Пн. | T3: Вт. | U3: Ср. | V3: Чт. | W3: Пт. | X3: Сб. | Y3: Вс. | Z3: Пн. | AA3: Вт. | AB3: Ср. | AC3: Чт. | AD3: Пт. | AE3: Сб. | AF3: Вс. | AG3: Пн. | AU3: Мотивация | BQ3: Мотривация
C4: 45839 | D4: 45840 | E4: 45841 | F4: 45842 | G4: 45843 | H4: 45844 | I4: 45845 | J4: 45846 | K4: 45847 | L4: 45848 | M4: 45849 | N4: 45850 | O4: 45851 | P4: 45852 | Q4: 45853 | R4: 45854 | S4: 45855 | T4: 45856 | U4: 45857 | V4: 45858 | W4: 45859 | X4: 45860 | Y4: 45861 | Z4: 45862 | AA4: 45863 | AB4: 45864 | AC4: 45865 | AD4: 45866 | AE4: 45867 | AF4: 45868 | AG4: 45869 | AU4: Операторы | AY4: З/П | BQ4: 45 000р.
B5: Обработано лидов | C5: 78 | D5: 112 | E5: 66 | F5: 68 | G5: 105 | H5: 76 | I5: 66 | J5: 47 | K5: 53 | L5: 78 | M5: 73 | N5: 80 | O5: 45 | P5: 44 | Q5: 35 | R5: 20 | S5: 98 | T5: 77 | U5: 80 | V5: 111 | W5: 68 | X5: 38 | Y5: 64 | Z5: 55 | AA5: 53 | AB5: 45 | AC5: 55 | AD5: 37 | AE5: 45 | AF5: 49 | AG5: 50 | AU5: Алексей Пряхин | AY5: 27 150р.
B6: Некачественных лидов | C6: 31 | D6: 51 | E6: 48 | F6: 64 | G6: 59 | H6: 66 | I6: 25 | J6: 21 | K6: 43 | L6: 33 | M6: 34 | N6: 36 | O6: 19 | P6: 21 | Q6: 16 | R6: 4 | S6: 52 | T6: 50 | U6: 32 | V6: 42 | W6: 24 | X6: 16 | Y6: 22 | Z6: 40 | AA6: 31 | AB6: 22 | AC6: 25 | AD6: 19 | AE6: 23 | AF6: 28 | AG6: 22 | AU6: Алексей Конобеев | AY6: 55 250р.
B7: Качественных лидов | C7: 47 | D7: 47 | E7: 18 | F7: 4 | G7: 46 | H7: 10 | I7: 41 | J7: 26 | K7: 10 | L7: 45 | M7: 39 | N7: 44 | O7: 26 | P7: 23 | Q7: 14 | R7: 14 | S7: 40 | T7: 23 | U7: 28 | V7: 58 | W7: 37 | X7: 22 | Y7: 42 | Z7: 15 | AA7: 22 | AB7: 23 | AC7: 30 | AD7: 18 | AE7: 22 | AF7: 21 | AG7: 28 | AU7: Алексей Лукин | AY7: 17 600р.
B8: Назначено встреч | C8: 20 | D8: 16 | E8: 16 | F8: 3 | G8: 15 | H8: 12 | I8: 13 | J8: 15 | K8: 10 | L8: 10 | M8: 12 | N8: 7 | O8: 13 | P8: 6 | Q8: 11 | R8: 6 | S8: 12 | T8: 12 | U8: 20 | V8: 18 | W8: 16 | X8: 5 | Y8: 7 | Z8: 4 | AA8: 7 | AB8: 11 | AC8: 8 | AD8: 11 | AE8: 7 | AF8: 7 | AG8: 16 | AU8: Оператор №5 | AY8: 17 600р.
B9: Визитов состоялось | C9: 5 | D9: 4 | E9: 13 | F9: 10 | G9: 13 | H9: 6 | I9: 13 | J9: 11 | K9: 11 | L9: 4 | M9: 12 | N9: 9 | O9: 16 | P9: 16 | Q9: 16 | R9: 16 | S9: 15 | T9: 20 | U9: 33 | V9: 11 | W9: 11 | X9: 5 | Y9: 2 | Z9: 4 | AA9: 6 | AB9: 8 | AC9: 8 | AD9: 6 | AE9: 13 | AF9: 10 | AG9: 11 | AU9: Оператор №6 | AY9: 17 600р.
B10: Визиты с улицы | C10: 2 | D10: - | E10: 2 | F10: 1 | G10: 1 | H10: 0 | I10: 0 | J10: 1 | K10: 0 | L10: 1 | M10: 1 | N10: 0 | O10: 2 | P10: 0 | Q10: 1 | R10: 0 | S10: 3 | T10: 2 | U10: 1 | V10: 0 | W10: 1 | X10: 0 | Y10: 2 | Z10: 2 | AA10: 1 | AB10: 1 | AC10: 1 | AD10: 1 | AE10: 1 | AF10: 0 | AG10: 0 | AU10: Оператор №7 | AY10: 17 600р.
AU11: Оператор №8 | AY11: 17 600р.
AU12: Оператор №9 | AY12: 17 600р.
B13: Целевые показатели | AU13: Оператор №10 | AY13: 17 600р.
B14: Конверсия лид-назначение | C14: 0.5
B15: Конверсия лид-визит | C15: 0.25
B16: Конверсия назначение-визит | C16: 0.5
B17: Доля квал. лидов | C17: 0.8
