Workbook
Name asm_OPEX: 'Базовый ОПиУ'!$D$17
Name base_GMVP: 'Базовый ОПиУ'!$D$12
Name base_GP: 'Базовый ОПиУ'!$D$16
Name base_OTHER: 'Базовый ОПиУ'!$D$14
Name base_PROFIT: 'Базовый ОПиУ'!$D$18
Name in_CANCEL: 'Исходные данные'!$C$17
Name in_CHECK: 'Исходные данные'!$C$9
Name in_COMPLAINT: 'Исходные данные'!$C$19
Name in_CONV: 'Исходные данные'!$C$13
Name in_CPA: 'Исходные данные'!$C$20
Name in_CR: 'Исходные данные'!$C$22
Name in_DELIVMIN: 'Исходные данные'!$C$16
Name in_FREQ: 'Исходные данные'!$C$7
Name in_GMPCT: 'Исходные данные'!$C$11
Name in_MAU: 'Исходные данные'!$C$6
Name in_NEWUSERS: 'Исходные данные'!$C$12
Name in_NPS: 'Исходные данные'!$C$18
Name in_ONTIME: 'Исходные данные'!$C$15
Name in_ORDERS: 'Исходные данные'!$C$8
Name in_ORGANIC: 'Исходные данные'!$C$21
Name in_RET: 'Исходные данные'!$C$14
Name in_REV: 'Исходные данные'!$C$10

Sheet Исходные данные
B2: Исходные данные брифа TechGourmet
B5: Показатель | C5: Значение | D5: Единица
B6: Активные пользователи (MAU) | C6: 100000 | D6: пользователей/мес
B7: Frequency (заказов на пользователя в месяц) | C7: 1.2 | D7: заказов/мес
B8: Заказы в месяц | C8: 120000 | D8: заказов/мес
B9: Средний чек | C9: 1400 | D9: руб.
B10: Месячная выручка | C10: 180000000 | D10: руб./мес
B11: Gross Margin (доля выручки) | C11: 0.18 | D11: доля
B12: Новые пользователи в месяц | C12: 12000 | D12: пользователей/мес
B13: Конверсия регистрация -> первая покупка | C13: 0.1 | D13: доля
B14: Месячный Retention Rate | C14: 0.32 | D14: доля
B15: Доля заказов, доставленных вовремя | C15: 0.89 | D15: доля
B16: Среднее время доставки | C16: 48 | D16: минут
B17: Доля отменённых заказов | C17: 0.06 | D17: доля
... B22: Conversion Rate на главной странице | C22: 0.15 | D22: доля

Sheet Базовый ОПиУ
B2: Базовый упрощённый ОПиУ TechGourmet (месяц/год)
B3: driver-based модель "снизу вверх", денежные потоки - в млн руб.
B5: Статья | C5: Формула | D5: Месяц | E5: Год
B6: Активные клиенты, шт | C6: перенос из брифа | D6: =in_MAU -> 100000
B7: Frequency, заказов/мес | C7: перенос из брифа | D7: =in_FREQ -> 1.2
B8: Заказы, шт/мес | C8: клиенты * frequency | D8: =D6*D7 -> 120000
B9: Средний чек, руб. | C9: перенос из брифа | D9: =in_CHECK -> 1400
B10: GMV (заказы * чек), млн руб./мес | C10: заказы * чек/1 000 000 | D10: =D8*D9/1000000 -> 168
B11: Выручка и прибыль
B12: GMV, млн руб. | C12: перенос расчёта выше | D12: =D10 -> 168 | E12: =D12*12 -> 2016
B13: Выручка по брифу, млн руб. | C13: перенос из брифа | D13: =in_REV/1000000 -> 180 | E13: =D13*12 -> 2160
B14: Прочая выручка, млн руб. | C14: выручка по брифу − GMV | D14: =D13-D12 -> 12 | E14: =D14*12 -> 144
B15: Выручка, млн руб. | C15: GMV + прочая выручка | D15: =D12+D14 -> 180 | E15: =D15*12 -> 2160
B16: Валовая прибыль, млн руб. | C16: выручка * Gross Margin | D16: =D15*in_GMPCT -> 32.4 | E16: =D16*12 -> 388.8
B17: Постоянные OPEX, млн руб. | C17: допущение (синий), обоснование ниже | D17: 22.4 | E17: =D17*12 -> 268.8
B18: Операционная прибыль, млн руб. | C18: валовая прибыль − OPEX | D18: =D16-D17 -> 10 | E18: =D18*12 -> 120
B19: Маржинальность прибыли | C19: прибыль/выручка | D19: =D18/D15 -> 0.055555556
B20: Обоснование допущения по OPEX (22,4 млн руб./мес ~= 12,4% выручки): в брифе нет структуры расходов, поэтому постоянные OPEX (офис, разработка, поддержка, базовый маркетинг, IT) заданы допущением так, чтобы операционная прибыль составляла 10 млн руб./мес (5,6% выручки) - правдоподобный уровень для маркетплейса доставки еды после масштабирования. Допущение подлежит уточнению с финансовой командой; целевые значения (+300%) не зависят от его уровня: при любом OPEX цель формулируется через рост валовой прибыли на +92,6%.

Sheet Цель и рычаги
B2: Цель +300% и анализ рычагов роста прибыли
B4: Блок 1. Целевые значения
B5: Базовая операционная прибыль, млн руб./мес | C5: =base_PROFIT -> 10
B6: Целевая прибыль (*4, +300%), млн руб./мес | C6: =C5*4 -> 40
B7: Требуемая валовая прибыль, млн руб./мес | C7: =C6+asm_OPEX -> 62.4
B8: Требуемый рост валовой прибыли | C8: =C7/base_GP-1 -> 0.92592593
B10: Блок 2. Требуемое изменение каждого рычага ПО ОТДЕЛЬНОСТИ (остальные на базе)
B11: Рычаг | C11: База | D11: Требуемое значение | E11: Изменение | F11: Оценка реалистичности
B12: Frequency, заказов/мес | C12: =in_FREQ -> 1.2 | D12: =in_FREQ*('Цель и рычаги'!$C$7/in_GMPCT-base_OTHER)/base_GMVP -> 2.3904762 | E12: =D12/C12-1 -> 0.99206349 | F12: 1,2 -> 2,39 заказа/мес - физически невозможно без смены модели
B13: Средний чек, руб. | C13: =in_CHECK -> 1400 | D13: =in_CHECK*('Цель и рычаги'!$C$7/in_GMPCT-base_OTHER)/base_GMVP -> 2788.8889 | E13: =D13/C13-1 -> 0.99206349 | F13: 1 400 -> 2 788 руб. (+99%) - нереально на рынке без скидочных войн
B14: Активные клиенты, шт | C14: =in_MAU -> 100000 | D14: =in_MAU*('Цель и рычаги'!$C$7/in_GMPCT-base_OTHER)/base_GMVP -> 199206.35 | E14: =D14/C14-1 -> 0.99206349 | F14: 100 000 -> 199 167 (+99%) - только платным привлечением при LTV/CAC ~= 0,4; см. "Анти-сценарий"
B15: Gross Margin, % | C15: =in_GMPCT -> 0.18 | D15: =C7/(base_GMVP+base_OTHER) -> 0.34666667 | E15: =D15/C15-1 -> 0.92592593 | F15: 18% -> 34,7% (+16,7 п.п.) - за один год недостижимо
B16: Прочая выручка, млн руб./мес | C16: =base_OTHER -> 12 | D16: =C7/in_GMPCT-base_GMVP -> 178.66667 | E16: =D16/C16-1 -> 13.888889 | F16: 12 -> 178,7 млн руб. (*15) - не является продуктовым рычагом
B18: Вывод: ни один рычаг в отдельности не даёт +300% реалистично - цель достигается только комбинацией рычагов (см. лист "Сценарий стратегии").
B20: Блок 3. Эластичность: эффект роста рычага на 10% (остальные на базе)
B21: Рычаг (+10%) | C21: Дельта валовой прибыли, млн/мес | D21: Дельта прибыли, млн/мес | E21: Дельта прибыли, % | F21: Эластичность (Дельта% прибыли/10%)
B22: Frequency *1,10 | C22: =0.1*base_GMVP*in_GMPCT -> 3.024 | D22: =C22 -> 3.024 | E22: =D22/base_PROFIT -> 0.3024 | F22: =E22/0.1 -> 3.024
B23: Средний чек *1,10 | C23: =0.1*base_GMVP*in_GMPCT -> 3.024 | D23: =C23 -> 3.024 | E23: =D23/base_PROFIT -> 0.3024 | F23: =E23/0.1 -> 3.024
B24: Активные клиенты *1,10 | C24: =0.1*base_GMVP*in_GMPCT -> 3.024 | D24: =C24 -> 3.024 | E24: =D24/base_PROFIT -> 0.3024 | F24: =E24/0.1 -> 3.024
B25: Gross Margin *1,10 (+1,8 п.п.) | C25: =0.1*in_GMPCT*(base_GMVP+base_OTHER) -> 3.24 | D25: =C25 -> 3.24 | E25: =D25/base_PROFIT -> 0.324 | F25: =E25/0.1 -> 3.24
B26: Прочая выручка *1,10 | C26: =0.1*base_OTHER*in_GMPCT -> 0.216 | D26: =C26 -> 0.216 | E26: =D26/base_PROFIT -> 0.0216 | F26: =E26/0.1 -> 0.216
B28: Эластичность клиенто-зависимых рычагов (frequency, чек, база) одинакова - все действуют через GMV; маржа эластичнее (действует на всю выручку), но её рост ограничен операционно. Численно цель требует произведения факторов ~= 1,93 к валовой прибыли.

Sheet Сценарий стратегии
B2: Сценарий "повторные заказы"
B3: Драйверы нарастают равномерно по кварталам (линейная рампа). Целевые значения (синие) выбраны по стратегии: главный вклад - frequency и маржа, умеренный - база и чек.
B5: Драйверы (значения на конец квартала)
B6: Драйвер | C6: Q0 (база) | D6: Q1 | E6: Q2 | F6: Q3 | G6: Q4 (цель)
B7: Frequency, заказов/мес | C7: =in_FREQ -> 1.2 | D7: =C$7+($G$7-C$7)*1/4 -> 1.32 | E7: =C$7+($G$7-C$7)*2/4 -> 1.44 | F7: =C$7+($G$7-C$7)*3/4 -> 1.56 | G7: 1.68
B8: Средний чек, руб. | C8: =in_CHECK -> 1400 | D8: =C$8+($G$8-C$8)*1/4 -> 1417.5 | E8: =C$8+($G$8-C$8)*2/4 -> 1435 | F8: =C$8+($G$8-C$8)*3/4 -> 1452.5 | G8: 1470
B9: Gross Margin, % | C9: =in_GMPCT -> 0.18 | D9: =C$9+($G$9-C$9)*1/4 -> 0.19 | E9: =C$9+($G$9-C$9)*2/4 -> 0.2 | F9: =C$9+($G$9-C$9)*3/4 -> 0.21 | G9: 0.22
B10: Активные клиенты, шт | C10: =in_MAU -> 100000 | D10: =C$10+($G$10-C$10)*1/4 -> 103000 | E10: =C$10+($G$10-C$10)*2/4 -> 106000 | F10: =C$10+($G$10-C$10)*3/4 -> 109000 | G10: 112000
B12: Поквартальный ОПиУ (средние драйверы квартала = середина интервала)
B13: Статья | D13: Q1 | E13: Q2 | F13: Q3 | G13: Q4 | H13: Год
B14: Frequency (среднее) | D14: =(D7+C7)/2 -> 1.26 | E14: =(E7+D7)/2 -> 1.38 | F14: =(F7+E7)/2 -> 1.5 | G14: =(G7+F7)/2 -> 1.62
B15: Средний чек (среднее) | D15: =(D8+C8)/2 -> 1408.75 | E15: =(E8+D8)/2 -> 1426.25 | F15: =(F8+E8)/2 -> 1443.75 | G15: =(G8+F8)/2 -> 1461.25
B16: Gross Margin (среднее) | D16: =(D9+C9)/2 -> 0.185 | E16: =(E9+D9)/2 -> 0.195 | F16: =(F9+E9)/2 -> 0.205 | G16: =(G9+F9)/2 -> 0.215
B17: Активные клиенты (среднее) | D17: =(D10+C10)/2 -> 101500 | E17: =(E10+D10)/2 -> 104500 | F17: =(F10+E10)/2 -> 107500 | G17: =(G10+F10)/2 -> 110500
B18: Заказы/мес, шт | D18: =D17*D14 -> 127890 | E18: =E17*E14 -> 144210 | F18: =F17*F14 -> 161250 | G18: =G17*G14 -> 179010
B19: GMV/мес, млн руб. | D19: =D18*D15/1000000 -> 180.16504 | E19: =E18*E15/1000000 -> 205.67951 | F19: =F18*F15/1000000 -> 232.80469 | G19: =G18*G15/1000000 -> 261.57836
B20: Выручка/мес, млн руб. | D20: =D19+base_OTHER -> 192.16504 | E20: =E19+base_OTHER -> 217.67951 | F20: =F19+base_OTHER -> 244.80469 | G20: =G19+base_OTHER -> 273.57836 | H20: =SUM(D20:G20) -> 928.2276
B21: Валовая прибыль/мес, млн руб. | D21: =D20*D16 -> 35.550532 | E21: =E20*E16 -> 42.447505 | F21: =F20*F16 -> 50.184961 | G21: =G20*G16 -> 58.819348 | H21: =SUM(D21:G21) -> 187.00235
B22: Операционная прибыль/мес, млн руб. | D22: =D21-asm_OPEX -> 13.150532 | E22: =E21-asm_OPEX -> 20.047505 | F22: =F21-asm_OPEX -> 27.784961 | G22: =G21-asm_OPEX -> 36.419348 | H22: =H23/12 -> 24.350586
B23: Операционная прибыль за квартал, млн руб. | D23: =D22*3 -> 39.451596 | E23: =E22*3 -> 60.142515 | F23: =F22*3 -> 83.354883 | G23: =G22*3 -> 109.25804 | H23: =SUM(D23:G23) -> 292.20704
B25: Проверка цели (run-rate на выходе года, по целевым значениям драйверов Q4):
B26: Прибыль/мес по целевым драйверам, млн руб. | D26: =(G10*G7*G8/1000000+base_OTHER)*G9-asm_OPEX -> 41.090944
B27: Прирост к базе (цель >= +300%) | D27: =D26/base_PROFIT-1 -> 3.1090944 | E27: цель достигнута
B30: Мост роста прибыли (месяц, выход на целевые значения; накопительное применение рычагов)
B31: Шаг | C31: Прибыль, млн/мес | D31: Прирост шага, млн/мес
B32: База | C32: =(base_GMVP+base_OTHER)*in_GMPCT-asm_OPEX -> 10
B33: + Frequency *1,40 | C33: =(base_GMVP*1.4+base_OTHER)*in_GMPCT-asm_OPEX -> 22.096 | D33: =C33-C32 -> 12.096
B34: + Средний чек *1,05 | C34: =(base_GMVP*1.4*1.05+base_OTHER)*in_GMPCT-asm_OPEX -> 24.2128 | D34: =C34-C33 -> 2.1168
B35: + Gross Margin -> 22% | C35: =(base_GMVP*1.4*1.05+base_OTHER)*0.22-asm_OPEX -> 34.5712 | D35: =C35-C34 -> 10.3584
B36: + Клиенты *1,12 | C36: =(base_GMVP*1.4*1.05*1.12+base_OTHER)*0.22-asm_OPEX -> 41.090944 | D36: =C36-C35 -> 6.519744

Sheet Юнит-экономика
B2: Почему привлечение не может быть главным рычагом
B4: 1. LTV и CAC (текущие значения)
B5: Средняя lifetime клиента, мес | C5: =1/(1-in_RET) -> 1.4705882 | D5: при retention 32%/мес
B6: Заказов за lifetime | C6: =C5*in_FREQ -> 1.7647059 | D6: lifetime * frequency
B7: Средний доход с заказа, руб. | C7: =in_CHECK+base_OTHER*1000000/in_ORDERS -> 1500 | D7: чек + прочая выручка на заказ (100 руб.)
B8: LTV (валовая прибыль), руб. | C8: =C6*C7*in_GMPCT -> 476.47059 | D8: заказы * доход * маржа
B9: CAC (CPA), руб. | C9: =in_CPA -> 1200 | D9: из брифа
B10: LTV/CAC | C10: =C8/C9 -> 0.39705882 | D10: бенчмарк зрелого бизнеса >= 3:1 (McKinsey)
B11: Окупаемость CAC из GP, мес | C11: =C9/(in_FREQ*C7*in_GMPCT) -> 3.7037037 | D11: средний срок жизни клиента - 1,47 мес < 3,7 мес: не окупается
B13: 2. Чувствительность LTV/CAC к retention и frequency
B14: Retention | C14: Lifetime, мес | D14: LTV, руб. (F=1,2) | E14: LTV/CAC (F=1,2) | F14: LTV, руб. (F=1,68) | G14: LTV/CAC (F=1,68)
B15: 0.32 | C15: =1/(1-B15) -> 1.4705882 | D15: =C15*in_FREQ*$C$7*in_GMPCT -> 476.47059 | E15: =D15/in_CPA -> 0.39705882 | F15: =C15*1.68*$C$7*in_GMPCT -> 667.05882 | G15: =F15/in_CPA -> 0.55588235
B16: 0.35 | C16: =1/(1-B16) -> 1.5384615 | D16: =C16*in_FREQ*$C$7*in_GMPCT -> 498.46154 | E16: =D16/in_CPA -> 0.41538462 | F16: =C16*1.68*$C$7*in_GMPCT -> 697.84615 | G16: =F16/in_CPA -> 0.58153846
B17: 0.4 | C17: =1/(1-B17) -> 1.6666667 | D17: =C17*in_FREQ*$C$7*in_GMPCT -> 540 | E17: =D17/in_CPA -> 0.45 | F17: =C17*1.68*$C$7*in_GMPCT -> 756 | G17: =F17/in_CPA -> 0.63
B18: 0.45 | C18: =1/(1-B18) -> 1.8181818 | D18: =C18*in_FREQ*$C$7*in_GMPCT -> 589.09091 | E18: =D18/in_CPA -> 0.49090909 | F18: =C18*1.68*$C$7*in_GMPCT -> 824.72727 | G18: =F18/in_CPA -> 0.68727273
B19: 0.5 | C19: =1/(1-B19) -> 2 | D19: =C19*in_FREQ*$C$7*in_GMPCT -> 648 | E19: =D19/in_CPA -> 0.54 | F19: =C19*1.68*$C$7*in_GMPCT -> 907.2 | G19: =F19/in_CPA -> 0.756
B21: Вывод: даже при retention 50% и frequency 1,68 LTV/CAC ~= 0,76 - платное привлечение по CPA 1 200 руб. разрушает стоимость. Параллельно нужно снижать CAC (рост органики с 15%, реферальные механики) до ~500 руб., тогда LTV/CAC при целевых метриках превысит 1,9.
B23: Почему рост через привлечение противоречит стратегии
B24: Клиентская база для +300% только привлечением, шт | C24: ='Цель и рычаги'!D14 -> 199206.35 | D24: тот же фактор 1,99, что и для frequency/чека
B25: Gross-привлечения (замещение оттока 68%/мес + net-рост), шт/мес | C25: =(1-in_RET)*(in_MAU+C24)/2+(C24-in_MAU)/12 -> 109997.35 | D25: оценка снизу: реактивации не учтены
B26: Маркетинговые затраты, млн руб./мес | C26: =C25*in_CPA/1000000 -> 131.99683 | D26: по CPA 1 200 руб. из брифа
B27: Прибыль после маркетинга, млн руб./мес | C27: ='Цель и рычаги'!C6-C26 -> -91.996825 | D27: убыток: привлечение "в вакууме" даёт цель, в реальности - нет
B29: Демпинг (GM −3 п.п.): | C29: 0.15 | D29: =(base_GMVP+base_OTHER)*C29-asm_OPEX -> 4.6 | E29: прибыль при демпинге, млн руб./мес (−54%)
