Workbook

Sheet Инвестору
B2: Общие условия | G2: Результаты
B4: Вложения инвестора | C4: 10000000 | G4: Окупаемость | J4: =MIN(26:26) -> 15 | K4: месяцев
B5: Доля инвестора | C5: 0.7 | D5: до окупаемости | G5: Доход за 1 год | I5: =-SUM(F24:N24) -> 6206332.5 | K5: рублей
C6: 0.5 | D6: после окупаемости | G6: Доход за 2 год | I6: =-SUM(O24:Z24) -> 14485502 | K6: рублей
B7: Открываем точек | C7: 10 | G7: Доход за 3 год | I7: =-SUM(AA24:AL24) -> 15148250 | K7: рублей
B8: Расходы на УК в месяц, рублей | C8: 750000 | G8: Итого за 3 года | I8: =SUM(I5:J7) -> 35840085 | K8: рублей
G9: ROI за 3 года | J9: =(I8-C4)/C4 -> 2.5840085
B11: Отчет о движении денег
B13: Месяц | C13: 1 | D13: 2 | E13: 3 | F13: 4 | G13: 5 | H13: 6 | I13: 7 | J13: 8 | K13: 9 | L13: 10 | M13: 11 | N13: 12 | O13: 13 | P13: 14 | Q13: 15 | R13: 16 | S13: 17 | T13: 18 | U13: 19 | V13: 20 | W13: 21 | X13: 22 | Y13: 23 | Z13: 24 | AA13: 25 | AB13: 26 | AC13: 27 | AD13: 28 | AE13: 29 | AF13: 30 | AG13: 31 | AH13: 32 | AI13: 33 | AJ13: 34 | AK13: 35 | AL13: 36
B14: Остаток денег на начало месяца | C14: 0 | D14: =C20 -> 1240000 | E14: =D20 -> 490000 | F14: =E20 -> 70561.333 | G14: =F20 -> -48027.333 | H14: =G20 -> 144101.88 | I14: =H20 -> 288179.33 | J14: =I20 -> 779831.19 | K14: =J20 -> 1462649 | ... AL14: =AK20 -> 44134605
B15: Операционная прибыль с точек [1] | E15: =Инвестору!J78*$C$7 -> 330561.33 | F15: =Инвестору!K78*$C$7 -> 631411.33 | G15: =Инвестору!L78*$C$7 -> 942129.21 | H15: =Инвестору!M78*$C$7 -> 894077.45 | I15: =Инвестору!N78*$C$7 -> 1241651.9 | J15: =Инвестору!O78*$C$7 -> 1432817.8 | K15: =Инвестору!P78*$C$7 -> 1633542 | L15: =Инвестору!Q78*$C$7 -> 1759998.3 | ... O15: =Инвестору!T78*$C$7 -> 2162587.8 | P15: =O15*101% -> 2184213.7 | Q15: =P15*101% -> 2206055.9 | R15: =Q15*101% -> 2228116.4 | S15: =R15*101% -> 2250397.6 | T15: =S15*101% -> 2272901.6 | U15: =T15*101% -> 2295630.6 | V15: =U15*101% -> 2318586.9 | W15: =V15*101% -> 2341772.7 | ... AL15: =AK15*101% -> 2718725.5
B16: Входящие инвестиции | C16: =C4 -> 10000000
B17: Вложения в открытие 10 точек | C17: =-Инвестору!E78*10 -> -8010000
B18: Расходы на УК | C18: =-$C$8 -> -750000 | D18: =-$C$8 -> -750000 | E18: =-$C$8 -> -750000 | F18: =-$C$8 -> -750000 | G18: =-$C$8 -> -750000 | H18: =-$C$8 -> -750000 | I18: =-$C$8 -> -750000 | J18: =-$C$8 -> -750000 | ... AL18: =-$C$8 -> -750000
B19: Возврат средств инвестору [2] | F19: =IF(E25>$C$4,-D15*$C$6,-D15*$C$5) -> 0 | G19: =IF(F25>$C$4,-E15*$C$6,-E15*$C$5) -> -231392.93 | H19: =IF(G25>$C$4,-F15*$C$6,-F15*$C$5) -> -441987.93 | I19: =IF(H25>$C$4,-G15*$C$6,-G15*$C$5) -> -659490.45 | J19: =IF(I25>$C$4,-H15*$C$6,-H15*$C$5) -> -625854.22 | K19: =IF(J25>$C$4,-I15*$C$6,-I15*$C$5) -> -869156.3 | L19: =IF(K25>$C$4,-J15*$C$6,-J15*$C$5) -> -1002972.5 | M19: =IF(L25>$C$4,-K15*$C$6,-K15*$C$5) -> -1143479.4 | ... AL19: =IF(AK25>$C$4,-AJ15*$C$6,-AJ15*$C$5) -> -1332577.9
B20: Остаток денег на конец месяца | C20: =SUM(C14:C18) -> 1240000 | D20: =SUM(D14:D18) -> 490000 | E20: =SUM(E14:E18) -> 70561.333 | F20: =SUM(F14:F18) -> -48027.333 | G20: =SUM(G14:G18) -> 144101.88 | H20: =SUM(H14:H18) -> 288179.33 | I20: =SUM(I14:I18) -> 779831.19 | J20: =SUM(J14:J18) -> 1462649 | ... AL20: =SUM(AL14:AL18) -> 46103330
B22: Инвестору
B23: Вложения | C23: =C16 -> 10000000
B24: Возврат средств | D24: =D19 -> 0 | E24: =E19 -> 0 | F24: =F19 -> 0 | G24: =G19 -> -231392.93 | H24: =H19 -> -441987.93 | I24: =I19 -> -659490.45 | J24: =J19 -> -625854.22 | K24: =K19 -> -869156.3 | ... AL24: =AL19 -> -1332577.9
B25: Возврат накопительно | E25: =D25-E24 -> 0 | F25: =E25-F24 -> 0 | G25: =F25-G24 -> 231392.93 | H25: =G25-H24 -> 673380.87 | I25: =H25-I24 -> 1332871.3 | J25: =I25-J24 -> 1958725.5 | K25: =J25-K24 -> 2827881.8 | L25: =K25-L24 -> 3830854.3 | ... AL25: =AK25-AL24 -> 35840085
B26: Окупаемость | E26: =IF(E25>$C$23,E13,"") | F26: =IF(F25>$C$23,F13,"") | G26: =IF(G25>$C$23,G13,"") | H26: =IF(H25>$C$23,H13,"") | I26: =IF(I25>$C$23,I13,"") | J26: =IF(J25>$C$23,J13,"") | K26: =IF(K25>$C$23,K13,"") | L26: =IF(L25>$C$23,L13,"") | ... AL26: =IF(AL25>$C$23,AL13,"") -> 36
B28: [1] для расчета используется «чистая прибыль» с вкладки «финплан 1 точка»
B29: Точки работают с 3-го месяца. Мы рассчитываем 2 месяца с запасом на поиск локаций, подготовку.
B30: После 12 места заложен рост прибыли 1% в месяц
B31: Рост продаж в первые 3 месяца для точки взят пессимистичный — 10% вместо 20% в базовом прогнозе
B33: [2] выплата доли средств инвестору выполняется через месяц, в котором получена прибыль
B34: Для того, чтобы не попадать в кассовый разрыв в момент роста
H41: Месяц | I41: 1 | J41: 2 | K41: 3 | L41: 4 | M41: 5 | N41: 6 | O41: 7 | P41: 8 | Q41: 9 | R41: 10 | S41: 11 | T41: 12
B43: ПОКАЗАТЕЛИ | H43: ВЫРУЧКА | I43: =I45 -> 0 | J43: =J45 -> 601700 | K43: =K45 -> 661870 | L43: =L45 -> 728057 | M43: =M45 -> 800862.7 | N43: =N45 -> 880948.97 | O43: =O45 -> 924996.42 | P43: =P45 -> 971246.24 | ... T43: =T45 -> 1093146.2
B45: Точка безубыточности (руб/мес) | E45: =(T63+T75+T76)/E50 -> 660628.63 | H45: Выручка от продаж | J45: =J46*J47 -> 601700 | K45: =K46*K47 -> 661870 | L45: =L46*L47 -> 728057 | M45: =M46*M47 -> 800862.7 | N45: =N46*N47 -> 880948.97 | O45: =O46*O47 -> 924996.42 | P45: =P46*P47 -> 971246.24 | Q45: =Q46*Q47 -> 1000383.6 | ... T45: =T46*T47 -> 1093146.2
B46: Точка безубыточности (руб/день) | E46: =E45/T46 -> 30028.574 | H46: Кол-во рабочих дней | J46: 22 | K46: =J46 -> 22 | L46: =K46 -> 22 | M46: =L46 -> 22 | N46: =M46 -> 22 | O46: =N46 -> 22 | P46: =O46 -> 22 | Q46: =P46 -> 22 | R46: =Q46 -> 22 | ... T46: =S46 -> 22
H47: Выручка в день | J47: =SUMPRODUCT($G$51:$G$58,J51:J58) -> 27350 | K47: =SUMPRODUCT($G$51:$G$58,K51:K58) -> 30085 | L47: =SUMPRODUCT($G$51:$G$58,L51:L58) -> 33093.5 | M47: =SUMPRODUCT($G$51:$G$58,M51:M58) -> 36402.85 | N47: =SUMPRODUCT($G$51:$G$58,N51:N58) -> 40043.135 | O47: =SUMPRODUCT($G$51:$G$58,O51:O58) -> 42045.292 | P47: =SUMPRODUCT($G$51:$G$58,P51:P58) -> 44147.556 | Q47: =SUMPRODUCT($G$51:$G$58,Q51:Q58) -> 45471.983 | ... T47: =SUMPRODUCT($G$51:$G$58,T51:T58) -> 49688.464
H48: Чеков в день (ср чек 220р) | J48: =J47/220 -> 124.31818 | K48: =K47/220 -> 136.75 | L48: =L47/220 -> 150.425 | M48: =M47/220 -> 165.4675 | N48: =N47/220 -> 182.01425 | O48: =O47/220 -> 191.11496 | P48: =P47/220 -> 200.67071 | Q48: =Q47/220 -> 206.69083 | ... T48: =T47/220 -> 225.85665
G49: 0.1 | H49: Рост продаж в месяц | K49: =G49 -> 0.1 | L49: =K49 -> 0.1 | M49: =L49 -> 0.1 | N49: =M49 -> 0.1 | O49: 0.05 | P49: =O49 -> 0.05 | Q49: 0.03 | R49: =Q49 -> 0.03 | S49: =R49 -> 0.03 | T49: =S49 -> 0.03
B50: Маржинальность средняя | E50: =T61/T45 -> 0.5 | G50: Цена | H50: Наименование
G51: 100 | H51: КОФЕ | J51: 50 | K51: =J51*(100%+K$49) -> 55 | L51: =K51*(100%+L$49) -> 60.5 | M51: =L51*(100%+M$49) -> 66.55 | N51: =M51*(100%+N$49) -> 73.205 | O51: =N51*(100%+O$49) -> 76.86525 | P51: =O51*(100%+P$49) -> 80.708513 | Q51: =P51*(100%+Q$49) -> 83.129768 | R51: =Q51*(100%+R$49) -> 85.623661 | ... T51: =S51*(100%+T$49) -> 90.838142
B52: Итого вложения всего (с запасом): | E52: =E78 -> 801000 | G52: 180 | H52: ВТОРЫЕ БЛЮДА | J52: 70 | K52: =J52*(100%+K$49) -> 77 | L52: =K52*(100%+L$49) -> 84.7 | M52: =L52*(100%+M$49) -> 93.17 | N52: =M52*(100%+N$49) -> 102.487 | O52: =N52*(100%+O$49) -> 107.61135 | P52: =O52*(100%+P$49) -> 112.99192 | Q52: =P52*(100%+Q$49) -> 116.38168 | R52: =Q52*(100%+R$49) -> 119.87313 | ... T52: =S52*(100%+T$49) -> 127.1734
B53: Месяц окупаемости | E53: =MIN(I82:T82) -> 9 | G53: 120 | H53: ПЕРВЫЕ БЛЮДА | J53: 5 | K53: =J53*(100%+K$49) -> 5.5 | L53: =K53*(100%+L$49) -> 6.05 | M53: =L53*(100%+M$49) -> 6.655 | N53: =M53*(100%+N$49) -> 7.3205 | O53: =N53*(100%+O$49) -> 7.686525 | P53: =O53*(100%+P$49) -> 8.0708513 | Q53: =P53*(100%+Q$49) -> 8.3129768 | R53: =Q53*(100%+R$49) -> 8.5623661 | ... T53: =S53*(100%+T$49) -> 9.0838142
G54: 120 | H54: САЛАТЫ | J54: 5 | K54: =J54*(100%+K$49) -> 5.5 | L54: =K54*(100%+L$49) -> 6.05 | M54: =L54*(100%+M$49) -> 6.655 | N54: =M54*(100%+N$49) -> 7.3205 | O54: =N54*(100%+O$49) -> 7.686525 | P54: =O54*(100%+P$49) -> 8.0708513 | Q54: =P54*(100%+Q$49) -> 8.3129768 | R54: =Q54*(100%+R$49) -> 8.5623661 | ... T54: =S54*(100%+T$49) -> 9.0838142
G55: 120 | H55: ДЕСЕРТЫ/ЗАВТРАКИ | J55: 10 | K55: =J55*(100%+K$49) -> 11 | L55: =K55*(100%+L$49) -> 12.1 | M55: =L55*(100%+M$49) -> 13.31 | N55: =M55*(100%+N$49) -> 14.641 | O55: =N55*(100%+O$49) -> 15.37305 | P55: =O55*(100%+P$49) -> 16.141703 | Q55: =P55*(100%+Q$49) -> 16.625954 | R55: =Q55*(100%+R$49) -> 17.124732 | ... T55: =S55*(100%+T$49) -> 18.167628
B56: Прибыль за год | E56: =SUM(J78:T78) -> 1494343.1 | G56: 120 | H56: СЕНДВИЧИ | J56: 10 | K56: =J56*(100%+K$49) -> 11 | L56: =K56*(100%+L$49) -> 12.1 | M56: =L56*(100%+M$49) -> 13.31 | N56: =M56*(100%+N$49) -> 14.641 | O56: =N56*(100%+O$49) -> 15.37305 | P56: =O56*(100%+P$49) -> 16.141703 | Q56: =P56*(100%+Q$49) -> 16.625954 | R56: =Q56*(100%+R$49) -> 17.124732 | ... T56: =S56*(100%+T$49) -> 18.167628
B57: Доходность, % годовых | E57: =E56/E52 -> 1.8655969 | G57: 120 | H57: ФРУКТЫ, ЯГОДЫ, ОРЕШКИ | J57: 10 | K57: =J57*(100%+K$49) -> 11 | L57: =K57*(100%+L$49) -> 12.1 | M57: =L57*(100%+M$49) -> 13.31 | N57: =M57*(100%+N$49) -> 14.641 | O57: =N57*(100%+O$49) -> 15.37305 | P57: =O57*(100%+P$49) -> 16.141703 | Q57: =P57*(100%+Q$49) -> 16.625954 | R57: =Q57*(100%+R$49) -> 17.124732 | ... T57: =S57*(100%+T$49) -> 18.167628
G58: 990 | H58: ДОСТАВКА ПО РАЙОНУ ТОЧКИ ПРОДАЖ | J58: 5 | K58: =J58*(100%+K$49) -> 5.5 | L58: =K58*(100%+L$49) -> 6.05 | M58: =L58*(100%+M$49) -> 6.655 | N58: =M58*(100%+N$49) -> 7.3205 | O58: =N58*(100%+O$49) -> 7.686525 | P58: =O58*(100%+P$49) -> 8.0708513 | Q58: =P58*(100%+Q$49) -> 8.3129768 | R58: =Q58*(100%+R$49) -> 8.5623661 | ... T58: =S58*(100%+T$49) -> 9.0838142
B59: ИНВЕСТИЦИИ | G59: 0.5 | H59: Себестоимость сырья (вкл. списание, порча) | I59: =I45*$G$62 -> 0 | J59: =J45*$G$59 -> 300850 | K59: =K45*$G$59 -> 330935 | L59: =L45*$G$59 -> 364028.5 | M59: =M45*$G$59 -> 400431.35 | N59: =N45*$G$59 -> 440474.49 | O59: =O45*$G$59 -> 462498.21 | P59: =P45*$G$59 -> 485623.12 | Q59: =Q45*$G$59 -> 500191.81 | ... T59: =T45*$G$59 -> 546573.1
C60: кол-во | D60: цена | E60: стоимость
B61: КОНСТРУКЦИЯ/МЕБЕЛЬ | C61: 9 кв м | D61: 200000 | E61: 200000 | H61: ВАЛОВАЯ ПРИБЫЛЬ | I61: =I43-I59 -> 0 | J61: =J43-J59 -> 300850 | K61: =K43-K59 -> 330935 | L61: =L43-L59 -> 364028.5 | M61: =M43-M59 -> 400431.35 | N61: =N43-N59 -> 440474.49 | O61: =O43-O59 -> 462498.21 | P61: =P43-P59 -> 485623.12 | ... T61: =T43-T59 -> 546573.1
B62: ТВ | C62: 2 | D62: 15000 | E62: =C62*D62 -> 30000
B63: IIKO — аренда сервера | C63: 1 | D63: 6000 | E63: =C63*D63 -> 6000 | H63: Прочие расходы | I63: =SUM(I64:I72) -> 801000 | J63: =SUM(J64:J72) -> 244627.2 | K63: =SUM(K64:K72) -> 244627.2 | L63: =SUM(L64:L72) -> 246648.91 | M63: =SUM(M64:M72) -> 287856.94 | N63: =SUM(N64:N72) -> 293142.63 | O63: =SUM(O64:O72) -> 296049.76 | P63: =SUM(P64:P72) -> 299102.25 | ... T63: =SUM(T64:T72) -> 307147.65
B64: ХОЛОДИЛЬНИК | C64: 2 | D64: 75000 | E64: =C64*D64 -> 150000 | G64: 100000 | H64: Аренда торговой площади | J64: =G64 -> 100000 | K64: =J64 -> 100000 | L64: =K64 -> 100000 | M64: =L64 -> 100000 | N64: =M64 -> 100000 | O64: =N64 -> 100000 | P64: =O64 -> 100000 | Q64: =P64 -> 100000 | R64: =Q64 -> 100000 | ... T64: =S64 -> 100000
B65: СВЧ | C65: 2 | D65: 10000 | E65: =C65*D65 -> 20000 | G65: 35000 | H65: Зарплата повар/кассир 2/2 | J65: =G65*2 -> 70000 | K65: =J65 -> 70000 | L65: =J65 -> 70000 | M65: =L65 -> 70000 | N65: =M65 -> 70000 | O65: =N65 -> 70000 | P65: =O65 -> 70000 | Q65: =P65 -> 70000 | R65: =Q65 -> 70000 | S65: =R65 -> 70000 | T65: =S65 -> 70000
B66: ФОРМА ДЛЯ СОТРУДНИКОВ | C66: 4 | D66: 3750 | E66: =C66*D66 -> 15000 | G66: 25000 | H66: Лизинг кофемашина | J66: =G66 -> 25000 | K66: =J66 -> 25000 | L66: =K66 -> 25000 | M66: =L66 -> 25000 | N66: =M66 -> 25000 | O66: =N66 -> 25000 | P66: =O66 -> 25000 | Q66: =P66 -> 25000 | R66: =Q66 -> 25000 | ... T66: =S66 -> 25000
B67: ХОЗ. РАСХОДЫ | C67: 1 | D67: 10000 | E67: =C67*D67 -> 10000 | G67: 25000 | H67: Маркетинг/реклама/промо | J67: =G67 -> 25000 | K67: =J67 -> 25000 | L67: =K67 -> 25000 | M67: =L67 -> 25000 | N67: =M67 -> 25000 | O67: =N67 -> 25000 | P67: =O67 -> 25000 | Q67: =P67 -> 25000 | R67: =Q67 -> 25000 | ... T67: =S67 -> 25000
B68: ВИДЕОНАБЛЮДЕНИЕ | C68: 1 | D68: 10000 | E68: =C68*D68 -> 10000 | H68: Банковские расходы | J68: =J43*80%*2% -> 9627.2 | K68: =J68 -> 9627.2 | L68: =L43*80%*2% -> 11648.912 | M68: =M43*80%*2% -> 12813.803 | N68: =N43*80%*2% -> 14095.184 | O68: =O43*80%*2% -> 14799.943 | P68: =P43*80%*2% -> 15539.94 | Q68: =Q43*80%*2% -> 16006.138 | R68: =R43*80%*2% -> 16486.322 | S68: =S43*80%*2% -> 16980.912 | T68: =T43*80%*2% -> 17490.339
B69: ОНЛАЙН-КАССА | C69: 1 | D69: 30000 | E69: =C69*D69 -> 30000 | G69: 15000 | H69: Прочие расходы | J69: =G69 -> 15000 | K69: =J69 -> 15000 | L69: =K69 -> 15000 | M69: =L69 -> 15000 | N69: =M69 -> 15000 | O69: =N69 -> 15000 | P69: =O69 -> 15000 | Q69: =P69 -> 15000 | R69: =Q69 -> 15000 | ... T69: =S69 -> 15000
B70: ОБОРУДОВАНИЕ IIKO | C70: 1 | D70: 80000 | E70: =C70*D70 -> 80000 | G70: 0.05 | H70: Роялти % (с 4-го мес.) | M70: =M43*$G$70 -> 40043.135 | N70: =N43*$G$70 -> 44047.449 | O70: =O43*$G$70 -> 46249.821 | P70: =P43*$G$70 -> 48562.312 | Q70: =Q43*$G$70 -> 50019.181 | R70: =R43*$G$70 -> 51519.757 | S70: =S43*$G$70 -> 53065.349 | T70: =T43*$G$70 -> 54657.31
H71: Инвестиции на открытие точки | I71: =E78 -> 801000
B72: КОФЕМАШИНА FRESH MILK / ЛИЗИНГ | C72: 1 шт | D72: 0 | E72: =D72 -> 0
B73: АРЕНДА (первый + посл. мес.) | C73: 9 кв м | D73: 100000 | E73: 200000 | H73: ПРИБЫЛЬ (EBITDA) | I73: =I61-I63 -> -801000 | J73: =J61-J63 -> 56222.8 | K73: =K61-K63 -> 86307.8 | L73: =L61-L63 -> 117379.59 | M73: =M61-M63 -> 112574.41 | N73: =N61-N63 -> 147331.85 | O73: =O61-O63 -> 166448.45 | P73: =P61-P63 -> 186520.87 | ... T73: =T61-T63 -> 239425.45
B74: ПЕРВЫЙ ЗАКУП ПРОДУКТОВ | D74: 30000 | E74: =D74 -> 30000
B75: ПРОЧИЕ НЕПРЕДВИДЕННЫЕ | D75: 20000 | E75: =D75 -> 20000 | H75: Патент | J75: 15000 | K75: =J75 -> 15000 | L75: =K75 -> 15000 | M75: =L75 -> 15000 | N75: =M75 -> 15000 | O75: =N75 -> 15000 | P75: =O75 -> 15000 | Q75: =P75 -> 15000 | R75: =Q75 -> 15000 | ... T75: =S75 -> 15000
H76: Амортизация | J76: =(E61+E62+E64+E65+E68+E70+E72)/60 -> 8166.6667 | K76: =J76 -> 8166.6667 | L76: =K76 -> 8166.6667 | M76: =L76 -> 8166.6667 | N76: =M76 -> 8166.6667 | O76: =N76 -> 8166.6667 | P76: =O76 -> 8166.6667 | Q76: =P76 -> 8166.6667 | R76: =Q76 -> 8166.6667 | ... T76: =S76 -> 8166.6667
B78: ИТОГО ИНВЕСТИЦИИ | E78: =SUM(E61:E77) -> 801000 | H78: Чистая прибыль | I78: =I73-I75-I76 -> -801000 | J78: =J73-(J75+J76) -> 33056.133 | K78: =K73-(K75+K76) -> 63141.133 | L78: =L73-(L75+L76) -> 94212.921 | M78: =M73-(M75+M76) -> 89407.745 | N78: =N73-(N75+N76) -> 124165.19 | O78: =O73-(O75+O76) -> 143281.78 | P78: =P73-(P75+P76) -> 163354.2 | Q78: =Q73-(Q75+Q76) -> 175999.83 | ... T78: =T73-(T75+T76) -> 216258.78
H79: Рентабельность по чистой прибыли | J79: =IF(J78/J43<0,"",J78/J43) -> 0.054937898 | K79: =IF(K78/K43<0,"",K78/K43) -> 0.095398089 | L79: =IF(L78/L43<0,"",L78/L43) -> 0.12940322 | M79: =IF(M78/M43<0,"",M78/M43) -> 0.11163929 | N79: =IF(N78/N43<0,"",N78/N43) -> 0.14094481 | O79: =IF(O78/O43<0,"",O78/O43) -> 0.15489982 | P79: =IF(P78/P43<0,"",P78/P43) -> 0.16819031 | Q79: =IF(Q78/Q43<0,"",Q78/Q43) -> 0.17593233 | ... T79: =IF(T78/T43<0,"",T78/T43) -> 0.19783153
H81: Остаток денег на конец месяца | I81: =E52+I78 -> 0 | J81: =I81+J78 -> 33056.133 | K81: =J81+K78 -> 96197.267 | L81: =K81+L78 -> 190410.19 | M81: =L81+M78 -> 279817.93 | N81: =M81+N78 -> 403983.12 | O81: =N81+O78 -> 547264.9 | P81: =O81+P78 -> 710619.1 | Q81: =P81+Q78 -> 886618.93 | ... T81: =S81+T78 -> 1494343.1
H82: Окупаемость | J82: =IF(J81>$E$52,J41,"") | K82: =IF(K81>$E$52,K41,"") | L82: =IF(L81>$E$52,L41,"") | M82: =IF(M81>$E$52,M41,"") | N82: =IF(N81>$E$52,N41,"") | O82: =IF(O81>$E$52,O41,"") | P82: =IF(P81>$E$52,P41,"") | Q82: =IF(Q81>$E$52,Q41,"") -> 9 | ... T82: =IF(T81>$E$52,T41,"") -> 12
