Workbook

Sheet Финмодель индексация 1,5 года
B1: ОПиУ 2026-28 | C1: 2026 | O1: 2027 | AA1: 2028
B2: Название статьи | C2: Январь | D2: Февраль | E2: Март | F2: Апрель | G2: Май | H2: Июнь | I2: Июль | J2: Август | K2: Сентябрь | L2: Октябрь | M2: Ноябрь | N2: Декабрь | O2: Январь | P2: Февраль | Q2: Март | R2: Апрель | S2: Май | T2: Июнь | U2: Июль | V2: Август | W2: Сентябрь | X2: Октябрь | Y2: Ноябрь | Z2: Декабрь | AA2: Январь | AB2: Февраль | AC2: Март | AD2: Апрель | AE2: Май | AF2: Июнь | AG2: Июль | AH2: Август | AI2: Сентябрь | AJ2: Октябрь | AK2: Ноябрь | AL2: Декабрь
A4: 1.03 | B4: Выручка от реализации
A5: 3900 | B5: Выручка от комиссии | C5: =C20*C23*C24 -> 30057.504 | D5: =D20*D23*D24 -> 28198.205 | E5: =E20*E23*E24 -> 27039.854 | F5: =F20*F23*F24 -> 26375.031 | G5: =G20*G23*G24 -> 26058.598 | H5: =H20*H23*H24 -> 25989.016 | I5: =I20*I23*I24 -> 26095.269 | J5: =J20*J23*J24 -> 26327.705 | ... AL5: =AL20*AL23*AL24 -> 47366.215
B6: Выручка от подписки | C6: =C12*C25 -> 53539.5 | D6: =D12*D25 -> 50227.65 | E6: =E12*E25 -> 48164.355 | F6: =F12*F25 -> 46980.149 | G6: =G12*G25 -> 46416.506 | H6: =H12*H25 -> 46292.564 | I6: =I12*I25 -> 46481.825 | J6: =J12*J25 -> 46895.848 | ... AL6: =AL12*AL25 -> 95619.781
B7: Выручка от доставки | C7: =C20*C26 -> 110505.53 | D7: =D20*D26 -> 103669.87 | E7: =E20*E26 -> 99411.229 | F7: =F20*F26 -> 96967.027 | G7: =G20*G26 -> 95803.668 | H7: =H20*H26 -> 95547.853 | I7: =I20*I26 -> 95938.487 | J7: =J20*J26 -> 96793.031 | ... AL7: =AL20*AL26 -> 191877.03
B8: Общая выручка | C8: =SUM(C5:C7) -> 194102.53 | D8: =SUM(D5:D7) -> 182095.72 | E8: =SUM(E5:E7) -> 174615.44 | F8: =SUM(F5:F7) -> 170322.21 | G8: =SUM(G5:G7) -> 168278.77 | H8: =SUM(H5:H7) -> 167829.43 | I8: =SUM(I5:I7) -> 168515.58 | J8: =SUM(J5:J7) -> 170016.58 | ... AL8: =SUM(AL5:AL7) -> 334863.02
B9: Прирост выручки (% к прошлому месяцу) | C9: 1 | D9: =(D8/C8*100%)-100% -> -0.061858067 | E9: =(E8/D8*100%)-100% -> -0.041078868 | F9: =(F8/E8*100%)-100% -> -0.024586782 | G9: =(G8/F8*100%)-100% -> -0.011997462 | H9: =(H8/G8*100%)-100% -> -0.0026702084 | I9: =(I8/H8*100%)-100% -> 0.0040883667 | J9: =(J8/I8*100%)-100% -> 0.0089072081 | K9: =(K8/J8*100%)-100% -> 0.012303599 | ... AL9: =(AL8/AK8*100%)-100% -> 0.019999696
B11: Воронка продаж
A12: 0.02 | B12: Активная база клиентов | C12: =30594-30594*C14 -> 21415.8 | D12: =C12+D13-(C12*D14) -> 20091.06 | E12: =D12+E13-(D12*E14) -> 19265.742 | F12: =E12+F13-(E12*F14) -> 18792.059 | G12: =F12+G13-(F12*G14) -> 18566.602 | H12: =G12+H13-(G12*H14) -> 18517.026 | I12: =H12+I13-(H12*I14) -> 18592.73 | J12: =I12+J13-(I12*J14) -> 18758.339 | K12: =J12+K13-(J12*K14) -> 18989.134 | ... AL12: =AK12+AL13-(AK12*AL14) -> 31873.26
A13: 5000 | B13: Новые клиенты | C13: =$A$13 -> 5000 | D13: =C13+C13*$A$12 -> 5100 | E13: =D13+D13*$A$12 -> 5202 | F13: =E13+E13*$A$12 -> 5306.04 | G13: =F13+F13*$A$12 -> 5412.1608 | H13: =G13+G13*$A$12 -> 5520.404 | I13: =H13+H13*$A$12 -> 5630.8121 | J13: =I13+I13*$A$12 -> 5743.4283 | K13: =J13+J13*$A$12 -> 5858.2969 | ... AL13: =AK13+AK13*$A$12 -> 9999.4478
A14: 0.3 | B14: Отток | C14: =$A$14 -> 0.3 | D14: =$A$14 -> 0.3 | E14: =$A$14 -> 0.3 | F14: =$A$14 -> 0.3 | G14: =$A$14 -> 0.3 | H14: =$A$14 -> 0.3 | I14: =$A$14 -> 0.3 | J14: =$A$14 -> 0.3 | ... AL14: =$A$14 -> 0.3
A15: 495 | B15: База шеф-поваров | C15: =$A$15 -> 495 | D15: =C15+(D13/18)-(C15*15%) -> 704.08333 | E15: =D15+(E13/18)-(D15*15%) -> 887.47083 | F15: =E15+(F13/18)-(E15*15%) -> 1049.1302 | G15: =F15+(G13/18)-(F15*15%) -> 1192.4363 | H15: =G15+(H13/18)-(G15*15%) -> 1320.2599 | I15: =H15+(I13/18)-(H15*15%) -> 1435.0438 | J15: =I15+(J13/18)-(I15*15%) -> 1538.8666 | K15: =J15+(K13/18)-(J15*15%) -> 1633.4976 | ... AL15: =AK15+(AL13/18)-(AK15*15%) -> 3329.1822
B16: Заказчиков на одного повара | C16: =C12/C15 -> 43.264242 | D16: =D12/D15 -> 28.53506 | E16: =E12/E15 -> 21.708592 | F16: =F12/F15 -> 17.912037 | G16: =G12/G15 -> 15.57031 | H16: =H12/H15 -> 14.025288 | I16: =I12/I15 -> 12.95621 | J16: =J12/J15 -> 12.189711 | ... AL16: =AL12/AL15 -> 9.5739009
A17: 0.86 | B17: Процент успешных доставок | C17: =$A$17 -> 0.86 | D17: =$A$17 -> 0.86 | E17: =$A$17 -> 0.86 | F17: =$A$17 -> 0.86 | G17: =$A$17 -> 0.86 | H17: =$A$17 -> 0.86 | I17: =$A$17 -> 0.86 | J17: =$A$17 -> 0.86 | ... AL17: =$A$17 -> 0.86
A18: 2 | B18: Частотность созданных заказов | C18: =$A$18+RANDBETWEEN(-0.4, 0.1) -> 2 | D18: =$A$18+RANDBETWEEN(-0.4, 0.1) -> 2 | E18: =$A$18+RANDBETWEEN(-0.4, 0.1) -> 2 | F18: =$A$18+RANDBETWEEN(-0.4, 0.1) -> 2 | G18: =$A$18+RANDBETWEEN(-0.4, 0.1) -> 2 | H18: =$A$18+RANDBETWEEN(-0.4, 0.1) -> 2 | I18: =$A$18+RANDBETWEEN(-0.4, 0.1) -> 2 | J18: =$A$18+RANDBETWEEN(-0.4, 0.1) -> 2 | ... AL18: =$A$18+RANDBETWEEN(-0.4, 0.1) -> 2
B19: Созданные заказы | C19: =C12*C18 -> 42831.6 | D19: =D12*D18 -> 40182.12 | E19: =E12*E18 -> 38531.484 | F19: =F12*F18 -> 37584.119 | G19: =G12*G18 -> 37133.205 | H19: =H12*H18 -> 37034.051 | I19: =I12*I18 -> 37185.46 | J19: =J12*J18 -> 37516.679 | ... AL19: =AL12*AL18 -> 63746.521
B20: Выполненные заказы | C20: =C19*C17 -> 36835.176 | D20: =D19*D17 -> 34556.623 | E20: =E19*E17 -> 33137.076 | F20: =F19*F17 -> 32322.342 | G20: =G19*G17 -> 31934.556 | H20: =H19*H17 -> 31849.284 | I20: =I19*I17 -> 31979.496 | J20: =J19*J17 -> 32264.344 | ... AL20: =AL19*AL17 -> 54822.008
B22: Юнит-экономика
A23: 6.8 | B23: Средняя стоимость обеда | C23: =$A$23 -> 6.8 | D23: =$A$23 -> 6.8 | E23: =$A$23 -> 6.8 | F23: =$A$23 -> 6.8 | G23: =$A$23 -> 6.8 | H23: =$A$23 -> 6.8 | I23: =$A$23 -> 6.8 | J23: =$A$23 -> 6.8 | ... N23: =$A$23 -> 6.8 | O23: =$A$23+0.2 -> 7 | P23: =$A$23+0.2 -> 7 | Q23: =$A$23+0.2 -> 7 | R23: =$A$23+0.2 -> 7 | S23: =$A$23+0.2 -> 7 | T23: =$A$23+0.2 -> 7 | U23: =$A$23+0.2 -> 7 | V23: =$A$23+0.2 -> 7 | ... Z23: =$A$23+0.2 -> 7 | AA23: =$A$23+0.4 -> 7.2 | AB23: =$A$23+0.4 -> 7.2 | AC23: =$A$23+0.4 -> 7.2 | AD23: =$A$23+0.4 -> 7.2 | AE23: =$A$23+0.4 -> 7.2 | AF23: =$A$23+0.4 -> 7.2 | AG23: =$A$23+0.4 -> 7.2 | AH23: =$A$23+0.4 -> 7.2 | ... AL23: =$A$23+0.4 -> 7.2
A24: 0.12 | B24: Комиссия сервиса с шефов | C24: =$A$24 -> 0.12 | D24: =$A$24 -> 0.12 | E24: =$A$24 -> 0.12 | F24: =$A$24 -> 0.12 | G24: =$A$24 -> 0.12 | H24: =$A$24 -> 0.12 | I24: =$A$24 -> 0.12 | J24: =$A$24 -> 0.12 | ... AL24: =$A$24 -> 0.12
A25: 2.5 | B25: Стоимость подписки на сервис | C25: =$A$25 -> 2.5 | D25: =$A$25 -> 2.5 | E25: =$A$25 -> 2.5 | F25: =$A$25 -> 2.5 | G25: =$A$25 -> 2.5 | H25: =$A$25 -> 2.5 | I25: =$A$25 -> 2.5 | J25: =$A$25 -> 2.5 | ... T25: =$A$25 -> 2.5 | U25: =$A$25+0.5 -> 3 | V25: =$A$25+0.5 -> 3 | W25: =$A$25+0.5 -> 3 | X25: =$A$25+0.5 -> 3 | Y25: =$A$25+0.5 -> 3 | Z25: =$A$25+0.5 -> 3 | AA25: =$A$25+0.5 -> 3 | AB25: =$A$25+0.5 -> 3 | ... AL25: =$A$25+0.5 -> 3
A26: 3 | B26: Стоимость доставки | C26: =$A$26 -> 3 | D26: =$A$26 -> 3 | E26: =$A$26 -> 3 | F26: =$A$26 -> 3 | G26: =$A$26 -> 3 | H26: =$A$26 -> 3 | I26: =$A$26 -> 3 | J26: =$A$26 -> 3 | ... T26: =$A$26 -> 3 | U26: =$A$26+0.5 -> 3.5 | V26: =$A$26+0.5 -> 3.5 | W26: =$A$26+0.5 -> 3.5 | X26: =$A$26+0.5 -> 3.5 | Y26: =$A$26+0.5 -> 3.5 | Z26: =$A$26+0.5 -> 3.5 | AA26: =$A$26+0.5 -> 3.5 | AB26: =$A$26+0.5 -> 3.5 | ... AL26: =$A$26+0.5 -> 3.5
A27: 0.85 | B27: Скидки на 1 пользователя в месяц | C27: =$A$27 -> 0.85 | D27: =$A$27 -> 0.85 | E27: =D27-0.05 -> 0.8 | F27: =E27-0.05 -> 0.75 | G27: =F27-0.05 -> 0.7 | H27: =G27-0.05 -> 0.65 | I27: =H27-0.05 -> 0.6 | J27: =I27-0.05 -> 0.55 | K27: =J27-0.05 -> 0.5 | L27: =K27 -> 0.5 | M27: =L27 -> 0.5 | N27: =M27 -> 0.5 | O27: =N27 -> 0.5 | P27: =O27 -> 0.5 | Q27: =P27 -> 0.5 | R27: =Q27 -> 0.5 | S27: =R27 -> 0.5 | ... AL27: =AK27 -> 0.5
A28: 125 | B28: Бонусы на 1 курьера в месяц | C28: =$A$28 - (ROUND($C$29,0)-ROUND(C29,0))*10 -> 125 | D28: =$A$28 - (ROUND($C$29,0)-ROUND(D29,0))*10 -> 105 | E28: =$A$28 - (ROUND($C$29,0)-ROUND(E29,0))*10 -> 95 | F28: =$A$28 - (ROUND($C$29,0)-ROUND(F29,0))*10 -> 85 | G28: =$A$28 - (ROUND($C$29,0)-ROUND(G29,0))*10 -> 75 | H28: =$A$28 - (ROUND($C$29,0)-ROUND(H29,0))*10 -> 65 | I28: =$A$28 - (ROUND($C$29,0)-ROUND(I29,0))*10 -> 65 | J28: =$A$28 - (ROUND($C$29,0)-ROUND(J29,0))*10 -> 65 | ... AL28: =$A$28 - (ROUND($C$29,0)-ROUND(AL29,0))*10 -> 75
B29: Заказы в день на курьера | C29: =(C20/C30)/31 -> 12.5077 | D29: =(D20/D30)/31 -> 11.392231 | E29: =(E20/E30)/31 -> 9.9311371 | F29: =(F20/F30)/31 -> 8.8063295 | G29: =(G20/G30)/31 -> 7.9097053 | H29: =(H20/H30)/31 -> 7.1714407 | I29: =(I20/I30)/31 -> 6.5461456 | J29: =(J20/J30)/31 -> 6.6044535 | ... AL29: =(AL20/AL30)/31 -> 7.8571654
A30: 95 | B30: Кол-во курьеров | C30: =A30 -> 95 | D30: =C30*103% -> 97.85 | E30: =D30*110% -> 107.635 | F30: =E30*110% -> 118.3985 | G30: =F30*110% -> 130.23835 | H30: =G30*110% -> 143.26219 | I30: =H30*110% -> 157.5884 | J30: =I30 -> 157.5884 | K30: =J30 -> 157.5884 | L30: =K30 -> 157.5884 | M30: =L30 -> 157.5884 | N30: =M30 -> 157.5884 | O30: =N30 -> 157.5884 | P30: =O30 -> 157.5884 | Q30: =P30 -> 157.5884 | ... T30: =S30 -> 157.5884 | U30: =T30*102% -> 160.74017 | V30: =U30*102% -> 163.95498 | W30: =V30*102% -> 167.23407 | X30: =W30*102% -> 170.57876 | Y30: =X30*102% -> 173.99033 | Z30: =Y30*102% -> 177.47014 | AA30: =Z30*102% -> 181.01954 | AB30: =AA30*102% -> 184.63993 | ... AL30: =AK30*102% -> 225.07505
A31: 8 | B31: Кол-во сотрудников | C31: =$A$31 -> 8 | D31: =$A$31 -> 8 | E31: =$A$31 -> 8 | F31: =$A$31 -> 8 | G31: =$A$31 -> 8 | H31: =$A$31 -> 8 | I31: =$A$31 -> 8 | J31: =$A$31 -> 8 | K31: =$A$31 -> 8 | L31: =$A$31+1 -> 9 | M31: =$A$31+1 -> 9 | N31: =$A$31+1 -> 9 | O31: =$A$31+1 -> 9 | P31: =$A$31+1 -> 9 | Q31: =$A$31+2 -> 10 | R31: =$A$31+2 -> 10 | S31: =$A$31+2 -> 10 | T31: =$A$31+2 -> 10 | U31: =$A$31+2 -> 10 | V31: =$A$31+2 -> 10 | W31: =$A$31+2 -> 10 | X31: =$A$31+3 -> 11 | Y31: =$A$31+3 -> 11 | Z31: =$A$31+3 -> 11 | AA31: =$A$31+3 -> 11 | AB31: =$A$31+3 -> 11 | AC31: =$A$31+3 -> 11 | AD31: =$A$31+3 -> 11 | AE31: =$A$31+4 -> 12 | AF31: =$A$31+4 -> 12 | AG31: =$A$31+4 -> 12 | AH31: =$A$31+4 -> 12 | AI31: =$A$31+4 -> 12 | AJ31: =$A$31+4 -> 12 | AK31: =$A$31+4 -> 12 | AL31: =$A$31+4 -> 12
A32: 7.5 | B32: CAC | C32: =$A$32 -> 7.5 | D32: =$A$32 -> 7.5 | E32: =$A$32 -> 7.5 | F32: =$A$32 -> 7.5 | G32: =$A$32 -> 7.5 | H32: =$A$32 -> 7.5 | I32: =$A$32 -> 7.5 | J32: =$A$32 -> 7.5 | ... N32: =$A$32 -> 7.5 | O32: =$A$32*105% -> 7.875 | P32: =$A$32*105% -> 7.875 | Q32: =$A$32*105% -> 7.875 | R32: =$A$32*105% -> 7.875 | S32: =$A$32*105% -> 7.875 | T32: =$A$32*105% -> 7.875 | U32: =$A$32*105% -> 7.875 | V32: =$A$32*105% -> 7.875 | ... Z32: =$A$32*105% -> 7.875 | AA32: =$A$32*112% -> 8.4 | AB32: =$A$32*112% -> 8.4 | AC32: =$A$32*112% -> 8.4 | AD32: =$A$32*112% -> 8.4 | AE32: =$A$32*112% -> 8.4 | AF32: =$A$32*112% -> 8.4 | AG32: =$A$32*112% -> 8.4 | AH32: =$A$32*112% -> 8.4 | ... AL32: =$A$32*112% -> 8.4
B34: Расходы | C34: =SUM(C35:C40) -> 191487.58 | D34: =SUM(D35:D40) -> 184384.05 | E34: =SUM(E35:E40) -> 180241.34 | F34: =SUM(F35:F40) -> 177708.49 | G34: =SUM(G35:G40) -> 176238.46 | H34: =SUM(H35:H40) -> 175442.03 | I34: =SUM(I35:I40) -> 176613.84 | J34: =SUM(J35:J40) -> 177260.82 | ... AL34: =SUM(AL35:AL40) -> 304946.64
A35: 5300 | B35: Аренда | C35: =$A$35 -> 5300 | D35: =$A$35 -> 5300 | E35: =$A$35 -> 5300 | F35: =$A$35 -> 5300 | G35: =$A$35 -> 5300 | H35: =$A$35 -> 5300 | I35: =$A$35 -> 5300 | J35: =$A$35 -> 5300 | ... N35: =$A$35 -> 5300 | O35: =$A$35*110% -> 5830 | P35: =$A$35*110% -> 5830 | Q35: =$A$35*110% -> 5830 | R35: =$A$35*110% -> 5830 | S35: =$A$35*110% -> 5830 | T35: =$A$35*110% -> 5830 | U35: =$A$35*110% -> 5830 | V35: =$A$35*110% -> 5830 | ... Z35: =$A$35*110% -> 5830 | AA35: =$A$35*115% -> 6095 | AB35: =$A$35*115% -> 6095 | AC35: =$A$35*115% -> 6095 | AD35: =$A$35*115% -> 6095 | AE35: =$A$35*115% -> 6095 | AF35: =$A$35*115% -> 6095 | AG35: =$A$35*115% -> 6095 | AH35: =$A$35*115% -> 6095 | ... AL35: =$A$35*115% -> 6095
A36: 4000 | B36: ФОТ | C36: =$A$36*C31 -> 32000 | D36: =$A$36*D31 -> 32000 | E36: =$A$36*E31 -> 32000 | F36: =$A$36*F31 -> 32000 | G36: =$A$36*G31 -> 32000 | H36: =$A$36*H31 -> 32000 | I36: =$A$36*I31 -> 32000 | J36: =$A$36*J31 -> 32000 | ... N36: =$A$36*N31 -> 36000 | O36: =$A$36*O31*105% -> 37800 | P36: =$A$36*P31*105% -> 37800 | Q36: =$A$36*Q31*105% -> 42000 | R36: =$A$36*R31*105% -> 42000 | S36: =$A$36*S31*105% -> 42000 | T36: =$A$36*T31*105% -> 42000 | U36: =$A$36*U31*105% -> 42000 | V36: =$A$36*V31*105% -> 42000 | ... Z36: =$A$36*Z31*105% -> 46200 | AA36: =$A$36*AA31*110% -> 48400 | AB36: =$A$36*AB31*110% -> 48400 | AC36: =$A$36*AC31*110% -> 48400 | AD36: =$A$36*AD31*110% -> 48400 | AE36: =$A$36*AE31*110% -> 52800 | AF36: =$A$36*AF31*110% -> 52800 | AG36: =$A$36*AG31*110% -> 52800 | AH36: =$A$36*AH31*110% -> 52800 | ... AL36: =$A$36*AL31*110% -> 52800
B37: Бюджет на маркетинг | C37: =C13*C32 -> 37500 | D37: =D13*D32 -> 38250 | E37: =E13*E32 -> 39015 | F37: =F13*F32 -> 39795.3 | G37: =G13*G32 -> 40591.206 | H37: =H13*H32 -> 41403.03 | I37: =I13*I32 -> 42231.091 | J37: =J13*J32 -> 43075.713 | ... AL37: =AL13*AL32 -> 83995.361
B38: Затраты на скидки | C38: =C12*C27 -> 18203.43 | D38: =D12*D27 -> 17077.401 | E38: =E12*E27 -> 15412.594 | F38: =F12*F27 -> 14094.045 | G38: =G12*G27 -> 12996.622 | H38: =H12*H27 -> 12036.067 | I38: =I12*I27 -> 11155.638 | J38: =J12*J27 -> 10317.087 | ... AL38: =AL12*AL27 -> 15936.63
A39: 2.25 | B39: Выплаты курьерам за доставку | C39: =C20*$A$39 + C28*C30 -> 94754.146 | D39: =D20*$A$39 + D28*D30 -> 88026.652 | E39: =E20*$A$39 + E28*E30 -> 84783.747 | F39: =F20*$A$39 + F28*F30 -> 82789.142 | G39: =G20*$A$39 + G28*G30 -> 81620.627 | H39: =H20*$A$39 + H28*H30 -> 80972.931 | I39: =I20*$A$39 + I28*I30 -> 82197.112 | J39: =J20*$A$39 + J28*J30 -> 82838.02 | ... AL39: =AL20*$A$39 + AL28*AL30 -> 140230.15
B40: Прочие операционные расходы | C40: =SUM(C35:C36)*10% -> 3730 | D40: =SUM(D35:D36)*10% -> 3730 | E40: =SUM(E35:E36)*10% -> 3730 | F40: =SUM(F35:F36)*10% -> 3730 | G40: =SUM(G35:G36)*10% -> 3730 | H40: =SUM(H35:H36)*10% -> 3730 | I40: =SUM(I35:I36)*10% -> 3730 | J40: =SUM(J35:J36)*10% -> 3730 | ... AL40: =SUM(AL35:AL36)*10% -> 5889.5
B41: Прирост расходов (% к прошлому месяцу) | C41: 1 | D41: =(D34/C34)-100% -> -0.037096521 | E41: =(E34/D34)-100% -> -0.022467849 | F41: =(F34/E34)-100% -> -0.014052565 | G41: =(G34/F34)-100% -> -0.008272153 | H41: =(H34/G34)-100% -> -0.0045190302 | I41: =(I34/H34)-100% -> 0.0066791986 | J41: =(J34/I34)-100% -> 0.0036632378 | K41: =(K34/J34)-100% -> 0.0052587584 | ... AL41: =(AL34/AK34)-100% -> 0.015684313
B43: EBITDA (операционная прибыль) | C43: =C8-C34 -> 2614.9556 | D43: =D8-D34 -> -2288.3291 | E43: =E8-E34 -> -5625.9022 | F43: =F8-F34 -> -7386.2807 | G43: =G8-G34 -> -7959.6831 | H43: =H8-H34 -> -7612.5956 | I43: =I8-I34 -> -8098.2595 | J43: =J8-J34 -> -7244.2346 | ... AL43: =AL8-AL34 -> 29916.387
B44: EBITDA нарастающим итогом | C44: =C43 -> 2614.9556 | D44: =D43+C44 -> 326.62655 | E44: =E43+D44 -> -5299.2757 | F44: =F43+E44 -> -12685.556 | G44: =G43+F44 -> -20645.239 | H44: =H43+G44 -> -28257.835 | I44: =I43+H44 -> -36356.095 | J44: =J43+I44 -> -43600.329 | K44: =K43+J44 -> -49684.92 | ... AL44: =AL43+AK44 -> 217591.36
B45: Рентабельность EBITDA (% от общей выручки) | C45: =C43/C8 -> 0.013472033 | D45: =D43/D8 -> -0.012566627 | E45: =E43/E8 -> -0.032218813 | F45: =F43/F8 -> -0.043366516 | G45: =G43/G8 -> -0.047300578 | H45: =H43/H8 -> -0.045359121 | I45: =I43/I8 -> -0.048056444 | J45: =J43/J8 -> -0.042608988 | ... AL45: =AL43/AL8 -> 0.089339176
B47: Прочие расходы
A48: 0.21 | B48: Налоговая нагрузка | C48: =IF(C43>0, C43*$A$48, 0) -> 549.14068 | D48: =IF(D43>0, D43*$A$48, 0) -> 0 | E48: =IF(E43>0, E43*$A$48, 0) -> 0 | F48: =IF(F43>0, F43*$A$48, 0) -> 0 | G48: =IF(G43>0, G43*$A$48, 0) -> 0 | H48: =IF(H43>0, H43*$A$48, 0) -> 0 | I48: =IF(I43>0, I43*$A$48, 0) -> 0 | J48: =IF(J43>0, J43*$A$48, 0) -> 0 | ... AL48: =IF(AL43>0, AL43*$A$48, 0) -> 6282.4412
B50: Чистая прибыль | C50: =C43-C48 -> 2065.8149 | D50: =D43-D48 -> -2288.3291 | E50: =E43-E48 -> -5625.9022 | F50: =F43-F48 -> -7386.2807 | G50: =G43-G48 -> -7959.6831 | H50: =H43-H48 -> -7612.5956 | I50: =I43-I48 -> -8098.2595 | J50: =J43-J48 -> -7244.2346 | ... AL50: =AL43-AL48 -> 23633.945
B51: Прибыль нарастающим итогом | C51: =C50 -> 2065.8149 | D51: =C51+D50 -> -222.51413 | E51: =D51+E50 -> -5848.4163 | F51: =E51+F50 -> -13234.697 | G51: =F51+G50 -> -21194.38 | H51: =G51+H50 -> -28806.976 | I51: =H51+I50 -> -36905.235 | J51: =I51+J50 -> -44149.47 | K51: =J51+K50 -> -50234.06 | ... AL51: =AK51+AL50 -> 137564.85
B52: Рентабельность чистой прибыли (%) | C52: =C50/C8 -> 0.010642906 | D52: =D50/D8 -> -0.012566627 | E52: =E50/E8 -> -0.032218813 | F52: =F50/F8 -> -0.043366516 | G52: =G50/G8 -> -0.047300578 | H52: =H50/H8 -> -0.045359121 | I52: =I50/I8 -> -0.048056444 | J52: =J50/J8 -> -0.042608988 | ... AL52: =AL50/AL8 -> 0.070577949
C56: 1 год | D56: 2 год | E56: 3 год | F56: 4 год
B57: Сумма чистой прибыли (год) | C57: -1477422 | D57: =SUM(C50:N50) -> -78547.284 | E57: =SUM(O50:Z50) -> 7955.142 | F57: =SUM(AA50:AL50) -> 208157
B58: NPV | F58: =C57 + NPV(0.15, D57:F57) -> -1402842.2
B59: IRR | F59: =IRR(C57:F57) -> -0.49344924

Sheet Финмодель индексация через год
B1: ОПиУ 2026-28 | C1: 2026 | O1: 2027 | AA1: 2028
B2: Название статьи | C2: Январь | D2: Февраль | E2: Март | F2: Апрель | G2: Май | H2: Июнь | I2: Июль | J2: Август | K2: Сентябрь | L2: Октябрь | M2: Ноябрь | N2: Декабрь | O2: Январь | P2: Февраль | Q2: Март | R2: Апрель | S2: Май | T2: Июнь | U2: Июль | V2: Август | W2: Сентябрь | X2: Октябрь | Y2: Ноябрь | Z2: Декабрь | AA2: Январь | AB2: Февраль | AC2: Март | AD2: Апрель | AE2: Май | AF2: Июнь | AG2: Июль | AH2: Август | AI2: Сентябрь | AJ2: Октябрь | AK2: Ноябрь | AL2: Декабрь
A4: 1.03 | B4: Выручка от реализации
A5: 3900 | B5: Выручка от комиссии | C5: =C20*C23*C24 -> 30057.504 | D5: =D20*D23*D24 -> 28198.205 | E5: =E20*E23*E24 -> 27039.854 | F5: =F20*F23*F24 -> 26375.031 | G5: =G20*G23*G24 -> 26058.598 | H5: =H20*H23*H24 -> 25989.016 | I5: =I20*I23*I24 -> 26095.269 | J5: =J20*J23*J24 -> 26327.705 | ... AL5: =AL20*AL23*AL24 -> 47366.215
B6: Выручка от подписки | C6: =C12*C25 -> 53539.5 | D6: =D12*D25 -> 50227.65 | E6: =E12*E25 -> 48164.355 | F6: =F12*F25 -> 46980.149 | G6: =G12*G25 -> 46416.506 | H6: =H12*H25 -> 46292.564 | I6: =I12*I25 -> 46481.825 | J6: =J12*J25 -> 46895.848 | ... AL6: =AL12*AL25 -> 111556.41
B7: Выручка от доставки | C7: =C20*C26 -> 110505.53 | D7: =D20*D26 -> 103669.87 | E7: =E20*E26 -> 99411.229 | F7: =F20*F26 -> 96967.027 | G7: =G20*G26 -> 95803.668 | H7: =H20*H26 -> 95547.853 | I7: =I20*I26 -> 95938.487 | J7: =J20*J26 -> 96793.031 | ... AL7: =AL20*AL26 -> 219288.03
B8: Общая выручка | C8: =SUM(C5:C7) -> 194102.53 | D8: =SUM(D5:D7) -> 182095.72 | E8: =SUM(E5:E7) -> 174615.44 | F8: =SUM(F5:F7) -> 170322.21 | G8: =SUM(G5:G7) -> 168278.77 | H8: =SUM(H5:H7) -> 167829.43 | I8: =SUM(I5:I7) -> 168515.58 | J8: =SUM(J5:J7) -> 170016.58 | ... AL8: =SUM(AL5:AL7) -> 378210.66
B9: Прирост выручки (% к прошлому месяцу) | C9: 1 | D9: =(D8/C8*100%)-100% -> -0.061858067 | E9: =(E8/D8*100%)-100% -> -0.041078868 | F9: =(F8/E8*100%)-100% -> -0.024586782 | G9: =(G8/F8*100%)-100% -> -0.011997462 | H9: =(H8/G8*100%)-100% -> -0.0026702084 | I9: =(I8/H8*100%)-100% -> 0.0040883667 | J9: =(J8/I8*100%)-100% -> 0.0089072081 | K9: =(K8/J8*100%)-100% -> 0.012303599 | ... AL9: =(AL8/AK8*100%)-100% -> 0.019999696
B11: Воронка продаж
A12: 0.02 | B12: Активная база клиентов | C12: =30594-30594*C14 -> 21415.8 | D12: =C12+D13-(C12*D14) -> 20091.06 | E12: =D12+E13-(D12*E14) -> 19265.742 | F12: =E12+F13-(E12*F14) -> 18792.059 | G12: =F12+G13-(F12*G14) -> 18566.602 | H12: =G12+H13-(G12*H14) -> 18517.026 | I12: =H12+I13-(H12*I14) -> 18592.73 | J12: =I12+J13-(I12*J14) -> 18758.339 | K12: =J12+K13-(J12*K14) -> 18989.134 | ... AL12: =AK12+AL13-(AK12*AL14) -> 31873.26
A13: 5000 | B13: Новые клиенты | C13: =$A$13 -> 5000 | D13: =C13+C13*$A$12 -> 5100 | E13: =D13+D13*$A$12 -> 5202 | F13: =E13+E13*$A$12 -> 5306.04 | G13: =F13+F13*$A$12 -> 5412.1608 | H13: =G13+G13*$A$12 -> 5520.404 | I13: =H13+H13*$A$12 -> 5630.8121 | J13: =I13+I13*$A$12 -> 5743.4283 | K13: =J13+J13*$A$12 -> 5858.2969 | ... AL13: =AK13+AK13*$A$12 -> 9999.4478
A14: 0.3 | B14: Отток | C14: =$A$14 -> 0.3 | D14: =$A$14 -> 0.3 | E14: =$A$14 -> 0.3 | F14: =$A$14 -> 0.3 | G14: =$A$14 -> 0.3 | H14: =$A$14 -> 0.3 | I14: =$A$14 -> 0.3 | J14: =$A$14 -> 0.3 | ... AL14: =$A$14 -> 0.3
A15: 495 | B15: База шеф-поваров | C15: =$A$15 -> 495 | D15: =C15+(D13/18)-(C15*15%) -> 704.08333 | E15: =D15+(E13/18)-(D15*15%) -> 887.47083 | F15: =E15+(F13/18)-(E15*15%) -> 1049.1302 | G15: =F15+(G13/18)-(F15*15%) -> 1192.4363 | H15: =G15+(H13/18)-(G15*15%) -> 1320.2599 | I15: =H15+(I13/18)-(H15*15%) -> 1435.0438 | J15: =I15+(J13/18)-(I15*15%) -> 1538.8666 | K15: =J15+(K13/18)-(J15*15%) -> 1633.4976 | ... AL15: =AK15+(AL13/18)-(AK15*15%) -> 3329.1822
B16: Заказчиков на одного повара | C16: =C12/C15 -> 43.264242 | D16: =D12/D15 -> 28.53506 | E16: =E12/E15 -> 21.708592 | F16: =F12/F15 -> 17.912037 | G16: =G12/G15 -> 15.57031 | H16: =H12/H15 -> 14.025288 | I16: =I12/I15 -> 12.95621 | J16: =J12/J15 -> 12.189711 | ... AL16: =AL12/AL15 -> 9.5739009
A17: 0.86 | B17: Процент успешных доставок | C17: =$A$17 -> 0.86 | D17: =$A$17 -> 0.86 | E17: =$A$17 -> 0.86 | F17: =$A$17 -> 0.86 | G17: =$A$17 -> 0.86 | H17: =$A$17 -> 0.86 | I17: =$A$17 -> 0.86 | J17: =$A$17 -> 0.86 | ... AL17: =$A$17 -> 0.86
A18: 2 | B18: Частотность созданных заказов | C18: =$A$18+RANDBETWEEN(-0.4, 0.1) -> 2 | D18: =$A$18+RANDBETWEEN(-0.4, 0.1) -> 2 | E18: =$A$18+RANDBETWEEN(-0.4, 0.1) -> 2 | F18: =$A$18+RANDBETWEEN(-0.4, 0.1) -> 2 | G18: =$A$18+RANDBETWEEN(-0.4, 0.1) -> 2 | H18: =$A$18+RANDBETWEEN(-0.4, 0.1) -> 2 | I18: =$A$18+RANDBETWEEN(-0.4, 0.1) -> 2 | J18: =$A$18+RANDBETWEEN(-0.4, 0.1) -> 2 | ... AL18: =$A$18+RANDBETWEEN(-0.4, 0.1) -> 2
B19: Созданные заказы | C19: =C12*C18 -> 42831.6 | D19: =D12*D18 -> 40182.12 | E19: =E12*E18 -> 38531.484 | F19: =F12*F18 -> 37584.119 | G19: =G12*G18 -> 37133.205 | H19: =H12*H18 -> 37034.051 | I19: =I12*I18 -> 37185.46 | J19: =J12*J18 -> 37516.679 | ... AL19: =AL12*AL18 -> 63746.521
B20: Выполненные заказы | C20: =C19*C17 -> 36835.176 | D20: =D19*D17 -> 34556.623 | E20: =E19*E17 -> 33137.076 | F20: =F19*F17 -> 32322.342 | G20: =G19*G17 -> 31934.556 | H20: =H19*H17 -> 31849.284 | I20: =I19*I17 -> 31979.496 | J20: =J19*J17 -> 32264.344 | ... AL20: =AL19*AL17 -> 54822.008
B22: Юнит-экономика
A23: 6.8 | B23: Средняя стоимость обеда | C23: =$A$23 -> 6.8 | D23: =$A$23 -> 6.8 | E23: =$A$23 -> 6.8 | F23: =$A$23 -> 6.8 | G23: =$A$23 -> 6.8 | H23: =$A$23 -> 6.8 | I23: =$A$23 -> 6.8 | J23: =$A$23 -> 6.8 | ... N23: =$A$23 -> 6.8 | O23: =$A$23+0.2 -> 7 | P23: =$A$23+0.2 -> 7 | Q23: =$A$23+0.2 -> 7 | R23: =$A$23+0.2 -> 7 | S23: =$A$23+0.2 -> 7 | T23: =$A$23+0.2 -> 7 | U23: =$A$23+0.2 -> 7 | V23: =$A$23+0.2 -> 7 | ... Z23: =$A$23+0.2 -> 7 | AA23: =$A$23+0.4 -> 7.2 | AB23: =$A$23+0.4 -> 7.2 | AC23: =$A$23+0.4 -> 7.2 | AD23: =$A$23+0.4 -> 7.2 | AE23: =$A$23+0.4 -> 7.2 | AF23: =$A$23+0.4 -> 7.2 | AG23: =$A$23+0.4 -> 7.2 | AH23: =$A$23+0.4 -> 7.2 | ... AL23: =$A$23+0.4 -> 7.2
A24: 0.12 | B24: Комиссия сервиса с шефов | C24: =$A$24 -> 0.12 | D24: =$A$24 -> 0.12 | E24: =$A$24 -> 0.12 | F24: =$A$24 -> 0.12 | G24: =$A$24 -> 0.12 | H24: =$A$24 -> 0.12 | I24: =$A$24 -> 0.12 | J24: =$A$24 -> 0.12 | ... AL24: =$A$24 -> 0.12
A25: 2.5 | B25: Стоимость подписки на сервис | C25: =$A$25 -> 2.5 | D25: =$A$25 -> 2.5 | E25: =$A$25 -> 2.5 | F25: =$A$25 -> 2.5 | G25: =$A$25 -> 2.5 | H25: =$A$25 -> 2.5 | I25: =$A$25 -> 2.5 | J25: =$A$25 -> 2.5 | ... N25: =$A$25 -> 2.5 | O25: =$A$25+0.5 -> 3 | P25: =$A$25+0.5 -> 3 | Q25: =$A$25+0.5 -> 3 | R25: =$A$25+0.5 -> 3 | S25: =$A$25+0.5 -> 3 | T25: =$A$25+0.5 -> 3 | U25: =$A$25+0.5 -> 3 | V25: =$A$25+0.5 -> 3 | ... Z25: =$A$25+0.5 -> 3 | AA25: =$A$25+1 -> 3.5 | AB25: =$A$25+1 -> 3.5 | AC25: =$A$25+1 -> 3.5 | AD25: =$A$25+1 -> 3.5 | AE25: =$A$25+1 -> 3.5 | AF25: =$A$25+1 -> 3.5 | AG25: =$A$25+1 -> 3.5 | AH25: =$A$25+1 -> 3.5 | ... AL25: =$A$25+1 -> 3.5
A26: 3 | B26: Стоимость доставки | C26: =$A$26 -> 3 | D26: =$A$26 -> 3 | E26: =$A$26 -> 3 | F26: =$A$26 -> 3 | G26: =$A$26 -> 3 | H26: =$A$26 -> 3 | I26: =$A$26 -> 3 | J26: =$A$26 -> 3 | ... N26: =$A$26 -> 3 | O26: =$A$26+0.5 -> 3.5 | P26: =$A$26+0.5 -> 3.5 | Q26: =$A$26+0.5 -> 3.5 | R26: =$A$26+0.5 -> 3.5 | S26: =$A$26+0.5 -> 3.5 | T26: =$A$26+0.5 -> 3.5 | U26: =$A$26+0.5 -> 3.5 | V26: =$A$26+0.5 -> 3.5 | ... Z26: =$A$26+0.5 -> 3.5 | AA26: =$A$26+1 -> 4 | AB26: =$A$26+1 -> 4 | AC26: =$A$26+1 -> 4 | AD26: =$A$26+1 -> 4 | AE26: =$A$26+1 -> 4 | AF26: =$A$26+1 -> 4 | AG26: =$A$26+1 -> 4 | AH26: =$A$26+1 -> 4 | ... AL26: =$A$26+1 -> 4
A27: 0.85 | B27: Скидки на 1 пользователя в месяц | C27: =$A$27 -> 0.85 | D27: =$A$27 -> 0.85 | E27: =D27-0.05 -> 0.8 | F27: =E27-0.05 -> 0.75 | G27: =F27-0.05 -> 0.7 | H27: =G27-0.05 -> 0.65 | I27: =H27-0.05 -> 0.6 | J27: =I27-0.05 -> 0.55 | K27: =J27-0.05 -> 0.5 | L27: =K27 -> 0.5 | M27: =L27 -> 0.5 | N27: =M27 -> 0.5 | O27: =N27 -> 0.5 | P27: =O27 -> 0.5 | Q27: =P27 -> 0.5 | R27: =Q27 -> 0.5 | S27: =R27 -> 0.5 | ... AL27: =AK27 -> 0.5
A28: 125 | B28: Бонусы на 1 курьера в месяц | C28: =$A$28 - (ROUND($C$29,0)-ROUND(C29,0))*10 -> 125 | D28: =$A$28 - (ROUND($C$29,0)-ROUND(D29,0))*10 -> 105 | E28: =$A$28 - (ROUND($C$29,0)-ROUND(E29,0))*10 -> 95 | F28: =$A$28 - (ROUND($C$29,0)-ROUND(F29,0))*10 -> 85 | G28: =$A$28 - (ROUND($C$29,0)-ROUND(G29,0))*10 -> 75 | H28: =$A$28 - (ROUND($C$29,0)-ROUND(H29,0))*10 -> 65 | I28: =$A$28 - (ROUND($C$29,0)-ROUND(I29,0))*10 -> 65 | J28: =$A$28 - (ROUND($C$29,0)-ROUND(J29,0))*10 -> 65 | ... AL28: =$A$28 - (ROUND($C$29,0)-ROUND(AL29,0))*10 -> 75
B29: Заказы в день на курьера | C29: =(C20/C30)/31 -> 12.5077 | D29: =(D20/D30)/31 -> 11.392231 | E29: =(E20/E30)/31 -> 9.9311371 | F29: =(F20/F30)/31 -> 8.8063295 | G29: =(G20/G30)/31 -> 7.9097053 | H29: =(H20/H30)/31 -> 7.1714407 | I29: =(I20/I30)/31 -> 6.5461456 | J29: =(J20/J30)/31 -> 6.6044535 | ... AL29: =(AL20/AL30)/31 -> 7.8571654
A30: 95 | B30: Кол-во курьеров | C30: =A30 -> 95 | D30: =C30*103% -> 97.85 | E30: =D30*110% -> 107.635 | F30: =E30*110% -> 118.3985 | G30: =F30*110% -> 130.23835 | H30: =G30*110% -> 143.26219 | I30: =H30*110% -> 157.5884 | J30: =I30 -> 157.5884 | K30: =J30 -> 157.5884 | L30: =K30 -> 157.5884 | M30: =L30 -> 157.5884 | N30: =M30 -> 157.5884 | O30: =N30 -> 157.5884 | P30: =O30 -> 157.5884 | Q30: =P30 -> 157.5884 | ... T30: =S30 -> 157.5884 | U30: =T30*102% -> 160.74017 | V30: =U30*102% -> 163.95498 | W30: =V30*102% -> 167.23407 | X30: =W30*102% -> 170.57876 | Y30: =X30*102% -> 173.99033 | Z30: =Y30*102% -> 177.47014 | AA30: =Z30*102% -> 181.01954 | AB30: =AA30*102% -> 184.63993 | ... AL30: =AK30*102% -> 225.07505
A31: 8 | B31: Кол-во сотрудников | C31: =$A$31 -> 8 | D31: =$A$31 -> 8 | E31: =$A$31 -> 8 | F31: =$A$31 -> 8 | G31: =$A$31 -> 8 | H31: =$A$31 -> 8 | I31: =$A$31 -> 8 | J31: =$A$31 -> 8 | K31: =$A$31 -> 8 | L31: =$A$31+1 -> 9 | M31: =$A$31+1 -> 9 | N31: =$A$31+1 -> 9 | O31: =$A$31+1 -> 9 | P31: =$A$31+1 -> 9 | Q31: =$A$31+2 -> 10 | R31: =$A$31+2 -> 10 | S31: =$A$31+2 -> 10 | T31: =$A$31+2 -> 10 | U31: =$A$31+2 -> 10 | V31: =$A$31+2 -> 10 | W31: =$A$31+2 -> 10 | X31: =$A$31+3 -> 11 | Y31: =$A$31+3 -> 11 | Z31: =$A$31+3 -> 11 | AA31: =$A$31+3 -> 11 | AB31: =$A$31+3 -> 11 | AC31: =$A$31+3 -> 11 | AD31: =$A$31+3 -> 11 | AE31: =$A$31+4 -> 12 | AF31: =$A$31+4 -> 12 | AG31: =$A$31+4 -> 12 | AH31: =$A$31+4 -> 12 | AI31: =$A$31+4 -> 12 | AJ31: =$A$31+4 -> 12 | AK31: =$A$31+4 -> 12 | AL31: =$A$31+4 -> 12
A32: 7.5 | B32: CAC | C32: =$A$32 -> 7.5 | D32: =$A$32 -> 7.5 | E32: =$A$32 -> 7.5 | F32: =$A$32 -> 7.5 | G32: =$A$32 -> 7.5 | H32: =$A$32 -> 7.5 | I32: =$A$32 -> 7.5 | J32: =$A$32 -> 7.5 | ... N32: =$A$32 -> 7.5 | O32: =$A$32*105% -> 7.875 | P32: =$A$32*105% -> 7.875 | Q32: =$A$32*105% -> 7.875 | R32: =$A$32*105% -> 7.875 | S32: =$A$32*105% -> 7.875 | T32: =$A$32*105% -> 7.875 | U32: =$A$32*105% -> 7.875 | V32: =$A$32*105% -> 7.875 | ... Z32: =$A$32*105% -> 7.875 | AA32: =$A$32*112% -> 8.4 | AB32: =$A$32*112% -> 8.4 | AC32: =$A$32*112% -> 8.4 | AD32: =$A$32*112% -> 8.4 | AE32: =$A$32*112% -> 8.4 | AF32: =$A$32*112% -> 8.4 | AG32: =$A$32*112% -> 8.4 | AH32: =$A$32*112% -> 8.4 | ... AL32: =$A$32*112% -> 8.4
B34: Расходы | C34: =SUM(C35:C40) -> 191487.58 | D34: =SUM(D35:D40) -> 184384.05 | E34: =SUM(E35:E40) -> 180241.34 | F34: =SUM(F35:F40) -> 177708.49 | G34: =SUM(G35:G40) -> 176238.46 | H34: =SUM(H35:H40) -> 175442.03 | I34: =SUM(I35:I40) -> 176613.84 | J34: =SUM(J35:J40) -> 177260.82 | ... AL34: =SUM(AL35:AL40) -> 304946.64
A35: 5300 | B35: Аренда | C35: =$A$35 -> 5300 | D35: =$A$35 -> 5300 | E35: =$A$35 -> 5300 | F35: =$A$35 -> 5300 | G35: =$A$35 -> 5300 | H35: =$A$35 -> 5300 | I35: =$A$35 -> 5300 | J35: =$A$35 -> 5300 | ... N35: =$A$35 -> 5300 | O35: =$A$35*110% -> 5830 | P35: =$A$35*110% -> 5830 | Q35: =$A$35*110% -> 5830 | R35: =$A$35*110% -> 5830 | S35: =$A$35*110% -> 5830 | T35: =$A$35*110% -> 5830 | U35: =$A$35*110% -> 5830 | V35: =$A$35*110% -> 5830 | ... Z35: =$A$35*110% -> 5830 | AA35: =$A$35*115% -> 6095 | AB35: =$A$35*115% -> 6095 | AC35: =$A$35*115% -> 6095 | AD35: =$A$35*115% -> 6095 | AE35: =$A$35*115% -> 6095 | AF35: =$A$35*115% -> 6095 | AG35: =$A$35*115% -> 6095 | AH35: =$A$35*115% -> 6095 | ... AL35: =$A$35*115% -> 6095
A36: 4000 | B36: ФОТ | C36: =$A$36*C31 -> 32000 | D36: =$A$36*D31 -> 32000 | E36: =$A$36*E31 -> 32000 | F36: =$A$36*F31 -> 32000 | G36: =$A$36*G31 -> 32000 | H36: =$A$36*H31 -> 32000 | I36: =$A$36*I31 -> 32000 | J36: =$A$36*J31 -> 32000 | ... N36: =$A$36*N31 -> 36000 | O36: =$A$36*O31*105% -> 37800 | P36: =$A$36*P31*105% -> 37800 | Q36: =$A$36*Q31*105% -> 42000 | R36: =$A$36*R31*105% -> 42000 | S36: =$A$36*S31*105% -> 42000 | T36: =$A$36*T31*105% -> 42000 | U36: =$A$36*U31*105% -> 42000 | V36: =$A$36*V31*105% -> 42000 | ... Z36: =$A$36*Z31*105% -> 46200 | AA36: =$A$36*AA31*110% -> 48400 | AB36: =$A$36*AB31*110% -> 48400 | AC36: =$A$36*AC31*110% -> 48400 | AD36: =$A$36*AD31*110% -> 48400 | AE36: =$A$36*AE31*110% -> 52800 | AF36: =$A$36*AF31*110% -> 52800 | AG36: =$A$36*AG31*110% -> 52800 | AH36: =$A$36*AH31*110% -> 52800 | ... AL36: =$A$36*AL31*110% -> 52800
B37: Бюджет на маркетинг | C37: =C13*C32 -> 37500 | D37: =D13*D32 -> 38250 | E37: =E13*E32 -> 39015 | F37: =F13*F32 -> 39795.3 | G37: =G13*G32 -> 40591.206 | H37: =H13*H32 -> 41403.03 | I37: =I13*I32 -> 42231.091 | J37: =J13*J32 -> 43075.713 | ... AL37: =AL13*AL32 -> 83995.361
B38: Затраты на скидки | C38: =C12*C27 -> 18203.43 | D38: =D12*D27 -> 17077.401 | E38: =E12*E27 -> 15412.594 | F38: =F12*F27 -> 14094.045 | G38: =G12*G27 -> 12996.622 | H38: =H12*H27 -> 12036.067 | I38: =I12*I27 -> 11155.638 | J38: =J12*J27 -> 10317.087 | ... AL38: =AL12*AL27 -> 15936.63
A39: 2.25 | B39: Выплаты курьерам за доставку | C39: =C20*$A$39 + C28*C30 -> 94754.146 | D39: =D20*$A$39 + D28*D30 -> 88026.652 | E39: =E20*$A$39 + E28*E30 -> 84783.747 | F39: =F20*$A$39 + F28*F30 -> 82789.142 | G39: =G20*$A$39 + G28*G30 -> 81620.627 | H39: =H20*$A$39 + H28*H30 -> 80972.931 | I39: =I20*$A$39 + I28*I30 -> 82197.112 | J39: =J20*$A$39 + J28*J30 -> 82838.02 | ... AL39: =AL20*$A$39 + AL28*AL30 -> 140230.15
B40: Прочие операционные расходы | C40: =SUM(C35:C36)*10% -> 3730 | D40: =SUM(D35:D36)*10% -> 3730 | E40: =SUM(E35:E36)*10% -> 3730 | F40: =SUM(F35:F36)*10% -> 3730 | G40: =SUM(G35:G36)*10% -> 3730 | H40: =SUM(H35:H36)*10% -> 3730 | I40: =SUM(I35:I36)*10% -> 3730 | J40: =SUM(J35:J36)*10% -> 3730 | ... AL40: =SUM(AL35:AL36)*10% -> 5889.5
B41: Прирост расходов (% к прошлому месяцу) | C41: 1 | D41: =(D34/C34)-100% -> -0.037096521 | E41: =(E34/D34)-100% -> -0.022467849 | F41: =(F34/E34)-100% -> -0.014052565 | G41: =(G34/F34)-100% -> -0.008272153 | H41: =(H34/G34)-100% -> -0.0045190302 | I41: =(I34/H34)-100% -> 0.0066791986 | J41: =(J34/I34)-100% -> 0.0036632378 | K41: =(K34/J34)-100% -> 0.0052587584 | ... AL41: =(AL34/AK34)-100% -> 0.015684313
B43: EBITDA (операционная прибыль) | C43: =C8-C34 -> 2614.9556 | D43: =D8-D34 -> -2288.3291 | E43: =E8-E34 -> -5625.9022 | F43: =F8-F34 -> -7386.2807 | G43: =G8-G34 -> -7959.6831 | H43: =H8-H34 -> -7612.5956 | I43: =I8-I34 -> -8098.2595 | J43: =J8-J34 -> -7244.2346 | ... AL43: =AL8-AL34 -> 73264.021
B44: EBITDA нарастающим итогом | C44: =C43 -> 2614.9556 | D44: =D43+C44 -> 326.62655 | E44: =E43+D44 -> -5299.2757 | F44: =F43+E44 -> -12685.556 | G44: =G43+F44 -> -20645.239 | H44: =H43+G44 -> -28257.835 | I44: =I43+H44 -> -36356.095 | J44: =J43+I44 -> -43600.329 | K44: =K43+J44 -> -49684.92 | ... AL44: =AL43+AK44 -> 858888.23
B45: Рентабельность EBITDA (% от общей выручки) | C45: =C43/C8 -> 0.013472033 | D45: =D43/D8 -> -0.012566627 | E45: =E43/E8 -> -0.032218813 | F45: =F43/F8 -> -0.043366516 | G45: =G43/G8 -> -0.047300578 | H45: =H43/H8 -> -0.045359121 | I45: =I43/I8 -> -0.048056444 | J45: =J43/J8 -> -0.042608988 | ... AL45: =AL43/AL8 -> 0.19371221
B47: Прочие расходы
A48: 0.21 | B48: Налоговая нагрузка | C48: =IF(C43>0, C43*$A$48, 0) -> 549.14068 | D48: =IF(D43>0, D43*$A$48, 0) -> 0 | E48: =IF(E43>0, E43*$A$48, 0) -> 0 | F48: =IF(F43>0, F43*$A$48, 0) -> 0 | G48: =IF(G43>0, G43*$A$48, 0) -> 0 | H48: =IF(H43>0, H43*$A$48, 0) -> 0 | I48: =IF(I43>0, I43*$A$48, 0) -> 0 | J48: =IF(J43>0, J43*$A$48, 0) -> 0 | ... AL48: =IF(AL43>0, AL43*$A$48, 0) -> 15385.444
B50: Чистая прибыль | C50: =C43-C48 -> 2065.8149 | D50: =D43-D48 -> -2288.3291 | E50: =E43-E48 -> -5625.9022 | F50: =F43-F48 -> -7386.2807 | G50: =G43-G48 -> -7959.6831 | H50: =H43-H48 -> -7612.5956 | I50: =I43-I48 -> -8098.2595 | J50: =J43-J48 -> -7244.2346 | ... AL50: =AL43-AL48 -> 57878.577
B51: Прибыль нарастающим итогом | C51: =C50 -> 2065.8149 | D51: =C51+D50 -> -222.51413 | E51: =D51+E50 -> -5848.4163 | F51: =E51+F50 -> -13234.697 | G51: =F51+G50 -> -21194.38 | H51: =G51+H50 -> -28806.976 | I51: =H51+I50 -> -36905.235 | J51: =I51+J50 -> -44149.47 | K51: =J51+K50 -> -50234.06 | ... AL51: =AK51+AL50 -> 661592.95
B52: Рентабельность чистой прибыли (%) | C52: =C50/C8 -> 0.010642906 | D52: =D50/D8 -> -0.012566627 | E52: =E50/E8 -> -0.032218813 | F52: =F50/F8 -> -0.043366516 | G52: =G50/G8 -> -0.047300578 | H52: =H50/H8 -> -0.045359121 | I52: =I50/I8 -> -0.048056444 | J52: =J50/J8 -> -0.042608988 | ... AL52: =AL50/AL8 -> 0.15303264
C56: 1 год | D56: 2 год | E56: 3 год | F56: 4 год
B57: Сумма чистой прибыли (год) | C57: -1477422 | D57: =SUM(C50:N50) -> -78547.284 | E57: =SUM(O50:Z50) -> 162588.14 | F57: =SUM(AA50:AL50) -> 577552.1
B58: NPV | F58: =C57 + NPV(0.15, D57:F57) -> -1043034.1
B59: IRR | F59: =IRR(C57:F57) -> -0.23715149

Sheet Финмодель сценарий 1
B1: Сценарий 1: Умеренный | C1: Небольшое снижение количества клиентов и рост стоимости привлечения, небольшое увеличение бонусов и скидок
B2: ОПиУ 2026-28 | C2: 2026 | O2: 2027 | AA2: 2028 | AM2: 2029
B3: Название статьи | C3: Январь | D3: Февраль | E3: Март | F3: Апрель | G3: Май | H3: Июнь | I3: Июль | J3: Август | K3: Сентябрь | L3: Октябрь | M3: Ноябрь | N3: Декабрь | O3: Январь | P3: Февраль | Q3: Март | R3: Апрель | S3: Май | T3: Июнь | U3: Июль | V3: Август | W3: Сентябрь | X3: Октябрь | Y3: Ноябрь | Z3: Декабрь | AA3: Январь | AB3: Февраль | AC3: Март | AD3: Апрель | AE3: Май | AF3: Июнь | AG3: Июль | AH3: Август | AI3: Сентябрь | AJ3: Октябрь | AK3: Ноябрь | AL3: Декабрь | AM3: Январь | AN3: Февраль | AO3: Март | AP3: Апрель | AQ3: Май | AR3: Июнь | AS3: Июль | AT3: Август | AU3: Сентябрь | AV3: Октябрь | AW3: Ноябрь | AX3: Декабрь
A5: 1.03 | B5: Выручка от реализации
A6: 3900 | B6: Выручка от комиссии | C6: =C21*C24*C25 -> 28769.325 | D6: =D21*D24*D25 -> 25717.604 | E6: =E21*E24*E25 -> 23801.795 | F6: =F21*F24*F25 -> 22649.623 | G6: =G21*G24*G25 -> 22011.715 | H6: =H21*H24*H25 -> 21721.047 | I6: =I21*I24*I25 -> 21665.763 | J6: =J21*J24*J25 -> 21770.976 | ... AX6: =AX21*AX24*AX25 -> 49430.489
B7: Выручка от подписки | C7: =C13*C26 -> 51244.95 | D7: =D13*D26 -> 45809.117 | E7: =E13*E26 -> 42396.608 | F7: =F13*F26 -> 40344.317 | G7: =G13*G26 -> 39208.054 | H7: =H13*H26 -> 38690.306 | I7: =I13*I26 -> 38591.832 | J7: =J13*J26 -> 38779.241 | ... AX7: =AX13*AX26 -> 116418.17
B8: Выручка от доставки | C8: =C21*C27 -> 105769.58 | D8: =D21*D27 -> 94550.016 | E8: =E21*E27 -> 87506.599 | F8: =F21*F27 -> 83270.671 | G8: =G21*G27 -> 80925.424 | H8: =H21*H27 -> 79856.791 | I8: =I21*I27 -> 79653.541 | J8: =J21*J27 -> 80040.354 | ... AX8: =AX21*AX27 -> 228844.86
B9: Общая выручка | C9: =SUM(C6:C8) -> 185783.85 | D9: =SUM(D6:D8) -> 166076.74 | E9: =SUM(E6:E8) -> 153705 | F9: =SUM(F6:F8) -> 146264.61 | G9: =SUM(G6:G8) -> 142145.19 | H9: =SUM(H6:H8) -> 140268.14 | I9: =SUM(I6:I8) -> 139911.14 | J9: =SUM(J6:J8) -> 140590.57 | ... AX9: =SUM(AX6:AX8) -> 394693.51
B10: Прирост выручки (% к прошлому месяцу) | C10: 1 | D10: =(D9/C9*100%)-100% -> -0.1060755 | E10: =(E9/D9*100%)-100% -> -0.07449409 | F10: =(F9/E9*100%)-100% -> -0.048406954 | G10: =(G9/F9*100%)-100% -> -0.028164138 | H10: =(H9/G9*100%)-100% -> -0.013205168 | I10: =(I9/H9*100%)-100% -> -0.0025451752 | J10: =(J9/I9*100%)-100% -> 0.004856189 | K10: =(K9/J9*100%)-100% -> 0.0099026811 | ... AX10: =(AX9/AW9*100%)-100% -> 0.019999999
B12: Воронка продаж
A13: 0.02 | B13: Активная база клиентов | C13: =30594-30594*C15 -> 20497.98 | D13: =C13+D14-(C13*D15) -> 18323.647 | E13: =D13+E14-(D13*E15) -> 16958.643 | F13: =E13+F14-(E13*F15) -> 16137.727 | G13: =F13+G14-(F13*G15) -> 15683.222 | H13: =G13+H14-(G13*H15) -> 15476.122 | I13: =H13+I14-(H13*I15) -> 15436.733 | J13: =I13+J14-(I13*J15) -> 15511.696 | K13: =J13+K14-(J13*K15) -> 15665.304 | ... AX13: =AW13+AX14-(AW13*AX15) -> 33262.334
A14: 4500 | B14: Новые клиенты | C14: =$A$14 -> 4500 | D14: =C14+C14*$A$13 -> 4590 | E14: =D14+D14*$A$13 -> 4681.8 | F14: =E14+E14*$A$13 -> 4775.436 | G14: =F14+F14*$A$13 -> 4870.9447 | H14: =G14+G14*$A$13 -> 4968.3636 | I14: =H14+H14*$A$13 -> 5067.7309 | J14: =I14+I14*$A$13 -> 5169.0855 | K14: =J14+J14*$A$13 -> 5272.4672 | ... AX14: =AW14+AW14*$A$13 -> 11413.546
A15: 0.33 | B15: Отток | C15: =$A$15 -> 0.33 | D15: =$A$15 -> 0.33 | E15: =$A$15 -> 0.33 | F15: =$A$15 -> 0.33 | G15: =$A$15 -> 0.33 | H15: =$A$15 -> 0.33 | I15: =$A$15 -> 0.33 | J15: =$A$15 -> 0.33 | ... AX15: =$A$15 -> 0.33
A16: 495 | B16: База шеф-поваров | C16: =$A$16 -> 495 | D16: =C16+(D14/18)-(C16*15%) -> 675.75 | E16: =D16+(E14/18)-(D16*15%) -> 834.4875 | F16: =E16+(F14/18)-(E16*15%) -> 974.61638 | G16: =F16+(G14/18)-(F16*15%) -> 1099.032 | H16: =G16+(H14/18)-(G16*15%) -> 1210.1974 | I16: =H16+(I14/18)-(H16*15%) -> 1310.2084 | J16: =I16+(J14/18)-(I16*15%) -> 1400.8485 | K16: =J16+(K14/18)-(J16*15%) -> 1483.6361 | ... AX16: =AW16+(AX14/18)-(AW16*15%) -> 3804.0313
B17: Заказчиков на одного повара | C17: =C13/C16 -> 41.410061 | D17: =D13/D16 -> 27.116014 | E17: =E13/E16 -> 20.322226 | F17: =F13/F16 -> 16.55803 | G17: =G13/G16 -> 14.270033 | H17: =H13/H16 -> 12.788098 | I17: =I13/I16 -> 11.781891 | J17: =J13/J16 -> 11.073072 | ... AX17: =AX13/AX16 -> 8.7439696
A18: 0.86 | B18: Процент успешных доставок | C18: =$A$18 -> 0.86 | D18: =$A$18 -> 0.86 | E18: =$A$18 -> 0.86 | F18: =$A$18 -> 0.86 | G18: =$A$18 -> 0.86 | H18: =$A$18 -> 0.86 | I18: =$A$18 -> 0.86 | J18: =$A$18 -> 0.86 | ... AX18: =$A$18 -> 0.86
A19: 2 | B19: Частотность созданных заказов | C19: =$A$19+RANDBETWEEN(-0.4, 0.1) -> 2 | D19: =$A$19+RANDBETWEEN(-0.4, 0.1) -> 2 | E19: =$A$19+RANDBETWEEN(-0.4, 0.1) -> 2 | F19: =$A$19+RANDBETWEEN(-0.4, 0.1) -> 2 | G19: =$A$19+RANDBETWEEN(-0.4, 0.1) -> 2 | H19: =$A$19+RANDBETWEEN(-0.4, 0.1) -> 2 | I19: =$A$19+RANDBETWEEN(-0.4, 0.1) -> 2 | J19: =$A$19+RANDBETWEEN(-0.4, 0.1) -> 2 | ... AX19: =$A$19+RANDBETWEEN(-0.4, 0.1) -> 2
B20: Созданные заказы | C20: =C13*C19 -> 40995.96 | D20: =D13*D19 -> 36647.293 | E20: =E13*E19 -> 33917.286 | F20: =F13*F19 -> 32275.454 | G20: =G13*G19 -> 31366.444 | H20: =H13*H19 -> 30952.244 | I20: =I13*I19 -> 30873.466 | J20: =J13*J19 -> 31023.393 | ... AX20: =AX13*AX19 -> 66524.667
B21: Выполненные заказы | C21: =C20*C18 -> 35256.526 | D21: =D20*D18 -> 31516.672 | E21: =E20*E18 -> 29168.866 | F21: =F20*F18 -> 27756.89 | G21: =G20*G18 -> 26975.141 | H21: =H20*H18 -> 26618.93 | I21: =I20*I18 -> 26551.18 | J21: =J20*J18 -> 26680.118 | ... AX21: =AX20*AX18 -> 57211.214
B23: Юнит-экономика
A24: 6.8 | B24: Средняя стоимость обеда | C24: =$A$24 -> 6.8 | D24: =$A$24 -> 6.8 | E24: =$A$24 -> 6.8 | F24: =$A$24 -> 6.8 | G24: =$A$24 -> 6.8 | H24: =$A$24 -> 6.8 | I24: =$A$24 -> 6.8 | J24: =$A$24 -> 6.8 | ... N24: =$A$24 -> 6.8 | O24: =$A$24+0.2 -> 7 | P24: =$A$24+0.2 -> 7 | Q24: =$A$24+0.2 -> 7 | R24: =$A$24+0.2 -> 7 | S24: =$A$24+0.2 -> 7 | T24: =$A$24+0.2 -> 7 | U24: =$A$24+0.2 -> 7 | V24: =$A$24+0.2 -> 7 | ... Z24: =$A$24+0.2 -> 7 | AA24: =$A$24+0.4 -> 7.2 | AB24: =$A$24+0.4 -> 7.2 | AC24: =$A$24+0.4 -> 7.2 | AD24: =$A$24+0.4 -> 7.2 | AE24: =$A$24+0.4 -> 7.2 | AF24: =$A$24+0.4 -> 7.2 | AG24: =$A$24+0.4 -> 7.2 | AH24: =$A$24+0.4 -> 7.2 | ... AX24: =$A$24+0.4 -> 7.2
A25: 0.12 | B25: Комиссия сервиса с шефов | C25: =$A$25 -> 0.12 | D25: =$A$25 -> 0.12 | E25: =$A$25 -> 0.12 | F25: =$A$25 -> 0.12 | G25: =$A$25 -> 0.12 | H25: =$A$25 -> 0.12 | I25: =$A$25 -> 0.12 | J25: =$A$25 -> 0.12 | ... AX25: =$A$25 -> 0.12
A26: 2.5 | B26: Стоимость подписки на сервис | C26: =$A$26 -> 2.5 | D26: =$A$26 -> 2.5 | E26: =$A$26 -> 2.5 | F26: =$A$26 -> 2.5 | G26: =$A$26 -> 2.5 | H26: =$A$26 -> 2.5 | I26: =$A$26 -> 2.5 | J26: =$A$26 -> 2.5 | ... N26: =$A$26 -> 2.5 | O26: =$A$26+0.5 -> 3 | P26: =$A$26+0.5 -> 3 | Q26: =$A$26+0.5 -> 3 | R26: =$A$26+0.5 -> 3 | S26: =$A$26+0.5 -> 3 | T26: =$A$26+0.5 -> 3 | U26: =$A$26+0.5 -> 3 | V26: =$A$26+0.5 -> 3 | ... Z26: =$A$26+0.5 -> 3 | AA26: =$A$26+1 -> 3.5 | AB26: =$A$26+1 -> 3.5 | AC26: =$A$26+1 -> 3.5 | AD26: =$A$26+1 -> 3.5 | AE26: =$A$26+1 -> 3.5 | AF26: =$A$26+1 -> 3.5 | AG26: =$A$26+1 -> 3.5 | AH26: =$A$26+1 -> 3.5 | ... AX26: =$A$26+1 -> 3.5
A27: 3 | B27: Стоимость доставки | C27: =$A$27 -> 3 | D27: =$A$27 -> 3 | E27: =$A$27 -> 3 | F27: =$A$27 -> 3 | G27: =$A$27 -> 3 | H27: =$A$27 -> 3 | I27: =$A$27 -> 3 | J27: =$A$27 -> 3 | ... N27: =$A$27 -> 3 | O27: =$A$27+0.5 -> 3.5 | P27: =$A$27+0.5 -> 3.5 | Q27: =$A$27+0.5 -> 3.5 | R27: =$A$27+0.5 -> 3.5 | S27: =$A$27+0.5 -> 3.5 | T27: =$A$27+0.5 -> 3.5 | U27: =$A$27+0.5 -> 3.5 | V27: =$A$27+0.5 -> 3.5 | ... Z27: =$A$27+0.5 -> 3.5 | AA27: =$A$27+1 -> 4 | AB27: =$A$27+1 -> 4 | AC27: =$A$27+1 -> 4 | AD27: =$A$27+1 -> 4 | AE27: =$A$27+1 -> 4 | AF27: =$A$27+1 -> 4 | AG27: =$A$27+1 -> 4 | AH27: =$A$27+1 -> 4 | ... AX27: =$A$27+1 -> 4
A28: 0.95 | B28: Скидки на 1 пользователя в месяц | C28: =$A$28 -> 0.95 | D28: =$A$28 -> 0.95 | E28: =D28-0.05 -> 0.9 | F28: =E28-0.05 -> 0.85 | G28: =F28-0.05 -> 0.8 | H28: =G28-0.05 -> 0.75 | I28: =H28-0.05 -> 0.7 | J28: =I28-0.05 -> 0.65 | K28: =J28-0.05 -> 0.6 | L28: =K28 -> 0.6 | M28: =L28 -> 0.6 | N28: =M28 -> 0.6 | O28: =N28 -> 0.6 | P28: =O28 -> 0.6 | Q28: =P28 -> 0.6 | R28: =Q28 -> 0.6 | S28: =R28 -> 0.6 | ... AX28: =AW28 -> 0.6
A29: 150 | B29: Бонусы на 1 курьера в месяц | C29: =$A$29 - (ROUND($C$30,0)-ROUND(C30,0))*10 -> 150 | D29: =$A$29 - (ROUND($C$30,0)-ROUND(D30,0))*10 -> 130 | E29: =$A$29 - (ROUND($C$30,0)-ROUND(E30,0))*10 -> 120 | F29: =$A$29 - (ROUND($C$30,0)-ROUND(F30,0))*10 -> 110 | G29: =$A$29 - (ROUND($C$30,0)-ROUND(G30,0))*10 -> 100 | H29: =$A$29 - (ROUND($C$30,0)-ROUND(H30,0))*10 -> 90 | I29: =$A$29 - (ROUND($C$30,0)-ROUND(I30,0))*10 -> 80 | J29: =$A$29 - (ROUND($C$30,0)-ROUND(J30,0))*10 -> 80 | ... AX29: =$A$29 - (ROUND($C$30,0)-ROUND(AX30,0))*10 -> 90
B30: Заказы в день на курьера | C30: =(C21/C31)/31 -> 11.971656 | D30: =(D21/D31)/31 -> 10.390055 | E30: =(E21/E31)/31 -> 8.74187 | F30: =(F21/F31)/31 -> 7.562457 | G30: =(G21/G31)/31 -> 6.6813335 | H30: =(H21/H31)/31 -> 5.9937322 | I30: =(I21/I31)/31 -> 5.4349792 | J30: =(J21/J31)/31 -> 5.4613724 | ... AX30: =(AX21/AX31)/31 -> 6.4653205
A31: 95 | B31: Кол-во курьеров | C31: =A31 -> 95 | D31: =C31*103% -> 97.85 | E31: =D31*110% -> 107.635 | F31: =E31*110% -> 118.3985 | G31: =F31*110% -> 130.23835 | H31: =G31*110% -> 143.26219 | I31: =H31*110% -> 157.5884 | J31: =I31 -> 157.5884 | K31: =J31 -> 157.5884 | L31: =K31 -> 157.5884 | M31: =L31 -> 157.5884 | N31: =M31 -> 157.5884 | O31: =N31 -> 157.5884 | P31: =O31 -> 157.5884 | Q31: =P31 -> 157.5884 | ... T31: =S31 -> 157.5884 | U31: =T31*102% -> 160.74017 | V31: =U31*102% -> 163.95498 | W31: =V31*102% -> 167.23407 | X31: =W31*102% -> 170.57876 | Y31: =X31*102% -> 173.99033 | Z31: =Y31*102% -> 177.47014 | AA31: =Z31*102% -> 181.01954 | AB31: =AA31*102% -> 184.63993 | ... AX31: =AW31*102% -> 285.44958
A32: 8 | B32: Кол-во сотрудников | C32: =$A$32 -> 8 | D32: =$A$32 -> 8 | E32: =$A$32 -> 8 | F32: =$A$32 -> 8 | G32: =$A$32 -> 8 | H32: =$A$32 -> 8 | I32: =$A$32 -> 8 | J32: =$A$32 -> 8 | K32: =$A$32 -> 8 | L32: =$A$32+1 -> 9 | M32: =$A$32+1 -> 9 | N32: =$A$32+1 -> 9 | O32: =$A$32+1 -> 9 | P32: =$A$32+1 -> 9 | Q32: =$A$32+2 -> 10 | R32: =$A$32+2 -> 10 | S32: =$A$32+2 -> 10 | T32: =$A$32+2 -> 10 | U32: =$A$32+2 -> 10 | V32: =$A$32+2 -> 10 | W32: =$A$32+2 -> 10 | X32: =$A$32+3 -> 11 | Y32: =$A$32+3 -> 11 | Z32: =$A$32+3 -> 11 | AA32: =$A$32+3 -> 11 | AB32: =$A$32+3 -> 11 | AC32: =$A$32+3 -> 11 | AD32: =$A$32+3 -> 11 | AE32: =$A$32+4 -> 12 | AF32: =$A$32+4 -> 12 | AG32: =$A$32+4 -> 12 | AH32: =$A$32+4 -> 12 | AI32: =$A$32+4 -> 12 | AJ32: =$A$32+4 -> 12 | AK32: =$A$32+4 -> 12 | AL32: =$A$32+4 -> 12 | AM32: =$A$32+3 -> 11 | AN32: =$A$32+3 -> 11 | AO32: =$A$32+3 -> 11 | AP32: =$A$32+3 -> 11 | AQ32: =$A$32+4 -> 12 | AR32: =$A$32+4 -> 12 | AS32: =$A$32+4 -> 12 | AT32: =$A$32+4 -> 12 | AU32: =$A$32+4 -> 12 | AV32: =$A$32+4 -> 12 | AW32: =$A$32+4 -> 12 | AX32: =$A$32+4 -> 12
A33: 9 | B33: CAC | C33: =$A$33 -> 9 | D33: =$A$33 -> 9 | E33: =$A$33 -> 9 | F33: =$A$33 -> 9 | G33: =$A$33 -> 9 | H33: =$A$33 -> 9 | I33: =$A$33 -> 9 | J33: =$A$33 -> 9 | ... N33: =$A$33 -> 9 | O33: =$A$33*105% -> 9.45 | P33: =$A$33*105% -> 9.45 | Q33: =$A$33*105% -> 9.45 | R33: =$A$33*105% -> 9.45 | S33: =$A$33*105% -> 9.45 | T33: =$A$33*105% -> 9.45 | U33: =$A$33*105% -> 9.45 | V33: =$A$33*105% -> 9.45 | ... Z33: =$A$33*105% -> 9.45 | AA33: =$A$33*112% -> 10.08 | AB33: =$A$33*112% -> 10.08 | AC33: =$A$33*112% -> 10.08 | AD33: =$A$33*112% -> 10.08 | AE33: =$A$33*112% -> 10.08 | AF33: =$A$33*112% -> 10.08 | AG33: =$A$33*112% -> 10.08 | AH33: =$A$33*112% -> 10.08 | ... AX33: =$A$33*112% -> 10.08
B35: Расходы | C35: =SUM(C36:C41) -> 194580.26 | D35: =SUM(D36:D41) -> 183380.48 | E35: =SUM(E36:E41) -> 176975.13 | F35: =SUM(F36:F41) -> 173202.83 | G35: =SUM(G36:G41) -> 171132.98 | H35: =SUM(H36:H41) -> 170138.55 | I35: =SUM(I36:I41) -> 169792.52 | J35: =SUM(J36:J41) -> 170271.71 | ... AX35: =SUM(AX36:AX41) -> 354206.14
A36: 5300 | B36: Аренда | C36: =$A$36 -> 5300 | D36: =$A$36 -> 5300 | E36: =$A$36 -> 5300 | F36: =$A$36 -> 5300 | G36: =$A$36 -> 5300 | H36: =$A$36 -> 5300 | I36: =$A$36 -> 5300 | J36: =$A$36 -> 5300 | ... N36: =$A$36 -> 5300 | O36: =$A$36*110% -> 5830 | P36: =$A$36*110% -> 5830 | Q36: =$A$36*110% -> 5830 | R36: =$A$36*110% -> 5830 | S36: =$A$36*110% -> 5830 | T36: =$A$36*110% -> 5830 | U36: =$A$36*110% -> 5830 | V36: =$A$36*110% -> 5830 | ... Z36: =$A$36*110% -> 5830 | AA36: =$A$36*115% -> 6095 | AB36: =$A$36*115% -> 6095 | AC36: =$A$36*115% -> 6095 | AD36: =$A$36*115% -> 6095 | AE36: =$A$36*115% -> 6095 | AF36: =$A$36*115% -> 6095 | AG36: =$A$36*115% -> 6095 | AH36: =$A$36*115% -> 6095 | ... AX36: =$A$36*115% -> 6095
A37: 4000 | B37: ФОТ | C37: =$A$37*C32 -> 32000 | D37: =$A$37*D32 -> 32000 | E37: =$A$37*E32 -> 32000 | F37: =$A$37*F32 -> 32000 | G37: =$A$37*G32 -> 32000 | H37: =$A$37*H32 -> 32000 | I37: =$A$37*I32 -> 32000 | J37: =$A$37*J32 -> 32000 | ... N37: =$A$37*N32 -> 36000 | O37: =$A$37*O32*105% -> 37800 | P37: =$A$37*P32*105% -> 37800 | Q37: =$A$37*Q32*105% -> 42000 | R37: =$A$37*R32*105% -> 42000 | S37: =$A$37*S32*105% -> 42000 | T37: =$A$37*T32*105% -> 42000 | U37: =$A$37*U32*105% -> 42000 | V37: =$A$37*V32*105% -> 42000 | ... Z37: =$A$37*Z32*105% -> 46200 | AA37: =$A$37*AA32*110% -> 48400 | AB37: =$A$37*AB32*110% -> 48400 | AC37: =$A$37*AC32*110% -> 48400 | AD37: =$A$37*AD32*110% -> 48400 | AE37: =$A$37*AE32*110% -> 52800 | AF37: =$A$37*AF32*110% -> 52800 | AG37: =$A$37*AG32*110% -> 52800 | AH37: =$A$37*AH32*110% -> 52800 | ... AX37: =$A$37*AX32*110% -> 52800
B38: Бюджет на маркетинг | C38: =C14*C33 -> 40500 | D38: =D14*D33 -> 41310 | E38: =E14*E33 -> 42136.2 | F38: =F14*F33 -> 42978.924 | G38: =G14*G33 -> 43838.502 | H38: =H14*H33 -> 44715.273 | I38: =I14*I33 -> 45609.578 | J38: =J14*J33 -> 46521.77 | ... AX38: =AX14*AX33 -> 115048.54
B39: Затраты на скидки | C39: =C13*C28 -> 19473.081 | D39: =D13*D28 -> 17407.464 | E39: =E13*E28 -> 15262.779 | F39: =F13*F28 -> 13717.068 | G39: =G13*G28 -> 12546.577 | H39: =H13*H28 -> 11607.092 | I39: =I13*I28 -> 10805.713 | J39: =J13*J28 -> 10082.603 | ... AX39: =AX13*AX28 -> 19957.4
A40: 2.25 | B40: Выплаты курьерам за доставку | C40: =C21*$A$40 + C29*C31 -> 93577.183 | D40: =D21*$A$40 + D29*D31 -> 83633.012 | E40: =E21*$A$40 + E29*E31 -> 78546.149 | F40: =F21*$A$40 + F29*F31 -> 75476.838 | G40: =G21*$A$40 + G29*G31 -> 73717.903 | H40: =H21*$A$40 + H29*H31 -> 72786.19 | I40: =I21*$A$40 + I29*I31 -> 72347.228 | J40: =J21*$A$40 + J29*J31 -> 72637.338 | ... AX40: =AX21*$A$40 + AX29*AX31 -> 154415.69
B41: Прочие операционные расходы | C41: =SUM(C36:C37)*10% -> 3730 | D41: =SUM(D36:D37)*10% -> 3730 | E41: =SUM(E36:E37)*10% -> 3730 | F41: =SUM(F36:F37)*10% -> 3730 | G41: =SUM(G36:G37)*10% -> 3730 | H41: =SUM(H36:H37)*10% -> 3730 | I41: =SUM(I36:I37)*10% -> 3730 | J41: =SUM(J36:J37)*10% -> 3730 | ... AX41: =SUM(AX36:AX37)*10% -> 5889.5
B42: Прирост расходов (% к прошлому месяцу) | C42: 1 | D42: =(D35/C35)-100% -> -0.0575587 | E42: =(E35/D35)-100% -> -0.034929282 | F42: =(F35/E35)-100% -> -0.021315413 | G42: =(G35/F35)-100% -> -0.011950423 | H42: =(H35/G35)-100% -> -0.0058108577 | I42: =(I35/H35)-100% -> -0.0020338411 | J42: =(J35/I35)-100% -> 0.0028222139 | K42: =(K35/J35)-100% -> 0.014197071 | ... AX42: =(AX35/AW35)-100% -> 0.016282427
B44: EBITDA (операционная прибыль) | C44: =C9-C35 -> -8796.4119 | D44: =D9-D35 -> -17303.739 | E44: =E9-E35 -> -23270.126 | F44: =F9-F35 -> -26938.219 | G44: =G9-G35 -> -28987.789 | H44: =H9-H35 -> -29870.411 | I44: =I9-I35 -> -29881.383 | J44: =J9-J35 -> -29681.139 | ... AX44: =AX9-AX35 -> 40487.376
B45: EBITDA нарастающим итогом | C45: =C44 -> -8796.4119 | D45: =D44+C45 -> -26100.151 | E45: =E44+D45 -> -49370.277 | F45: =F44+E45 -> -76308.496 | G45: =G44+F45 -> -105296.29 | H45: =H44+G45 -> -135166.7 | I45: =I44+H45 -> -165048.08 | J45: =J44+I45 -> -194729.22 | K45: =K44+J45 -> -225435.49 | ... AX45: =AX44+AW45 -> -12605.292
B46: Рентабельность EBITDA (% от общей выручки) | C46: =C44/C9 -> -0.047347559 | D46: =D44/D9 -> -0.10419123 | E46: =E44/E9 -> -0.15139472 | F46: =F44/F9 -> -0.18417455 | G46: =G44/G9 -> -0.20393084 | H46: =H44/H9 -> -0.21295221 | I46: =I44/I9 -> -0.21357401 | J46: =J44/J9 -> -0.21111756 | ... AX46: =AX44/AX9 -> 0.10257928
B48: Прочие расходы
A49: 0.21 | B49: Налоговая нагрузка | C49: =IF(C44>0, C44*$A$49, 0) -> 0 | D49: =IF(D44>0, D44*$A$49, 0) -> 0 | E49: =IF(E44>0, E44*$A$49, 0) -> 0 | F49: =IF(F44>0, F44*$A$49, 0) -> 0 | G49: =IF(G44>0, G44*$A$49, 0) -> 0 | H49: =IF(H44>0, H44*$A$49, 0) -> 0 | I49: =IF(I44>0, I44*$A$49, 0) -> 0 | J49: =IF(J44>0, J44*$A$49, 0) -> 0 | ... AX49: =IF(AX44>0, AX44*$A$49, 0) -> 8502.349
B51: Чистая прибыль | C51: =C44-C49 -> -8796.4119 | D51: =D44-D49 -> -17303.739 | E51: =E44-E49 -> -23270.126 | F51: =F44-F49 -> -26938.219 | G51: =G44-G49 -> -28987.789 | H51: =H44-H49 -> -29870.411 | I51: =I44-I49 -> -29881.383 | J51: =J44-J49 -> -29681.139 | ... AX51: =AX44-AX49 -> 31985.027
B52: Прибыль нарастающим итогом | C52: =C51 -> -8796.4119 | D52: =C52+D51 -> -26100.151 | E52: =D52+E51 -> -49370.277 | F52: =E52+F51 -> -76308.496 | G52: =F52+G51 -> -105296.29 | H52: =G52+H51 -> -135166.7 | I52: =H52+I51 -> -165048.08 | J52: =I52+J51 -> -194729.22 | K52: =J52+K51 -> -225435.49 | ... AX52: =AW52+AX51 -> -120719.51
B53: Рентабельность чистой прибыли (%) | C53: =C51/C9 -> -0.047347559 | D53: =D51/D9 -> -0.10419123 | E53: =E51/E9 -> -0.15139472 | F53: =F51/F9 -> -0.18417455 | G53: =G51/G9 -> -0.20393084 | H53: =H51/H9 -> -0.21295221 | I53: =I51/I9 -> -0.21357401 | J53: =J51/J9 -> -0.21111756 | ... AX53: =AX51/AX9 -> 0.081037631
C57: 1 год | D57: 2 год | E57: 3 год | F57: 4 год | G57: 5 год
B58: Сумма чистой прибыли (год) | C58: -1477422 | D58: =SUM(C51:N51) -> -330118.14 | E58: =SUM(O51:Z51) -> -197316.75 | F58: =SUM(AA51:AL51) -> 108492.1 | G58: =SUM(AM51:AX51) -> 298223.28
B59: NPV | F59: =C58 + NPV(0.15, D58:F58) -> -1842345.7 | G59: =C58 + NPV(0.15, D58:G58) -> -1671835.6
B60: IRR | F60: =IRR(C58:F58) -> -0.72705508 | G60: =IRR(C58:G58) -> -0.38384749

Sheet Финмодель сценарий 2
B1: Сценарий 2: Критический | C1: Значительное снижение количества клиентов и рост стоимости привлечения, вынужденное увеличение бонусов и скидок, снижение цен и комиссии
B2: ОПиУ 2026-28 | C2: 2026 | O2: 2027 | AA2: 2028
B3: Название статьи | C3: Январь | D3: Февраль | E3: Март | F3: Апрель | G3: Май | H3: Июнь | I3: Июль | J3: Август | K3: Сентябрь | L3: Октябрь | M3: Ноябрь | N3: Декабрь | O3: Январь | P3: Февраль | Q3: Март | R3: Апрель | S3: Май | T3: Июнь | U3: Июль | V3: Август | W3: Сентябрь | X3: Октябрь | Y3: Ноябрь | Z3: Декабрь | AA3: Январь | AB3: Февраль | AC3: Март | AD3: Апрель | AE3: Май | AF3: Июнь | AG3: Июль | AH3: Август | AI3: Сентябрь | AJ3: Октябрь | AK3: Ноябрь | AL3: Декабрь
A5: 1.03 | B5: Выручка от реализации
A6: 3900 | B6: Выручка от комиссии | C6: =C21*C24*C25 -> 15727.764 | D6: =D21*D24*D25 -> 12058.466 | E6: =E21*E24*E25 -> 9909.3238 | F6: =F21*F24*F25 -> 8673.3233 | G6: =G21*G24*G25 -> 7986.2776 | H6: =H21*H24*H25 -> 7629.6959 | I6: =I21*I24*I25 -> 7472.5054 | J6: =J21*J24*J25 -> 7436.0849 | ... AL6: =AL21*AL24*AL25 -> 13218.47
B7: Выручка от подписки | C7: =C13*C26 -> 36712.8 | D7: =D13*D26 -> 28147.68 | E7: =E13*E26 -> 23131.008 | F7: =F13*F26 -> 20245.853 | G7: =G13*G26 -> 18642.105 | H7: =H13*H26 -> 17809.748 | I7: =I13*I26 -> 17442.823 | J7: =J13*J26 -> 17357.808 | ... AL7: =AL13*AL26 -> 43711.872
B8: Выручка от доставки | C8: =C21*C27 -> 64247.4 | D8: =D21*D27 -> 49258.44 | E8: =E21*E27 -> 40479.264 | F8: =F21*F27 -> 35430.242 | G8: =G21*G27 -> 32623.683 | H8: =H21*H27 -> 31167.058 | I8: =I21*I27 -> 30524.94 | J8: =J21*J27 -> 30376.164 | ... AL8: =AL21*AL27 -> 71396.058
B9: Общая выручка | C9: =SUM(C6:C8) -> 116687.96 | D9: =SUM(D6:D8) -> 89464.586 | E9: =SUM(E6:E8) -> 73519.596 | F9: =SUM(F6:F8) -> 64349.419 | G9: =SUM(G6:G8) -> 59252.065 | H9: =SUM(H6:H8) -> 56606.502 | I9: =SUM(I6:I8) -> 55440.269 | J9: =SUM(J6:J8) -> 55170.056 | ... AL9: =SUM(AL6:AL8) -> 128326.4
B10: Прирост выручки (% к прошлому месяцу) | C10: 1 | D10: =(D9/C9*100%)-100% -> -0.23330065 | E10: =(E9/D9*100%)-100% -> -0.17822684 | F10: =(F9/E9*100%)-100% -> -0.12473106 | G10: =(G9/F9*100%)-100% -> -0.079213663 | H10: =(H9/G9*100%)-100% -> -0.044649306 | I10: =(I9/H9*100%)-100% -> -0.020602455 | J10: =(J9/I9*100%)-100% -> -0.0048739372 | K10: =(K9/J9*100%)-100% -> 0.005002541 | ... AL10: =(AL9/AK9*100%)-100% -> 0.019999991
B12: Воронка продаж
A13: 0.02 | B13: Активная база клиентов | C13: =30594-30594*C15 -> 18356.4 | D13: =C13+D14-(C13*D15) -> 14073.84 | E13: =D13+E14-(D13*E15) -> 11565.504 | F13: =E13+F14-(E13*F15) -> 10122.926 | G13: =F13+G14-(F13*G15) -> 9321.0523 | H13: =G13+H14-(G13*H15) -> 8904.8738 | I13: =H13+I14-(H13*I15) -> 8721.4115 | J13: =I13+J14-(I13*J15) -> 8678.9039 | K13: =J13+K14-(J13*K15) -> 8722.3205 | ... AL13: =AK13+AL14-(AK13*AL15) -> 14570.624
A14: 3000 | B14: Новые клиенты | C14: =$A$14 -> 3000 | D14: =C14+C14*$A$13 -> 3060 | E14: =D14+D14*$A$13 -> 3121.2 | F14: =E14+E14*$A$13 -> 3183.624 | G14: =F14+F14*$A$13 -> 3247.2965 | H14: =G14+G14*$A$13 -> 3312.2424 | I14: =H14+H14*$A$13 -> 3378.4873 | J14: =I14+I14*$A$13 -> 3446.057 | K14: =J14+J14*$A$13 -> 3514.9781 | ... AL14: =AK14+AK14*$A$13 -> 5999.6687
A15: 0.4 | B15: Отток | C15: =$A$15 -> 0.4 | D15: =$A$15 -> 0.4 | E15: =$A$15 -> 0.4 | F15: =$A$15 -> 0.4 | G15: =$A$15 -> 0.4 | H15: =$A$15 -> 0.4 | I15: =$A$15 -> 0.4 | J15: =$A$15 -> 0.4 | ... AL15: =$A$15 -> 0.4
A16: 495 | B16: База шеф-поваров | C16: =$A$16 -> 495 | D16: =C16+(D14/18)-(C16*15%) -> 590.75 | E16: =D16+(E14/18)-(D16*15%) -> 675.5375 | F16: =E16+(F14/18)-(E16*15%) -> 751.07488 | G16: =F16+(G14/18)-(F16*15%) -> 818.819 | H16: =G16+(H14/18)-(G16*15%) -> 880.00962 | I16: =H16+(I14/18)-(H16*15%) -> 935.70191 | J16: =I16+(J14/18)-(I16*15%) -> 986.79424 | K16: =J16+(K14/18)-(J16*15%) -> 1034.0517 | ... AL16: =AK16+(AL14/18)-(AK16*15%) -> 1998.1797
B17: Заказчиков на одного повара | C17: =C13/C16 -> 37.083636 | D17: =D13/D16 -> 23.823682 | E17: =E13/E16 -> 17.120447 | F17: =F13/F16 -> 13.477919 | G17: =G13/G16 -> 11.383532 | H17: =H13/H16 -> 10.119064 | I17: =I13/I16 -> 9.3207157 | J17: =J13/J16 -> 8.7950493 | ... AL17: =AL13/AL16 -> 7.2919487
A18: 0.7 | B18: Процент успешных доставок | C18: =$A$18 -> 0.7 | D18: =$A$18 -> 0.7 | E18: =$A$18 -> 0.7 | F18: =$A$18 -> 0.7 | G18: =$A$18 -> 0.7 | H18: =$A$18 -> 0.7 | I18: =$A$18 -> 0.7 | J18: =$A$18 -> 0.7 | ... AL18: =$A$18 -> 0.7
A19: 2 | B19: Частотность созданных заказов | C19: =$A$19+RANDBETWEEN(-0.4, 0.1) -> 2 | D19: =$A$19+RANDBETWEEN(-0.4, 0.1) -> 2 | E19: =$A$19+RANDBETWEEN(-0.4, 0.1) -> 2 | F19: =$A$19+RANDBETWEEN(-0.4, 0.1) -> 2 | G19: =$A$19+RANDBETWEEN(-0.4, 0.1) -> 2 | H19: =$A$19+RANDBETWEEN(-0.4, 0.1) -> 2 | I19: =$A$19+RANDBETWEEN(-0.4, 0.1) -> 2 | J19: =$A$19+RANDBETWEEN(-0.4, 0.1) -> 2 | ... AL19: =$A$19+RANDBETWEEN(-0.4, 0.1) -> 2
B20: Созданные заказы | C20: =C13*C19 -> 36712.8 | D20: =D13*D19 -> 28147.68 | E20: =E13*E19 -> 23131.008 | F20: =F13*F19 -> 20245.853 | G20: =G13*G19 -> 18642.105 | H20: =H13*H19 -> 17809.748 | I20: =I13*I19 -> 17442.823 | J20: =J13*J19 -> 17357.808 | ... AL20: =AL13*AL19 -> 29141.248
B21: Выполненные заказы | C21: =C20*C18 -> 25698.96 | D21: =D20*D18 -> 19703.376 | E21: =E20*E18 -> 16191.706 | F21: =F20*F18 -> 14172.097 | G21: =G20*G18 -> 13049.473 | H21: =H20*H18 -> 12466.823 | I21: =I20*I18 -> 12209.976 | J21: =J20*J18 -> 12150.465 | ... AL21: =AL20*AL18 -> 20398.874
B23: Юнит-экономика
A24: 6.8 | B24: Средняя стоимость обеда | C24: =$A$24 -> 6.8 | D24: =$A$24 -> 6.8 | E24: =$A$24 -> 6.8 | F24: =$A$24 -> 6.8 | G24: =$A$24 -> 6.8 | H24: =$A$24 -> 6.8 | I24: =$A$24 -> 6.8 | J24: =$A$24 -> 6.8 | ... N24: =$A$24 -> 6.8 | O24: =$A$24+0.2 -> 7 | P24: =$A$24+0.2 -> 7 | Q24: =$A$24+0.2 -> 7 | R24: =$A$24+0.2 -> 7 | S24: =$A$24+0.2 -> 7 | T24: =$A$24+0.2 -> 7 | U24: =$A$24+0.2 -> 7 | V24: =$A$24+0.2 -> 7 | ... Z24: =$A$24+0.2 -> 7 | AA24: =$A$24+0.4 -> 7.2 | AB24: =$A$24+0.4 -> 7.2 | AC24: =$A$24+0.4 -> 7.2 | AD24: =$A$24+0.4 -> 7.2 | AE24: =$A$24+0.4 -> 7.2 | AF24: =$A$24+0.4 -> 7.2 | AG24: =$A$24+0.4 -> 7.2 | AH24: =$A$24+0.4 -> 7.2 | ... AL24: =$A$24+0.4 -> 7.2
A25: 0.09 | B25: Комиссия сервиса с шефов | C25: =$A$25 -> 0.09 | D25: =$A$25 -> 0.09 | E25: =$A$25 -> 0.09 | F25: =$A$25 -> 0.09 | G25: =$A$25 -> 0.09 | H25: =$A$25 -> 0.09 | I25: =$A$25 -> 0.09 | J25: =$A$25 -> 0.09 | ... AL25: =$A$25 -> 0.09
A26: 2 | B26: Стоимость подписки на сервис | C26: =$A$26 -> 2 | D26: =$A$26 -> 2 | E26: =$A$26 -> 2 | F26: =$A$26 -> 2 | G26: =$A$26 -> 2 | H26: =$A$26 -> 2 | I26: =$A$26 -> 2 | J26: =$A$26 -> 2 | ... N26: =$A$26 -> 2 | O26: =$A$26+0.5 -> 2.5 | P26: =$A$26+0.5 -> 2.5 | Q26: =$A$26+0.5 -> 2.5 | R26: =$A$26+0.5 -> 2.5 | S26: =$A$26+0.5 -> 2.5 | T26: =$A$26+0.5 -> 2.5 | U26: =$A$26+0.5 -> 2.5 | V26: =$A$26+0.5 -> 2.5 | ... Z26: =$A$26+0.5 -> 2.5 | AA26: =$A$26+1 -> 3 | AB26: =$A$26+1 -> 3 | AC26: =$A$26+1 -> 3 | AD26: =$A$26+1 -> 3 | AE26: =$A$26+1 -> 3 | AF26: =$A$26+1 -> 3 | AG26: =$A$26+1 -> 3 | AH26: =$A$26+1 -> 3 | ... AL26: =$A$26+1 -> 3
A27: 2.5 | B27: Стоимость доставки | C27: =$A$27 -> 2.5 | D27: =$A$27 -> 2.5 | E27: =$A$27 -> 2.5 | F27: =$A$27 -> 2.5 | G27: =$A$27 -> 2.5 | H27: =$A$27 -> 2.5 | I27: =$A$27 -> 2.5 | J27: =$A$27 -> 2.5 | ... N27: =$A$27 -> 2.5 | O27: =$A$27+0.5 -> 3 | P27: =$A$27+0.5 -> 3 | Q27: =$A$27+0.5 -> 3 | R27: =$A$27+0.5 -> 3 | S27: =$A$27+0.5 -> 3 | T27: =$A$27+0.5 -> 3 | U27: =$A$27+0.5 -> 3 | V27: =$A$27+0.5 -> 3 | ... Z27: =$A$27+0.5 -> 3 | AA27: =$A$27+1 -> 3.5 | AB27: =$A$27+1 -> 3.5 | AC27: =$A$27+1 -> 3.5 | AD27: =$A$27+1 -> 3.5 | AE27: =$A$27+1 -> 3.5 | AF27: =$A$27+1 -> 3.5 | AG27: =$A$27+1 -> 3.5 | AH27: =$A$27+1 -> 3.5 | ... AL27: =$A$27+1 -> 3.5
A28: 1.5 | B28: Скидки на 1 пользователя в месяц | C28: =$A$28 -> 1.5 | D28: =$A$28 -> 1.5 | E28: =D28-0.05 -> 1.45 | F28: =E28-0.05 -> 1.4 | G28: =F28-0.05 -> 1.35 | H28: =G28-0.05 -> 1.3 | I28: =H28-0.05 -> 1.25 | J28: =I28-0.05 -> 1.2 | K28: =J28-0.05 -> 1.15 | L28: =K28 -> 1.15 | M28: =L28 -> 1.15 | N28: =M28 -> 1.15 | O28: =N28 -> 1.15 | P28: =O28 -> 1.15 | Q28: =P28 -> 1.15 | R28: =Q28 -> 1.15 | S28: =R28 -> 1.15 | ... AL28: =AK28 -> 1.15
A29: 200 | B29: Бонусы на 1 курьера в месяц | C29: =$A$29 - (ROUND($C$30,0)-ROUND(C30,0))*10 -> 200 | D29: =$A$29 - (ROUND($C$30,0)-ROUND(D30,0))*10 -> 170 | E29: =$A$29 - (ROUND($C$30,0)-ROUND(E30,0))*10 -> 160 | F29: =$A$29 - (ROUND($C$30,0)-ROUND(F30,0))*10 -> 150 | G29: =$A$29 - (ROUND($C$30,0)-ROUND(G30,0))*10 -> 140 | H29: =$A$29 - (ROUND($C$30,0)-ROUND(H30,0))*10 -> 140 | I29: =$A$29 - (ROUND($C$30,0)-ROUND(I30,0))*10 -> 130 | J29: =$A$29 - (ROUND($C$30,0)-ROUND(J30,0))*10 -> 130 | ... AL29: =$A$29 - (ROUND($C$30,0)-ROUND(AL30,0))*10 -> 140
B30: Заказы в день на курьера | C30: =(C21/C31)/31 -> 8.7263022 | D30: =(D21/D31)/31 -> 6.4955828 | E30: =(E21/E31)/31 -> 4.8526324 | F30: =(F21/F31)/31 -> 3.8612349 | G30: =(G21/G31)/31 -> 3.2321567 | H30: =(H21/H31)/31 -> 2.8071301 | I30: =(I21/I31)/31 -> 2.4993603 | J30: =(J21/J31)/31 -> 2.4871786 | ... AL30: =(AL21/AL31)/31 -> 2.9235946
A31: 95 | B31: Кол-во курьеров | C31: =A31 -> 95 | D31: =C31*103% -> 97.85 | E31: =D31*110% -> 107.635 | F31: =E31*110% -> 118.3985 | G31: =F31*110% -> 130.23835 | H31: =G31*110% -> 143.26219 | I31: =H31*110% -> 157.5884 | J31: =I31 -> 157.5884 | K31: =J31 -> 157.5884 | L31: =K31 -> 157.5884 | M31: =L31 -> 157.5884 | N31: =M31 -> 157.5884 | O31: =N31 -> 157.5884 | P31: =O31 -> 157.5884 | Q31: =P31 -> 157.5884 | ... T31: =S31 -> 157.5884 | U31: =T31*102% -> 160.74017 | V31: =U31*102% -> 163.95498 | W31: =V31*102% -> 167.23407 | X31: =W31*102% -> 170.57876 | Y31: =X31*102% -> 173.99033 | Z31: =Y31*102% -> 177.47014 | AA31: =Z31*102% -> 181.01954 | AB31: =AA31*102% -> 184.63993 | ... AL31: =AK31*102% -> 225.07505
A32: 8 | B32: Кол-во сотрудников | C32: =$A$32 -> 8 | D32: =$A$32 -> 8 | E32: =$A$32 -> 8 | F32: =$A$32 -> 8 | G32: =$A$32 -> 8 | H32: =$A$32 -> 8 | I32: =$A$32 -> 8 | J32: =$A$32 -> 8 | K32: =$A$32 -> 8 | L32: =$A$32+1 -> 9 | M32: =$A$32+1 -> 9 | N32: =$A$32+1 -> 9 | O32: =$A$32+1 -> 9 | P32: =$A$32+1 -> 9 | Q32: =$A$32+2 -> 10 | R32: =$A$32+2 -> 10 | S32: =$A$32+2 -> 10 | T32: =$A$32+2 -> 10 | U32: =$A$32+2 -> 10 | V32: =$A$32+2 -> 10 | W32: =$A$32+2 -> 10 | X32: =$A$32+3 -> 11 | Y32: =$A$32+3 -> 11 | Z32: =$A$32+3 -> 11 | AA32: =$A$32+3 -> 11 | AB32: =$A$32+3 -> 11 | AC32: =$A$32+3 -> 11 | AD32: =$A$32+3 -> 11 | AE32: =$A$32+4 -> 12 | AF32: =$A$32+4 -> 12 | AG32: =$A$32+4 -> 12 | AH32: =$A$32+4 -> 12 | AI32: =$A$32+4 -> 12 | AJ32: =$A$32+4 -> 12 | AK32: =$A$32+4 -> 12 | AL32: =$A$32+4 -> 12
A33: 14 | B33: CAC | C33: =$A$33 -> 14 | D33: =$A$33 -> 14 | E33: =$A$33 -> 14 | F33: =$A$33 -> 14 | G33: =$A$33 -> 14 | H33: =$A$33 -> 14 | I33: =$A$33 -> 14 | J33: =$A$33 -> 14 | ... N33: =$A$33 -> 14 | O33: =$A$33*105% -> 14.7 | P33: =$A$33*105% -> 14.7 | Q33: =$A$33*105% -> 14.7 | R33: =$A$33*105% -> 14.7 | S33: =$A$33*105% -> 14.7 | T33: =$A$33*105% -> 14.7 | U33: =$A$33*105% -> 14.7 | V33: =$A$33*105% -> 14.7 | ... Z33: =$A$33*105% -> 14.7 | AA33: =$A$33*112% -> 15.68 | AB33: =$A$33*112% -> 15.68 | AC33: =$A$33*112% -> 15.68 | AD33: =$A$33*112% -> 15.68 | AE33: =$A$33*112% -> 15.68 | AF33: =$A$33*112% -> 15.68 | AG33: =$A$33*112% -> 15.68 | AH33: =$A$33*112% -> 15.68 | ... AL33: =$A$33*112% -> 15.68
B35: Расходы | C35: =SUM(C36:C41) -> 187387.26 | D35: =SUM(D36:D41) -> 165947.86 | E35: =SUM(E36:E41) -> 155149.72 | F35: =SUM(F36:F41) -> 149419.83 | G35: =SUM(G36:G41) -> 146670.26 | H35: =SUM(H36:H41) -> 147084.79 | I35: =SUM(I36:I41) -> 147189.52 | J35: =SUM(J36:J41) -> 147514.52 | ... AL35: =SUM(AL36:AL41) -> 253023.49
A36: 5300 | B36: Аренда | C36: =$A$36 -> 5300 | D36: =$A$36 -> 5300 | E36: =$A$36 -> 5300 | F36: =$A$36 -> 5300 | G36: =$A$36 -> 5300 | H36: =$A$36 -> 5300 | I36: =$A$36 -> 5300 | J36: =$A$36 -> 5300 | ... N36: =$A$36 -> 5300 | O36: =$A$36*110% -> 5830 | P36: =$A$36*110% -> 5830 | Q36: =$A$36*110% -> 5830 | R36: =$A$36*110% -> 5830 | S36: =$A$36*110% -> 5830 | T36: =$A$36*110% -> 5830 | U36: =$A$36*110% -> 5830 | V36: =$A$36*110% -> 5830 | ... Z36: =$A$36*110% -> 5830 | AA36: =$A$36*115% -> 6095 | AB36: =$A$36*115% -> 6095 | AC36: =$A$36*115% -> 6095 | AD36: =$A$36*115% -> 6095 | AE36: =$A$36*115% -> 6095 | AF36: =$A$36*115% -> 6095 | AG36: =$A$36*115% -> 6095 | AH36: =$A$36*115% -> 6095 | ... AL36: =$A$36*115% -> 6095
A37: 4000 | B37: ФОТ | C37: =$A$37*C32 -> 32000 | D37: =$A$37*D32 -> 32000 | E37: =$A$37*E32 -> 32000 | F37: =$A$37*F32 -> 32000 | G37: =$A$37*G32 -> 32000 | H37: =$A$37*H32 -> 32000 | I37: =$A$37*I32 -> 32000 | J37: =$A$37*J32 -> 32000 | ... N37: =$A$37*N32 -> 36000 | O37: =$A$37*O32*105% -> 37800 | P37: =$A$37*P32*105% -> 37800 | Q37: =$A$37*Q32*105% -> 42000 | R37: =$A$37*R32*105% -> 42000 | S37: =$A$37*S32*105% -> 42000 | T37: =$A$37*T32*105% -> 42000 | U37: =$A$37*U32*105% -> 42000 | V37: =$A$37*V32*105% -> 42000 | ... Z37: =$A$37*Z32*105% -> 46200 | AA37: =$A$37*AA32*110% -> 48400 | AB37: =$A$37*AB32*110% -> 48400 | AC37: =$A$37*AC32*110% -> 48400 | AD37: =$A$37*AD32*110% -> 48400 | AE37: =$A$37*AE32*110% -> 52800 | AF37: =$A$37*AF32*110% -> 52800 | AG37: =$A$37*AG32*110% -> 52800 | AH37: =$A$37*AH32*110% -> 52800 | ... AL37: =$A$37*AL32*110% -> 52800
B38: Бюджет на маркетинг | C38: =C14*C33 -> 42000 | D38: =D14*D33 -> 42840 | E38: =E14*E33 -> 43696.8 | F38: =F14*F33 -> 44570.736 | G38: =G14*G33 -> 45462.151 | H38: =H14*H33 -> 46371.394 | I38: =I14*I33 -> 47298.822 | J38: =J14*J33 -> 48244.798 | ... AL38: =AL14*AL33 -> 94074.805
B39: Затраты на скидки | C39: =C13*C28 -> 27534.6 | D39: =D13*D28 -> 21110.76 | E39: =E13*E28 -> 16769.981 | F39: =F13*F28 -> 14172.097 | G39: =G13*G28 -> 12583.421 | H39: =H13*H28 -> 11576.336 | I39: =I13*I28 -> 10901.764 | J39: =J13*J28 -> 10414.685 | ... AL39: =AL13*AL28 -> 16756.218
A40: 2.25 | B40: Выплаты курьерам за доставку | C40: =C21*$A$40 + C29*C31 -> 76822.66 | D40: =D21*$A$40 + D29*D31 -> 60967.096 | E40: =E21*$A$40 + E29*E31 -> 53652.938 | F40: =F21*$A$40 + F29*F31 -> 49646.993 | G40: =G21*$A$40 + G29*G31 -> 47594.684 | H40: =H21*$A$40 + H29*H31 -> 48107.058 | I40: =I21*$A$40 + I29*I31 -> 47958.939 | J40: =J21*$A$40 + J29*J31 -> 47825.04 | ... AL40: =AL21*$A$40 + AL29*AL31 -> 77407.972
B41: Прочие операционные расходы | C41: =SUM(C36:C37)*10% -> 3730 | D41: =SUM(D36:D37)*10% -> 3730 | E41: =SUM(E36:E37)*10% -> 3730 | F41: =SUM(F36:F37)*10% -> 3730 | G41: =SUM(G36:G37)*10% -> 3730 | H41: =SUM(H36:H37)*10% -> 3730 | I41: =SUM(I36:I37)*10% -> 3730 | J41: =SUM(J36:J37)*10% -> 3730 | ... AL41: =SUM(AL36:AL37)*10% -> 5889.5
B42: Прирост расходов (% к прошлому месяцу) | C42: 1 | D42: =(D35/C35)-100% -> -0.11441228 | E42: =(E35/D35)-100% -> -0.065069461 | F42: =(F35/E35)-100% -> -0.036931374 | G42: =(G35/F35)-100% -> -0.018401647 | H42: =(H35/G35)-100% -> 0.0028262915 | I42: =(I35/H35)-100% -> 0.0007120844 | J42: =(J35/I35)-100% -> 0.0022080222 | K42: =(K35/J35)-100% -> 0.0048648907 | ... AL42: =(AL35/AK35)-100% -> 0.014803363
B44: EBITDA (операционная прибыль) | C44: =C9-C35 -> -70699.296 | D44: =D9-D35 -> -76483.27 | E44: =E9-E35 -> -81630.123 | F44: =F9-F35 -> -85070.408 | G44: =G9-G35 -> -87418.19 | H44: =H9-H35 -> -90478.286 | I44: =I9-I35 -> -91749.256 | J44: =J9-J35 -> -92344.466 | ... AL44: =AL9-AL35 -> -124697.09
B45: EBITDA нарастающим итогом | C45: =C44 -> -70699.296 | D45: =D44+C45 -> -147182.57 | E45: =E44+D45 -> -228812.69 | F45: =F44+E45 -> -313883.1 | G45: =G44+F45 -> -401301.29 | H45: =H44+G45 -> -491779.57 | I45: =I44+H45 -> -583528.83 | J45: =J44+I45 -> -675873.29 | K45: =K44+J45 -> -768659.41 | ... AL45: =AL44+AK45 -> -3727320.3
B46: Рентабельность EBITDA (% от общей выручки) | C46: =C44/C9 -> -0.60588337 | D46: =D44/D9 -> -0.85489995 | E46: =E44/E9 -> -1.1103179 | F46: =F44/F9 -> -1.3220074 | G46: =G44/G9 -> -1.4753611 | H46: =H44/H9 -> -1.5983727 | I46: =I44/I9 -> -1.6549208 | J46: =J44/J9 -> -1.673815 | ... AL46: =AL44/AL9 -> -0.97171816
B48: Прочие расходы
A49: 0.21 | B49: Налоговая нагрузка | C49: =IF(C44>0, C44*$A$49, 0) -> 0 | D49: =IF(D44>0, D44*$A$49, 0) -> 0 | E49: =IF(E44>0, E44*$A$49, 0) -> 0 | F49: =IF(F44>0, F44*$A$49, 0) -> 0 | G49: =IF(G44>0, G44*$A$49, 0) -> 0 | H49: =IF(H44>0, H44*$A$49, 0) -> 0 | I49: =IF(I44>0, I44*$A$49, 0) -> 0 | J49: =IF(J44>0, J44*$A$49, 0) -> 0 | ... AL49: =IF(AL44>0, AL44*$A$49, 0) -> 0
B51: Чистая прибыль | C51: =C44-C49 -> -70699.296 | D51: =D44-D49 -> -76483.27 | E51: =E44-E49 -> -81630.123 | F51: =F44-F49 -> -85070.408 | G51: =G44-G49 -> -87418.19 | H51: =H44-H49 -> -90478.286 | I51: =I44-I49 -> -91749.256 | J51: =J44-J49 -> -92344.466 | ... AL51: =AL44-AL49 -> -124697.09
B52: Прибыль нарастающим итогом | C52: =C51 -> -70699.296 | D52: =C52+D51 -> -147182.57 | E52: =D52+E51 -> -228812.69 | F52: =E52+F51 -> -313883.1 | G52: =F52+G51 -> -401301.29 | H52: =G52+H51 -> -491779.57 | I52: =H52+I51 -> -583528.83 | J52: =I52+J51 -> -675873.29 | K52: =J52+K51 -> -768659.41 | ... AL52: =AK52+AL51 -> -3727320.3
B53: Рентабельность чистой прибыли (%) | C53: =C51/C9 -> -0.60588337 | D53: =D51/D9 -> -0.85489995 | E53: =E51/E9 -> -1.1103179 | F53: =F51/F9 -> -1.3220074 | G53: =G51/G9 -> -1.4753611 | H53: =H51/H9 -> -1.5983727 | I53: =I51/I9 -> -1.6549208 | J53: =J51/J9 -> -1.673815 | ... AL53: =AL51/AL9 -> -0.97171816
C57: 1 год | D57: 2 год | E57: 3 год | F57: 4 год
B58: Сумма чистой прибыли (год) | C58: -1477422 | D58: =SUM(C51:N51) -> -1069492.2 | E58: =SUM(O51:Z51) -> -1253506.7 | F58: =SUM(AA51:AL51) -> -1404321.5
B59: NPV | F59: =C58 + NPV(0.15, D58:F58) -> -4278610.5
B60: IRR | F60: =IRR(C58:F58) -> #NUM!

Sheet Финмодель сценарий 2 (ред)
B1: Сценарий 2: Критический | C1: Пересчет 2 сценария с учетом упора бизнеса на повышение качества продукта
B2: ОПиУ 2026-28 | C2: 2026 | O2: 2027 | AA2: 2028 | AM2: 2029
B3: Название статьи | C3: Январь | D3: Февраль | E3: Март | F3: Апрель | G3: Май | H3: Июнь | I3: Июль | J3: Август | K3: Сентябрь | L3: Октябрь | M3: Ноябрь | N3: Декабрь | O3: Январь | P3: Февраль | Q3: Март | R3: Апрель | S3: Май | T3: Июнь | U3: Июль | V3: Август | W3: Сентябрь | X3: Октябрь | Y3: Ноябрь | Z3: Декабрь | AA3: Январь | AB3: Февраль | AC3: Март | AD3: Апрель | AE3: Май | AF3: Июнь | AG3: Июль | AH3: Август | AI3: Сентябрь | AJ3: Октябрь | AK3: Ноябрь | AL3: Декабрь | AM3: Январь | AN3: Февраль | AO3: Март | AP3: Апрель | AQ3: Май | AR3: Июнь | AS3: Июль | AT3: Август | AU3: Сентябрь | AV3: Октябрь | AW3: Ноябрь | AX3: Декабрь
A5: 1.03 | B5: Выручка от реализации
A6: 3900 | B6: Выручка от комиссии | C6: =C21*C24*C25 -> 19322.681 | D6: =D21*D24*D25 -> 14909.425 | E6: =E21*E24*E25 -> 12427.262 | F6: =F21*F24*F25 -> 11112.044 | G6: =G21*G24*G25 -> 10505.698 | H6: =H21*H24*H25 -> 10333.814 | I6: =I21*I24*I25 -> 10432.203 | J6: =J21*J24*J25 -> 10702.832 | ... AX6: =AX21*AX24*AX25 -> 146353.69
B7: Выручка от подписки | C7: =C13*C26 -> 36712.8 | D7: =D13*D26 -> 28327.68 | E7: =E13*E26 -> 23611.608 | F7: =F13*F26 -> 21112.715 | G7: =G13*G26 -> 19960.666 | H7: =H13*H26 -> 19634.089 | I7: =I13*I26 -> 19821.027 | J7: =J13*J26 -> 20335.219 | ... AX7: =AX13*AX26 -> 303120.46
B8: Выручка от доставки | C8: =C21*C27 -> 78932.52 | D8: =D21*D27 -> 60904.512 | E8: =E21*E27 -> 50764.957 | F8: =F21*F27 -> 45392.337 | G8: =G21*G27 -> 42915.433 | H8: =H21*H27 -> 42213.292 | I8: =I21*I27 -> 42615.209 | J8: =J21*J27 -> 43720.721 | ... AX8: =AX21*AX27 -> 660624.29
B9: Общая выручка | C9: =SUM(C6:C8) -> 134968 | D9: =SUM(D6:D8) -> 104141.62 | E9: =SUM(E6:E8) -> 86803.827 | F9: =SUM(F6:F8) -> 77617.096 | G9: =SUM(G6:G8) -> 73381.797 | H9: =SUM(H6:H8) -> 72181.195 | I9: =SUM(I6:I8) -> 72868.439 | J9: =SUM(J6:J8) -> 74758.772 | ... AX9: =SUM(AX6:AX8) -> 1110098.4
B10: Прирост выручки (% к прошлому месяцу) | C10: 1 | D10: =(D9/C9*100%)-100% -> -0.22839773 | E10: =(E9/D9*100%)-100% -> -0.16648282 | F10: =(F9/E9*100%)-100% -> -0.10583325 | G10: =(G9/F9*100%)-100% -> -0.05456657 | H10: =(H9/G9*100%)-100% -> -0.016361036 | I10: =(I9/H9*100%)-100% -> 0.0095211018 | J10: =(J9/I9*100%)-100% -> 0.025941722 | K10: =(K9/J9*100%)-100% -> 0.035930033 | ... AX10: =(AX9/AW9*100%)-100% -> 0.050003908
B12: Воронка продаж
A13: 0.05 | B13: Активная база клиентов | C13: =30594-30594*C15 -> 18356.4 | D13: =C13+D14-(C13*D15) -> 14163.84 | E13: =D13+E14-(D13*E15) -> 11805.804 | F13: =E13+F14-(E13*F15) -> 10556.357 | G13: =F13+G14-(F13*G15) -> 9980.3332 | H13: =G13+H14-(G13*H15) -> 9817.0446 | I13: =H13+I14-(H13*I15) -> 9910.5137 | J13: =I13+J14-(I13*J15) -> 10167.609 | K13: =J13+K14-(J13*K15) -> 10532.932 | ... AX13: =AW13+AX14-(AW13*AX15) -> 89153.076
A14: 3000 | B14: Новые клиенты | C14: =$A$14 -> 3000 | D14: =C14+C14*$A$13 -> 3150 | E14: =D14+D14*$A$13 -> 3307.5 | F14: =E14+E14*$A$13 -> 3472.875 | G14: =F14+F14*$A$13 -> 3646.5188 | H14: =G14+G14*$A$13 -> 3828.8447 | I14: =H14+H14*$A$13 -> 4020.2869 | J14: =I14+I14*$A$13 -> 4221.3013 | K14: =J14+J14*$A$13 -> 4432.3663 | ... AX14: =AW14+AW14*$A$13 -> 29717.913
A15: 0.4 | B15: Отток | C15: =$A$15 -> 0.4 | D15: =$A$15 -> 0.4 | E15: =$A$15 -> 0.4 | F15: =$A$15 -> 0.4 | G15: =$A$15 -> 0.4 | H15: =$A$15 -> 0.4 | I15: =$A$15 -> 0.4 | J15: =$A$15 -> 0.4 | ... N15: =$A$15 -> 0.4 | O15: 0.35 | P15: =O15 -> 0.35 | Q15: =P15 -> 0.35 | R15: =Q15 -> 0.35 | S15: =R15 -> 0.35 | T15: =S15 -> 0.35 | U15: =T15 -> 0.35 | V15: =U15 -> 0.35 | W15: =V15 -> 0.35 | ... Z15: =Y15 -> 0.35 | AA15: 0.3 | AB15: =AA15 -> 0.3 | AC15: =AB15 -> 0.3 | AD15: =AC15 -> 0.3 | AE15: =AD15 -> 0.3 | AF15: =AE15 -> 0.3 | AG15: =AF15 -> 0.3 | AH15: =AG15 -> 0.3 | AI15: =AH15 -> 0.3 | ... AX15: =AW15 -> 0.3
A16: 495 | B16: База шеф-поваров | C16: =$A$16 -> 495 | D16: =C16+(D14/18)-(C16*15%) -> 595.75 | E16: =D16+(E14/18)-(D16*15%) -> 690.1375 | F16: =E16+(F14/18)-(E16*15%) -> 779.55438 | G16: =F16+(G14/18)-(F16*15%) -> 865.20559 | H16: =G16+(H14/18)-(G16*15%) -> 948.13835 | I16: =H16+(I14/18)-(H16*15%) -> 1029.2669 | J16: =I16+(J14/18)-(I16*15%) -> 1109.3936 | K16: =J16+(K14/18)-(J16*15%) -> 1189.2271 | ... AX16: =AW16+(AX14/18)-(AW16*15%) -> 8667.5417
B17: Заказчиков на одного повара | C17: =C13/C16 -> 37.083636 | D17: =D13/D16 -> 23.774805 | E17: =E13/E16 -> 17.106452 | F17: =F13/F16 -> 13.541528 | G17: =G13/G16 -> 11.535216 | H17: =H13/H16 -> 10.354021 | I17: =I13/I16 -> 9.6287114 | J17: =J13/J16 -> 9.1650156 | ... AX17: =AX13/AX16 -> 10.285855
A18: 0.86 | B18: Процент успешных доставок | C18: =$A$18 -> 0.86 | D18: =$A$18 -> 0.86 | E18: =$A$18 -> 0.86 | F18: =$A$18 -> 0.86 | G18: =$A$18 -> 0.86 | H18: =$A$18 -> 0.86 | I18: =$A$18 -> 0.86 | J18: =$A$18 -> 0.86 | ... N18: =$A$18 -> 0.86 | O18: 0.9 | P18: =O18 -> 0.9 | Q18: =P18 -> 0.9 | R18: =Q18 -> 0.9 | S18: =R18 -> 0.9 | T18: =S18 -> 0.9 | U18: =T18 -> 0.9 | V18: =U18 -> 0.9 | W18: =V18 -> 0.9 | ... Z18: =Y18 -> 0.9 | AA18: 0.95 | AB18: =AA18 -> 0.95 | AC18: =AB18 -> 0.95 | AD18: =AC18 -> 0.95 | AE18: =AD18 -> 0.95 | AF18: =AE18 -> 0.95 | AG18: =AF18 -> 0.95 | AH18: =AG18 -> 0.95 | AI18: =AH18 -> 0.95 | ... AX18: =AW18 -> 0.95
A19: 2 | B19: Частотность созданных заказов | C19: =$A$19+RANDBETWEEN(-0.4, 0.1) -> 2 | D19: =$A$19+RANDBETWEEN(-0.4, 0.1) -> 2 | E19: =$A$19+RANDBETWEEN(-0.4, 0.1) -> 2 | F19: =$A$19+RANDBETWEEN(-0.4, 0.1) -> 2 | G19: =$A$19+RANDBETWEEN(-0.4, 0.1) -> 2 | H19: =$A$19+RANDBETWEEN(-0.4, 0.1) -> 2 | I19: =$A$19+RANDBETWEEN(-0.4, 0.1) -> 2 | J19: =$A$19+RANDBETWEEN(-0.4, 0.1) -> 2 | ... AX19: =$A$19+RANDBETWEEN(-0.4, 0.1) -> 2
B20: Созданные заказы | C20: =C13*C19 -> 36712.8 | D20: =D13*D19 -> 28327.68 | E20: =E13*E19 -> 23611.608 | F20: =F13*F19 -> 21112.715 | G20: =G13*G19 -> 19960.666 | H20: =H13*H19 -> 19634.089 | I20: =I13*I19 -> 19821.027 | J20: =J13*J19 -> 20335.219 | ... AX20: =AX13*AX19 -> 178306.15
B21: Выполненные заказы | C21: =C20*C18 -> 31573.008 | D21: =D20*D18 -> 24361.805 | E21: =E20*E18 -> 20305.983 | F21: =F20*F18 -> 18156.935 | G21: =G20*G18 -> 17166.173 | H21: =H20*H18 -> 16885.317 | I21: =I20*I18 -> 17046.084 | J21: =J20*J18 -> 17488.288 | ... AX21: =AX20*AX18 -> 169390.84
B23: Юнит-экономика
A24: 6.8 | B24: Средняя стоимость обеда | C24: =$A$24 -> 6.8 | D24: =$A$24 -> 6.8 | E24: =$A$24 -> 6.8 | F24: =$A$24 -> 6.8 | G24: =$A$24 -> 6.8 | H24: =$A$24 -> 6.8 | I24: =$A$24 -> 6.8 | J24: =$A$24 -> 6.8 | ... N24: =$A$24 -> 6.8 | O24: =$A$24+0.2 -> 7 | P24: =$A$24+0.2 -> 7 | Q24: =$A$24+0.2 -> 7 | R24: =$A$24+0.2 -> 7 | S24: =$A$24+0.2 -> 7 | T24: =$A$24+0.2 -> 7 | U24: =$A$24+0.2 -> 7 | V24: =$A$24+0.2 -> 7 | ... Z24: =$A$24+0.2 -> 7 | AA24: =$A$24+0.4 -> 7.2 | AB24: =$A$24+0.4 -> 7.2 | AC24: =$A$24+0.4 -> 7.2 | AD24: =$A$24+0.4 -> 7.2 | AE24: =$A$24+0.4 -> 7.2 | AF24: =$A$24+0.4 -> 7.2 | AG24: =$A$24+0.4 -> 7.2 | AH24: =$A$24+0.4 -> 7.2 | ... AX24: =$A$24+0.4 -> 7.2
A25: 0.09 | B25: Комиссия сервиса с шефов | C25: =$A$25 -> 0.09 | D25: =$A$25 -> 0.09 | E25: =$A$25 -> 0.09 | F25: =$A$25 -> 0.09 | G25: =$A$25 -> 0.09 | H25: =$A$25 -> 0.09 | I25: =$A$25 -> 0.09 | J25: =$A$25 -> 0.09 | ... N25: =$A$25 -> 0.09 | O25: 0.11 | P25: =O25 -> 0.11 | Q25: =P25 -> 0.11 | R25: =Q25 -> 0.11 | S25: =R25 -> 0.11 | T25: =S25 -> 0.11 | U25: =T25 -> 0.11 | V25: =U25 -> 0.11 | W25: =V25 -> 0.11 | ... Z25: =Y25 -> 0.11 | AA25: 0.12 | AB25: =AA25 -> 0.12 | AC25: =AB25 -> 0.12 | AD25: =AC25 -> 0.12 | AE25: =AD25 -> 0.12 | AF25: =AE25 -> 0.12 | AG25: =AF25 -> 0.12 | AH25: =AG25 -> 0.12 | AI25: =AH25 -> 0.12 | ... AX25: =AW25 -> 0.12
A26: 2 | B26: Стоимость подписки на сервис | C26: =$A$26 -> 2 | D26: =$A$26 -> 2 | E26: =$A$26 -> 2 | F26: =$A$26 -> 2 | G26: =$A$26 -> 2 | H26: =$A$26 -> 2 | I26: =$A$26 -> 2 | J26: =$A$26 -> 2 | ... N26: =$A$26 -> 2 | O26: =$A$26+0.7 -> 2.7 | P26: =$A$26+0.7 -> 2.7 | Q26: =$A$26+0.7 -> 2.7 | R26: =$A$26+0.7 -> 2.7 | S26: =$A$26+0.7 -> 2.7 | T26: =$A$26+0.7 -> 2.7 | U26: =$A$26+0.7 -> 2.7 | V26: =$A$26+0.7 -> 2.7 | ... Z26: =$A$26+0.7 -> 2.7 | AA26: =$A$26+1.4 -> 3.4 | AB26: =$A$26+1.4 -> 3.4 | AC26: =$A$26+1.4 -> 3.4 | AD26: =$A$26+1.4 -> 3.4 | AE26: =$A$26+1.4 -> 3.4 | AF26: =$A$26+1.4 -> 3.4 | AG26: =$A$26+1.4 -> 3.4 | AH26: =$A$26+1.4 -> 3.4 | ... AX26: =$A$26+1.4 -> 3.4
A27: 2.5 | B27: Стоимость доставки | C27: =$A$27 -> 2.5 | D27: =$A$27 -> 2.5 | E27: =$A$27 -> 2.5 | F27: =$A$27 -> 2.5 | G27: =$A$27 -> 2.5 | H27: =$A$27 -> 2.5 | I27: =$A$27 -> 2.5 | J27: =$A$27 -> 2.5 | ... N27: =$A$27 -> 2.5 | O27: =$A$27+0.7 -> 3.2 | P27: =$A$27+0.7 -> 3.2 | Q27: =$A$27+0.7 -> 3.2 | R27: =$A$27+0.7 -> 3.2 | S27: =$A$27+0.7 -> 3.2 | T27: =$A$27+0.7 -> 3.2 | U27: =$A$27+0.7 -> 3.2 | V27: =$A$27+0.7 -> 3.2 | ... Z27: =$A$27+0.7 -> 3.2 | AA27: =$A$27+1.4 -> 3.9 | AB27: =$A$27+1.4 -> 3.9 | AC27: =$A$27+1.4 -> 3.9 | AD27: =$A$27+1.4 -> 3.9 | AE27: =$A$27+1.4 -> 3.9 | AF27: =$A$27+1.4 -> 3.9 | AG27: =$A$27+1.4 -> 3.9 | AH27: =$A$27+1.4 -> 3.9 | ... AX27: =$A$27+1.4 -> 3.9
A28: 1.5 | B28: Скидки на 1 пользователя в месяц | C28: =$A$28 -> 1.5 | D28: =$A$28 -> 1.5 | E28: =D28-0.05 -> 1.45 | F28: =E28-0.05 -> 1.4 | G28: =F28-0.05 -> 1.35 | H28: =G28-0.05 -> 1.3 | I28: =H28-0.05 -> 1.25 | J28: =I28-0.05 -> 1.2 | K28: =J28-0.05 -> 1.15 | L28: =K28 -> 1.15 | M28: =L28 -> 1.15 | N28: =M28 -> 1.15 | O28: =N28 -> 1.15 | P28: =O28 -> 1.15 | Q28: =P28 -> 1.15 | R28: =Q28 -> 1.15 | S28: =R28 -> 1.15 | ... AX28: =AW28 -> 1.15
B29: Бонусы на 1 курьера в месяц | C29: =$A$29 - (ROUND($C$30,0)-ROUND(C30,0))*10 -> 0 | D29: =$A$29 - (ROUND($C$30,0)-ROUND(D30,0))*10 -> -30 | E29: =$A$29 - (ROUND($C$30,0)-ROUND(E30,0))*10 -> -20 | F29: =$A$29 - (ROUND($C$30,0)-ROUND(F30,0))*10 -> -10 | G29: =$A$29 - (ROUND($C$30,0)-ROUND(G30,0))*10 -> -30 | H29: =$A$29 - (ROUND($C$30,0)-ROUND(H30,0))*10 -> -20 | I29: =$A$29 - (ROUND($C$30,0)-ROUND(I30,0))*10 -> -20 | J29: =$A$29 - (ROUND($C$30,0)-ROUND(J30,0))*10 -> 0 | ... AX29: =$A$29 - (ROUND($C$30,0)-ROUND(AX30,0))*10 -> 20
B30: Заказы в день на курьера | C30: =(C21/C31)/31 -> 8.8563837 | D30: =(D21/D31)/31 -> 6.1395677 | E30: =(E21/E31)/31 -> 6.6164819 | F30: =(F21/F31)/31 -> 7.9149672 | G30: =(G21/G31)/31 -> 6.1527502 | H30: =(H21/H31)/31 -> 7.2625018 | I30: =(I21/I31)/31 -> 7.2351798 | J30: =(J21/J31)/31 -> 8.8146614 | ... AX30: =(AX21/AX31)/31 -> 10.983358
A31: 95 | B31: Кол-во курьеров | C31: 115 | D31: 128 | E31: 99 | F31: 74 | G31: 90 | H31: 75 | I31: 76 | J31: 64 | K31: 74 | L31: 77 | M31: 96 | N31: 75 | O31: 87 | P31: 104 | Q31: 133 | R31: 117 | S31: 161 | T31: 144 | U31: 165 | V31: 173 | W31: 167 | X31: 207 | Y31: 201 | Z31: 176 | AA31: 184 | AB31: 199 | AC31: 284 | AD31: 327 | AE31: 266 | AF31: 281 | AG31: 355 | AH31: 405 | AI31: 328 | AJ31: 345 | AK31: 326 | AL31: 342 | AM31: 379 | AN31: 389.77273 | AO31: 400.54545 | AP31: 411.31818 | AQ31: 422.09091 | AR31: 432.86364 | AS31: 443.63636 | AT31: 454.40909 | AU31: 465.18182 | AV31: 475.95455 | AW31: 486.72727 | AX31: 497.5
A32: 8 | B32: Кол-во сотрудников | C32: =$A$32 -> 8 | D32: =$A$32 -> 8 | E32: =$A$32 -> 8 | F32: =$A$32 -> 8 | G32: =$A$32 -> 8 | H32: =$A$32 -> 8 | I32: =$A$32 -> 8 | J32: =$A$32 -> 8 | K32: =$A$32 -> 8 | L32: =$A$32+1 -> 9 | M32: =$A$32+1 -> 9 | N32: =$A$32+1 -> 9 | O32: =$A$32+1 -> 9 | P32: =$A$32+1 -> 9 | Q32: =$A$32+2 -> 10 | R32: =$A$32+2 -> 10 | S32: =$A$32+2 -> 10 | T32: =$A$32+2 -> 10 | U32: =$A$32+2 -> 10 | V32: =$A$32+2 -> 10 | W32: =$A$32+2 -> 10 | X32: =$A$32+3 -> 11 | Y32: =$A$32+3 -> 11 | Z32: =$A$32+3 -> 11 | AA32: =$A$32+3 -> 11 | AB32: =$A$32+3 -> 11 | AC32: =$A$32+3 -> 11 | AD32: =$A$32+3 -> 11 | AE32: =$A$32+4 -> 12 | AF32: =$A$32+4 -> 12 | AG32: =$A$32+4 -> 12 | AH32: =$A$32+4 -> 12 | AI32: =$A$32+4 -> 12 | AJ32: =$A$32+4 -> 12 | AK32: =$A$32+4 -> 12 | AL32: =$A$32+4 -> 12 | AM32: =$A$32+3 -> 11 | AN32: =$A$32+3 -> 11 | AO32: =$A$32+3 -> 11 | AP32: =$A$32+4 -> 12 | AQ32: =$A$32+4 -> 12 | AR32: =$A$32+4 -> 12 | AS32: =$A$32+4 -> 12 | AT32: =$A$32+4 -> 12 | AU32: =$A$32+4 -> 12 | AV32: =$A$32+4 -> 12 | AW32: =$A$32+4 -> 12 | AX32: =$A$32+3 -> 11
A33: 14 | B33: CAC | C33: =$A$33 -> 14 | D33: =$A$33 -> 14 | E33: =$A$33 -> 14 | F33: =$A$33 -> 14 | G33: =$A$33 -> 14 | H33: =$A$33 -> 14 | I33: =$A$33 -> 14 | J33: =$A$33 -> 14 | ... N33: =$A$33 -> 14 | O33: =$A$33*105% -> 14.7 | P33: =$A$33*105% -> 14.7 | Q33: =$A$33*105% -> 14.7 | R33: =$A$33*105% -> 14.7 | S33: =$A$33*105% -> 14.7 | T33: =$A$33*105% -> 14.7 | U33: =$A$33*105% -> 14.7 | V33: =$A$33*105% -> 14.7 | ... Z33: =$A$33*105% -> 14.7 | AA33: =$A$33*112% -> 15.68 | AB33: =$A$33*112% -> 15.68 | AC33: =$A$33*112% -> 15.68 | AD33: =$A$33*112% -> 15.68 | AE33: =$A$33*112% -> 15.68 | AF33: =$A$33*112% -> 15.68 | AG33: =$A$33*112% -> 15.68 | AH33: =$A$33*112% -> 15.68 | ... AX33: =$A$33*112% -> 15.68
B35: Расходы | C35: =SUM(C36:C41) -> 157924.11 | D35: =SUM(D36:D41) -> 142918.47 | E35: =SUM(E36:E41) -> 134912.39 | F35: =SUM(F36:F41) -> 131664.55 | G35: =SUM(G36:G41) -> 131303.97 | H35: =SUM(H36:H41) -> 132723.96 | I35: =SUM(I36:I41) -> 135271.28 | J35: =SUM(J36:J41) -> 138561.78 | ... AX35: =SUM(AX36:AX41) -> 882533.69
A36: 5300 | B36: Аренда | C36: =$A$36 -> 5300 | D36: =$A$36 -> 5300 | E36: =$A$36 -> 5300 | F36: =$A$36 -> 5300 | G36: =$A$36 -> 5300 | H36: =$A$36 -> 5300 | I36: =$A$36 -> 5300 | J36: =$A$36 -> 5300 | ... N36: =$A$36 -> 5300 | O36: =$A$36*110% -> 5830 | P36: =$A$36*110% -> 5830 | Q36: =$A$36*110% -> 5830 | R36: =$A$36*110% -> 5830 | S36: =$A$36*110% -> 5830 | T36: =$A$36*110% -> 5830 | U36: =$A$36*110% -> 5830 | V36: =$A$36*110% -> 5830 | ... Z36: =$A$36*110% -> 5830 | AA36: =$A$36*115% -> 6095 | AB36: =$A$36*115% -> 6095 | AC36: =$A$36*115% -> 6095 | AD36: =$A$36*115% -> 6095 | AE36: =$A$36*115% -> 6095 | AF36: =$A$36*115% -> 6095 | AG36: =$A$36*115% -> 6095 | AH36: =$A$36*115% -> 6095 | ... AX36: =$A$36*115% -> 6095
A37: 4000 | B37: ФОТ | C37: =$A$37*C32 -> 32000 | D37: =$A$37*D32 -> 32000 | E37: =$A$37*E32 -> 32000 | F37: =$A$37*F32 -> 32000 | G37: =$A$37*G32 -> 32000 | H37: =$A$37*H32 -> 32000 | I37: =$A$37*I32 -> 32000 | J37: =$A$37*J32 -> 32000 | ... N37: =$A$37*N32 -> 36000 | O37: =$A$37*O32*105% -> 37800 | P37: =$A$37*P32*105% -> 37800 | Q37: =$A$37*Q32*105% -> 42000 | R37: =$A$37*R32*105% -> 42000 | S37: =$A$37*S32*105% -> 42000 | T37: =$A$37*T32*105% -> 42000 | U37: =$A$37*U32*105% -> 42000 | V37: =$A$37*V32*105% -> 42000 | ... Z37: =$A$37*Z32*105% -> 46200 | AA37: =$A$37*AA32*110% -> 48400 | AB37: =$A$37*AB32*110% -> 48400 | AC37: =$A$37*AC32*110% -> 48400 | AD37: =$A$37*AD32*110% -> 48400 | AE37: =$A$37*AE32*110% -> 52800 | AF37: =$A$37*AF32*110% -> 52800 | AG37: =$A$37*AG32*110% -> 52800 | AH37: =$A$37*AH32*110% -> 52800 | ... AX37: =$A$37*AX32*110% -> 48400
B38: Бюджет на маркетинг | C38: =C14*C33 -> 42000 | D38: =D14*D33 -> 44100 | E38: =E14*E33 -> 46305 | F38: =F14*F33 -> 48620.25 | G38: =G14*G33 -> 51051.263 | H38: =H14*H33 -> 53603.826 | I38: =I14*I33 -> 56284.017 | J38: =J14*J33 -> 59098.218 | ... AX38: =AX14*AX33 -> 465976.88
B39: Затраты на скидки | C39: =C13*C28 -> 27534.6 | D39: =D13*D28 -> 21245.76 | E39: =E13*E28 -> 17118.416 | F39: =F13*F28 -> 14778.9 | G39: =G13*G28 -> 13473.45 | H39: =H13*H28 -> 12762.158 | I39: =I13*I28 -> 12388.142 | J39: =J13*J28 -> 12201.131 | ... AX39: =AX13*AX28 -> 102526.04
A40: 2.5 | B40: Выплаты курьерам за доставку | C40: =C21*($A$40-1) -> 47359.512 | D40: =D21*($A$40-1) -> 36542.707 | E40: =E21*($A$40-1) -> 30458.974 | F40: =F21*($A$40-1) -> 27235.402 | G40: =G21*($A$40-1) -> 25749.26 | H40: =H21*($A$40-1) -> 25327.975 | I40: =I21*($A$40-1) -> 25569.125 | J40: =J21*($A$40-1) -> 26232.432 | ... AX40: =AX21*($A$40-1) -> 254086.27
B41: Прочие операционные расходы | C41: =SUM(C36:C37)*10% -> 3730 | D41: =SUM(D36:D37)*10% -> 3730 | E41: =SUM(E36:E37)*10% -> 3730 | F41: =SUM(F36:F37)*10% -> 3730 | G41: =SUM(G36:G37)*10% -> 3730 | H41: =SUM(H36:H37)*10% -> 3730 | I41: =SUM(I36:I37)*10% -> 3730 | J41: =SUM(J36:J37)*10% -> 3730 | ... AX41: =SUM(AX36:AX37)*10% -> 5449.5
B42: Прирост расходов (% к прошлому месяцу) | C42: 1 | D42: =(D35/C35)-100% -> -0.095018073 | E42: =(E35/D35)-100% -> -0.056018492 | F42: =(F35/E35)-100% -> -0.02407368 | G42: =(G35/F35)-100% -> -0.0027386302 | H42: =(H35/G35)-100% -> 0.0108145 | I42: =(I35/H35)-100% -> 0.019192659 | J42: =(J35/I35)-100% -> 0.024325172 | K42: =(K35/J35)-100% -> 0.027490867 | ... AX42: =(AX35/AW35)-100% -> 0.04047644
B44: EBITDA (операционная прибыль) | C44: =C9-C35 -> -22956.111 | D44: =D9-D35 -> -38776.851 | E44: =E9-E35 -> -48108.563 | F44: =F9-F35 -> -54047.457 | G44: =G9-G35 -> -57922.175 | H44: =H9-H35 -> -60542.764 | I44: =I9-I35 -> -62402.845 | J44: =J9-J35 -> -63803.009 | ... AX44: =AX9-AX35 -> 227564.76
B45: EBITDA нарастающим итогом | C45: =C44 -> -22956.111 | D45: =D44+C45 -> -61732.962 | E45: =E44+D45 -> -109841.53 | F45: =F44+E45 -> -163888.98 | G45: =G44+F45 -> -221811.16 | H45: =H44+G45 -> -282353.92 | I45: =I44+H45 -> -344756.77 | J45: =J44+I45 -> -408559.78 | K45: =K44+J45 -> -473485.88 | ... AX45: =AX44+AW45 -> 1327981.6
B46: Рентабельность EBITDA (% от общей выручки) | C46: =C44/C9 -> -0.17008558 | D46: =D44/D9 -> -0.37234731 | E46: =E44/E9 -> -0.55422169 | F46: =F44/F9 -> -0.69633444 | G46: =G44/G9 -> -0.7893262 | H46: =H44/H9 -> -0.8387609 | I46: =I44/I9 -> -0.85637686 | J46: =J44/J9 -> -0.85345181 | ... AX46: =AX44/AX9 -> 0.20499512
B48: Прочие расходы
A49: 0.21 | B49: Налоговая нагрузка | C49: =IF(C44>0, C44*$A$49, 0) -> 0 | D49: =IF(D44>0, D44*$A$49, 0) -> 0 | E49: =IF(E44>0, E44*$A$49, 0) -> 0 | F49: =IF(F44>0, F44*$A$49, 0) -> 0 | G49: =IF(G44>0, G44*$A$49, 0) -> 0 | H49: =IF(H44>0, H44*$A$49, 0) -> 0 | I49: =IF(I44>0, I44*$A$49, 0) -> 0 | J49: =IF(J44>0, J44*$A$49, 0) -> 0 | ... AX49: =IF(AX44>0, AX44*$A$49, 0) -> 47788.599
B51: Чистая прибыль | C51: =C44-C49 -> -22956.111 | D51: =D44-D49 -> -38776.851 | E51: =E44-E49 -> -48108.563 | F51: =F44-F49 -> -54047.457 | G51: =G44-G49 -> -57922.175 | H51: =H44-H49 -> -60542.764 | I51: =I44-I49 -> -62402.845 | J51: =J44-J49 -> -63803.009 | ... AX51: =AX44-AX49 -> 179776.16
B52: Прибыль нарастающим итогом | C52: =C51 -> -22956.111 | D52: =C52+D51 -> -61732.962 | E52: =D52+E51 -> -109841.53 | F52: =E52+F51 -> -163888.98 | G52: =F52+G51 -> -221811.16 | H52: =G52+H51 -> -282353.92 | I52: =H52+I51 -> -344756.77 | J52: =I52+J51 -> -408559.78 | K52: =J52+K51 -> -473485.88 | ... AX52: =AW52+AX51 -> 785913.03
B53: Рентабельность чистой прибыли (%) | C53: =C51/C9 -> -0.17008558 | D53: =D51/D9 -> -0.37234731 | E53: =E51/E9 -> -0.55422169 | F53: =F51/F9 -> -0.69633444 | G53: =G51/G9 -> -0.7893262 | H53: =H51/H9 -> -0.8387609 | I53: =I51/I9 -> -0.85637686 | J53: =J51/J9 -> -0.85345181 | ... AX53: =AX51/AX9 -> 0.16194614
C57: 1 год | D57: 2 год | E57: 3 год | F57: 4 год | G57: 5 год
B58: Сумма чистой прибыли (год) | C58: -1477422 | D58: =SUM(C51:N51) -> -690349.66 | E58: =SUM(O51:Z51) -> -562947.8 | F58: =SUM(AA51:AL51) -> 524981.08 | G58: =SUM(AM51:AX51) -> 1514229.4
B59: NPV | F59: =C58 + NPV(0.15, D58:F58) -> -2158211.9 | G59: =C58 + NPV(0.15, D58:G58) -> -1292446.3
B60: IRR | F60: =IRR(C58:F58) -> -0.5513335 | G60: =IRR(C58:G58) -> -0.091139267

Sheet Financial Data
B4: Operational Metrics | C4: Units | D4: 45658 | E4: =EOMONTH(D4,0)+1 -> 45689 | F4: =EOMONTH(E4,0)+1 -> 45717 | G4: =EOMONTH(F4,0)+1 -> 45748 | H4: =EOMONTH(G4,0)+1 -> 45778 | I4: =EOMONTH(H4,0)+1 -> 45809 | J4: =EOMONTH(I4,0)+1 -> 45839 | K4: =EOMONTH(J4,0)+1 -> 45870 | L4: =EOMONTH(K4,0)+1 -> 45901 | ... O4: =EOMONTH(N4,0)+1 -> 45992
B6: Total Orders | C6: # | D6: ='Operational Data'!D15 -> 758.8 | E6: ='Operational Data'!E15 -> 1517.6 | F6: ='Operational Data'!F15 -> 4085.8995 | G6: ='Operational Data'!G15 -> 4233.786 | H6: ='Operational Data'!H15 -> 6103.6658 | I6: ='Operational Data'!I15 -> 10337.02 | J6: ='Operational Data'!J15 -> 14291.926 | K6: ='Operational Data'!K15 -> 17071.453 | ... O6: ='Operational Data'!O15 -> 53545.037
B7: Gross Transactions | C7: usd | D7: ='Operational Data'!D16*'Operational Data'!D25 -> 2276.4 | E7: ='Operational Data'!E16*'Operational Data'!E25 -> 5759.292 | F7: ='Operational Data'!F16*'Operational Data'!F25 -> 11327.427 | G7: ='Operational Data'!G16*'Operational Data'!G25 -> 23996.494 | H7: ='Operational Data'!H16*'Operational Data'!H25 -> 32432.537 | I7: ='Operational Data'!I16*'Operational Data'!I25 -> 55763.936 | J7: ='Operational Data'!J16*'Operational Data'!J25 -> 75554.347 | K7: ='Operational Data'!K16*'Operational Data'!K25 -> 101078.13 | ... O7: ='Operational Data'!O16*'Operational Data'!O25 -> 281014.7
B9: Total revenue | C9: usd | D9: =SUM(D10:D13) -> 113.82 | E9: =SUM(E10:E13) -> 287.9646 | F9: =SUM(F10:F13) -> 566.37134 | G9: =SUM(G10:G13) -> 7211.9521 | H9: =SUM(H10:H13) -> 10224.185 | I9: =SUM(I10:I13) -> 34335.102 | J9: =SUM(J10:J13) -> 48325.033 | K9: =SUM(K10:K13) -> 58806.378 | ... O9: =SUM(O10:O13) -> 165800.05
B10: Delivery revenue | C10: usd | D10: ='Operational Data'!D16*'Operational Data'!D21 -> 0 | E10: ='Operational Data'!E16*'Operational Data'!E21 -> 0 | F10: ='Operational Data'!F16*'Operational Data'!F21 -> 0 | G10: ='Operational Data'!G16*'Operational Data'!G21 -> 0 | H10: ='Operational Data'!H16*'Operational Data'!H21 -> 0 | I10: ='Operational Data'!I16*'Operational Data'!I21 -> 16952.712 | J10: ='Operational Data'!J16*'Operational Data'!J21 -> 25725.466 | K10: ='Operational Data'!K16*'Operational Data'!K21 -> 30728.615 | ... O10: ='Operational Data'!O16*'Operational Data'!O21 -> 82459.357
B11: Subscription revenue | C11: usd | D11: ='Operational Data'!D19*'Operational Data'!D6 -> 0 | E11: ='Operational Data'!E19*'Operational Data'!E6 -> 0 | F11: ='Operational Data'!F19*'Operational Data'!F6 -> 0 | G11: ='Operational Data'!G19*'Operational Data'!G6 -> 5292.2325 | H11: ='Operational Data'!H19*'Operational Data'!H6 -> 7629.5822 | I11: ='Operational Data'!I19*'Operational Data'!I6 -> 12921.275 | J11: ='Operational Data'!J19*'Operational Data'!J6 -> 15044.132 | K11: ='Operational Data'!K19*'Operational Data'!K6 -> 17969.95 | ... O11: ='Operational Data'!O19*'Operational Data'!O6 -> 41188.49
B12: Ads revenue | C12: usd | D12: 0 | E12: 0 | F12: 0 | G12: 0 | H12: 0 | I12: 0 | J12: 0 | K12: 0 | L12: 0 | M12: 0 | N12: 0 | O12: 0
B13: Comission revenue | C13: usd | D13: ='Operational Data'!D16*'Operational Data'!D25*'Operational Data'!D20 -> 113.82 | E13: ='Operational Data'!E16*'Operational Data'!E25*'Operational Data'!E20 -> 287.9646 | F13: ='Operational Data'!F16*'Operational Data'!F25*'Operational Data'!F20 -> 566.37134 | G13: ='Operational Data'!G16*'Operational Data'!G25*'Operational Data'!G20 -> 1919.7195 | H13: ='Operational Data'!H16*'Operational Data'!H25*'Operational Data'!H20 -> 2594.6029 | I13: ='Operational Data'!I16*'Operational Data'!I25*'Operational Data'!I20 -> 4461.1149 | J13: ='Operational Data'!J16*'Operational Data'!J25*'Operational Data'!J20 -> 7555.4347 | K13: ='Operational Data'!K16*'Operational Data'!K25*'Operational Data'!K20 -> 10107.813 | ... O13: ='Operational Data'!O16*'Operational Data'!O25*'Operational Data'!O20 -> 42152.204
B15: Operational costs | C15: usd | D15: =D16+D17 -> 4800 | E15: =E16+E17 -> 6900 | F15: =F16+F17 -> 14950 | G15: =G16+G17 -> 14852.5 | H15: =H16+H17 -> 24700 | I15: =I16+I17 -> 32400 | J15: =J16+J17 -> 41600 | K15: =K16+K17 -> 48830 | ... O15: =O16+O17 -> 97060.137
B16: Courier subsidies | C16: usd | D16: ='Operational Data'!D28*'Operational Data'!D30 -> 800 | E16: ='Operational Data'!E28*'Operational Data'!E30 -> 900 | F16: ='Operational Data'!F28*'Operational Data'!F30 -> 1950 | G16: ='Operational Data'!G28*'Operational Data'!G30 -> 1852.5 | H16: ='Operational Data'!H28*'Operational Data'!H30 -> 5700 | I16: ='Operational Data'!I28*'Operational Data'!I30 -> 5400 | J16: ='Operational Data'!J28*'Operational Data'!J30 -> 9600 | K16: ='Operational Data'!K28*'Operational Data'!K30 -> 10830 | ... O16: ='Operational Data'!O28*'Operational Data'!O30 -> 11060.137
B17: Courier salaries | C17: usd | D17: ='Operational Data'!D31*'Operational Data'!D30 -> 4000 | E17: ='Operational Data'!E31*'Operational Data'!E30 -> 6000 | F17: ='Operational Data'!F31*'Operational Data'!F30 -> 13000 | G17: ='Operational Data'!G31*'Operational Data'!G30 -> 13000 | H17: ='Operational Data'!H31*'Operational Data'!H30 -> 19000 | I17: ='Operational Data'!I31*'Operational Data'!I30 -> 27000 | J17: ='Operational Data'!J31*'Operational Data'!J30 -> 32000 | K17: ='Operational Data'!K31*'Operational Data'!K30 -> 38000 | ... O17: ='Operational Data'!O31*'Operational Data'!O30 -> 86000
B19: Marketing costs | C19: usd | D19: =SUM(D20:D21) -> 11653 | E19: =SUM(E20:E21) -> 21138 | F19: =SUM(F20:F21) -> 52159.061 | G19: =SUM(G20:G21) -> 48566.156 | H19: =SUM(H20:H21) -> 58313.135 | I19: =SUM(I20:I21) -> 91881.629 | J19: =SUM(J20:J21) -> 98995.44 | K19: =SUM(K20:K21) -> 99756.924 | ... O19: =SUM(O20:O21) -> 162655.52
B20: Customer subsidies | C20: usd | D20: ='Operational Data'!D27*'Operational Data'!D6 -> 813 | E20: ='Operational Data'!E27*'Operational Data'!E6 -> 1626 | F20: ='Operational Data'!F27*'Operational Data'!F6 -> 3639.0043 | G20: ='Operational Data'!G27*'Operational Data'!G6 -> 3582.1799 | H20: ='Operational Data'!H27*'Operational Data'!H6 -> 4906.0598 | I20: ='Operational Data'!I27*'Operational Data'!I6 -> 7893.3442 | J20: ='Operational Data'!J27*'Operational Data'!J6 -> 8730.6471 | K20: ='Operational Data'!K27*'Operational Data'!K6 -> 9907.1735 | ... O20: ='Operational Data'!O27*'Operational Data'!O6 -> 18495.803
B21: General marketing | C21: usd | D21: ='Operational Data'!D36*'Operational Data'!D6 -> 10840 | E21: ='Operational Data'!E36*'Operational Data'!E6 -> 19512 | F21: ='Operational Data'!F36*'Operational Data'!F6 -> 48520.057 | G21: ='Operational Data'!G36*'Operational Data'!G6 -> 44983.977 | H21: ='Operational Data'!H36*'Operational Data'!H6 -> 53407.076 | I21: ='Operational Data'!I36*'Operational Data'!I6 -> 83988.285 | J21: ='Operational Data'!J36*'Operational Data'!J6 -> 90264.793 | K21: ='Operational Data'!K36*'Operational Data'!K6 -> 89849.751 | ... O21: ='Operational Data'!O36*'Operational Data'!O6 -> 144159.71
B23: SG&A | C23: usd | D23: =SUM(D24:D26) -> 29000 | E23: =SUM(E24:E26) -> 29800 | F23: =SUM(F24:F26) -> 29285.714 | G23: =SUM(G24:G26) -> 30142.857 | H23: =SUM(H24:H26) -> 33591.837 | I23: =SUM(I24:I26) -> 34510.204 | J23: =SUM(J24:J26) -> 33919.825 | K23: =SUM(K24:K26) -> 34903.79 | ... O23: =SUM(O24:O26) -> 42042.641
B24: Salaries | C24: usd | D24: ='Operational Data'!D34*4000 -> 20000 | E24: ='Operational Data'!E34*4000 -> 20000 | F24: ='Operational Data'!F34*4000 -> 20000 | G24: ='Operational Data'!G34*4000 -> 20000 | H24: ='Operational Data'!H34*4000 -> 24000 | I24: ='Operational Data'!I34*4000 -> 24000 | J24: ='Operational Data'!J34*4000 -> 24000 | K24: ='Operational Data'!K34*4000 -> 24000 | ... O24: ='Operational Data'!O34*4000 -> 32000
B25: Office cost | C25: usd | D25: 5000 | E25: 5000 | F25: 5000 | G25: 5000 | H25: 5000 | I25: 5000 | J25: 5000 | K25: 5000 | L25: 5000 | M25: 5000 | N25: 5000 | O25: 5000
B26: Other costs | C26: usd | D26: 4000 | E26: 4800 | F26: 4285.7143 | G26: 5142.8571 | H26: 4591.8367 | I26: 5510.2041 | J26: 4919.8251 | K26: 5903.7901 | L26: 5271.2411 | M26: 6325.4894 | N26: 5647.7584 | O26: 5042.6414
B28: EBITDA | C28: usd | D28: =D9-D15-D19-D23 -> -45339.18 | E28: =E9-E15-E19-E23 -> -57550.035 | F28: =F9-F15-F19-F23 -> -95828.404 | G28: =G9-G15-G19-G23 -> -86349.561 | H28: =H9-H15-H19-H23 -> -106380.79 | I28: =I9-I15-I19-I23 -> -124456.73 | J28: =J9-J15-J19-J23 -> -126190.23 | K28: =K9-K15-K19-K23 -> -124684.34 | ... O28: =O9-O15-O19-O23 -> -135958.25
B29: EBITDA margin | C29: % | D29: =D28/D7 -> -19.917053 | E29: =E28/E7 -> -9.9925538 | F29: =F28/F7 -> -8.4598564 | G29: =G28/G7 -> -3.598424 | H29: =H28/H7 -> -3.2800637 | I29: =I28/I7 -> -2.2318498 | J29: =J28/J7 -> -1.6701915 | K29: =K28/K7 -> -1.2335441 | ... O29: =O28/O7 -> -0.48381187
D32: Корреляция между затратами на маркетинг и приходом новых клиентов | O32: =SUM(D28:O28) -> -1477421.6
D33: Соотношение расходов на маркетинг и новых клиентов по двум осям
D34: EBITDA margin + absolute numbers
D36: Соотношение расходов на маркетинг и выручки

Sheet Operational Data
B4: Operational Metrics | C4: Units | D4: 45658 | E4: =EOMONTH(D4,0)+1 -> 45689 | F4: =EOMONTH(E4,0)+1 -> 45717 | G4: =EOMONTH(F4,0)+1 -> 45748 | H4: =EOMONTH(G4,0)+1 -> 45778 | I4: =EOMONTH(H4,0)+1 -> 45809 | J4: =EOMONTH(I4,0)+1 -> 45839 | K4: =EOMONTH(J4,0)+1 -> 45870 | L4: =EOMONTH(K4,0)+1 -> 45901 | ... O4: =EOMONTH(N4,0)+1 -> 45992
B6: Общее кол-во заказчиков | C6: # | D6: 542 | E6: 1084 | F6: 2553.6872 | G6: 2646.1163 | H6: 3814.7911 | I6: 6460.6373 | J6: 7522.0661 | K6: 8984.9751 | L6: 14624.132 | M6: 16808.06 | N6: 19073.487 | O6: 20594.245
B7: Кол-во новичков | C7: # | D7: 542 | E7: 775.06 | F7: 1643.1272 | G7: 1369.2727 | H7: 1697.8981 | I7: 3599.544 | J7: 2999.62 | K7: 3719.5288 | L7: 7885.401 | M7: 6571.1675 | N7: 8148.2477 | O7: 10103.827
B8: Оттекших клиентов | C8: # | E8: =E7+D6-E6 -> 233.06 | F8: =F7+E6-F6 -> 173.44 | G8: =G7+F6-G6 -> 1276.8436 | H8: =H7+G6-H6 -> 529.22325 | I8: =I7+H6-I6 -> 953.69778 | J8: =J7+I6-J6 -> 1938.1912 | K8: =K7+J6-K6 -> 2256.6198 | L8: =L7+K6-L6 -> 2246.2438 | ... O8: =O7+N6-O6 -> 8583.0691
B9: Отток | C9: % | E9: =E8/E6 -> 0.215 | F9: =F8/F6 -> 0.06791748 | G9: =G8/G6 -> 0.48253496 | H9: =H8/H6 -> 0.13872929 | I9: =I8/I6 -> 0.14761667 | J9: =J8/J6 -> 0.2576674 | K9: =K8/K6 -> 0.25115482 | L9: =L8/L6 -> 0.15359843 | ... O9: =O8/O6 -> 0.41677027
B11: Общее кол-во поваров | C11: # | D11: 20 | E11: 36 | F11: 51.3 | G11: 108.54 | H11: 174.582 | I11: 238.8231 | J11: 305.08961 | K11: 370.64623 | L11: 409.52998 | M11: 453.0684 | N11: 474.45867 | O11: 479.57045
B12: Новые повара | C12: # | D12: 20 | E12: 20 | F12: 22.5 | G12: 67.5 | H12: 87.75 | I12: 99.1575 | J12: 114.03112 | K12: 126.57455 | L12: 113.01299 | M12: 125.44442 | N12: 112.00395 | O12: 100.00352
B13: Заказчиков на 1 повара | D13: =D7/D11 -> 27.1 | E13: =E7/E11 -> 21.529444 | F13: =F7/F11 -> 32.02977 | G13: =G7/G11 -> 12.615374 | H13: =H7/H11 -> 9.725505 | I13: =I7/I11 -> 15.072009 | J13: =J7/J11 -> 9.8319311 | K13: =K7/K11 -> 10.035253 | ... O13: =O7/O11 -> 21.068494
B15: Созданные заказы | C15: # | D15: =D6*1.4 -> 758.8 | E15: =E6*1.4 -> 1517.6 | F15: =F6*1.6 -> 4085.8995 | G15: =G6*1.6 -> 4233.786 | H15: =H6*1.6 -> 6103.6658 | I15: =I6*1.6 -> 10337.02 | J15: =J6*1.9 -> 14291.926 | K15: =K6*1.9 -> 17071.453 | L15: =L6*1.9 -> 27785.851 | M15: =M6*2.1 -> 35296.926 | N15: =N6*1.2 -> 22888.184 | O15: =O6*2.6 -> 53545.037
B16: Доставленные заказы | C16: # | D16: =D15*D17 -> 379.4 | E16: =E15*E17 -> 834.68 | F16: =F15*F17 -> 1838.6548 | G16: =G15*G17 -> 3387.0288 | H16: =H15*H17 -> 5127.0793 | I16: =I15*I17 -> 8476.3562 | J16: =J15*J17 -> 12862.733 | K16: =K15*K17 -> 15364.307 | ... O16: =O15*O17 -> 41229.678
B17: Процент успешных доставок | C17: % | D17: 0.5 | E17: 0.55 | F17: 0.45 | G17: 0.8 | H17: 0.84 | I17: 0.82 | J17: 0.9 | K17: 0.9 | L17: 0.81 | M17: 0.84 | N17: 0.82 | O17: 0.77
B19: Стоимость подписки на сервис | C19: usd | D19: 0 | E19: 0 | F19: 0 | G19: 2 | H19: 2 | I19: 2 | J19: 2 | K19: 2 | L19: 2 | M19: 2 | N19: 2 | O19: 2
B20: Комиссия сервиса с шефов | C20: % | D20: 0.05 | E20: 0.05 | F20: 0.05 | G20: 0.08 | H20: 0.08 | I20: 0.08 | J20: 0.1 | K20: 0.1 | L20: 0.1 | M20: 0.13 | N20: 0.14 | O20: 0.15
B21: Стоимость доставки | C21: usd | D21: 0 | E21: 0 | F21: 0 | G21: 0 | H21: 0 | I21: 2 | J21: 2 | K21: 2 | L21: 2 | M21: 2 | N21: 2 | O21: 2
B23: Конверсия из сессии в заказ | C23: % | D23: 0.25 | E23: 0.3 | F23: 0.2 | G23: 0.5 | H23: 0.55 | I23: 0.4 | J23: 0.64 | K23: 0.6 | L23: 0.35 | M23: 0.42 | N23: 0.33 | O23: 0.3
B25: Стоимость 1 обеда | C25: usd | D25: 6 | E25: 6.9 | F25: 6.1607143 | G25: 7.0848214 | H25: 6.3257334 | I25: 6.5787628 | J25: 5.8738953 | K25: 6.5787628 | L25: 5.9268133 | M25: 6.8158353 | N25: 6.0855672 | O25: 6.8158353
B27: Скидки на 1 пользователя в месяц | C27: usd | D27: 1.5 | E27: 1.5 | F27: =E27*0.95 -> 1.425 | G27: =F27*0.95 -> 1.35375 | H27: =G27*0.95 -> 1.2860625 | I27: =H27*0.95 -> 1.2217594 | J27: =I27*0.95 -> 1.1606714 | K27: =J27*0.95 -> 1.1026378 | L27: =K27*0.95 -> 1.0475059 | M27: =L27*0.95 -> 0.99513065 | ... O27: =N27*0.95 -> 0.89810541
B28: Бонусы на 1 курьера в месяц | C28: usd | D28: 200 | E28: 150 | F28: 150 | G28: =F28*0.95 -> 142.5 | H28: 300 | I28: 200 | J28: 300 | K28: =J28*0.95 -> 285 | L28: 150 | M28: =L28*0.95 -> 142.5 | N28: =M28*0.95 -> 135.375 | O28: =N28*0.95 -> 128.60625
B30: Кол-во курьеров | C30: # | D30: =ROUNDUP(D6/30/6,0) -> 4 | E30: =ROUNDUP(E6/30/7,0) -> 6 | F30: =ROUNDUP(F6/30/7,0) -> 13 | G30: =ROUNDUP(G6/30/7,0) -> 13 | H30: =ROUNDUP(H6/30/7,0) -> 19 | I30: =ROUNDUP(I6/30/8,0) -> 27 | J30: =ROUNDUP(J6/30/8,0) -> 32 | K30: =ROUNDUP(K6/30/8,0) -> 38 | L30: =ROUNDUP(L6/30/8,0) -> 61 | M30: =ROUNDUP(M6/30/8,0) -> 71 | N30: =ROUNDUP(N6/30/8,0) -> 80 | O30: =ROUNDUP(O6/30/8,0) -> 86
B31: Месячная зарплата курьеров до бонусов | C31: usd | D31: 1000 | E31: 1000 | F31: 1000 | G31: 1000 | H31: 1000 | I31: 1000 | J31: 1000 | K31: 1000 | L31: 1000 | M31: 1000 | N31: 1000 | O31: 1000
B32: Заказы в день на курьера | C32: # | D32: 7 | E32: 7 | F32: 7 | G32: 7 | H32: 7 | I32: 8 | J32: 8 | K32: 8 | L32: 8 | M32: 8 | N32: 8 | O32: 8
B34: Кол-во сотрудников | C34: usd | D34: 5 | E34: 5 | F34: 5 | G34: 5 | H34: =G34+1 -> 6 | I34: =H34 -> 6 | J34: =I34 -> 6 | K34: =J34 -> 6 | L34: =K34 -> 6 | M34: =L34+1 -> 7 | N34: =M34+1 -> 8 | O34: =N34 -> 8
B36: CAC | C36: usd | D36: 20 | E36: 18 | F36: 19 | G36: 17 | H36: 14 | I36: 13 | J36: 12 | K36: 10 | L36: 11 | M36: 9 | N36: 8 | O36: 7
B37: 3Y LTV | C37: usd | D37: 3 | E37: 2 | F37: 4 | G37: 5 | H37: 4 | I37: 5 | J37: 6 | K37: 6 | L37: 7 | M37: 7 | N37: 8 | O37: 8
B38: Частотность заказов (созданные) | D38: =D15/D6 -> 1.4 | E38: =E15/E6 -> 1.4 | F38: =F15/F6 -> 1.6 | G38: =G15/G6 -> 1.6 | H38: =H15/H6 -> 1.6 | I38: =I15/I6 -> 1.6 | J38: =J15/J6 -> 1.9 | K38: =K15/K6 -> 1.9 | ... O38: =O15/O6 -> 2.6
B39: Частотность заказов (доставка) | D39: =D16/D6 -> 0.7 | E39: =E16/E6 -> 0.77 | F39: =F16/F6 -> 0.72 | G39: =G16/G6 -> 1.28 | H39: =H16/H6 -> 1.344 | I39: =I16/I6 -> 1.312 | J39: =J16/J6 -> 1.71 | K39: =K16/K6 -> 1.71 | ... O39: =O16/O6 -> 2.002
B40: Потери в воронке (в заказах) | D40: =D38-D39 -> 0.7 | E40: =E38-E39 -> 0.63 | F40: =F38-F39 -> 0.88 | G40: =G38-G39 -> 0.32 | H40: =H38-H39 -> 0.256 | I40: =I38-I39 -> 0.288 | J40: =J38-J39 -> 0.19 | K40: =K38-K39 -> 0.19 | ... O40: =O38-O39 -> 0.598
B41: Потери в воронке (по стоимости на клиента) | C41: usd | D41: =(('Financial Data'!D13 + 'Financial Data'!D10) / 'Financial Data'!D6)*D40 -> 0.105 | E41: =(('Financial Data'!E13 + 'Financial Data'!E10) / 'Financial Data'!E6)*E40 -> 0.1195425 | F41: =(('Financial Data'!F13 + 'Financial Data'!F10) / 'Financial Data'!F6)*F40 -> 0.12198214 | G41: =(('Financial Data'!G13 + 'Financial Data'!G10) / 'Financial Data'!G6)*G40 -> 0.14509714 | H41: =(('Financial Data'!H13 + 'Financial Data'!H10) / 'Financial Data'!H6)*H40 -> 0.10882286 | I41: =(('Financial Data'!I13 + 'Financial Data'!I10) / 'Financial Data'!I6)*I40 -> 0.59661125 | J41: =(('Financial Data'!J13 + 'Financial Data'!J10) / 'Financial Data'!J6)*J40 -> 0.44244361 | K41: =(('Financial Data'!K13 + 'Financial Data'!K10) / 'Financial Data'!K6)*K40 -> 0.45449684 | ... O41: =(('Financial Data'!O13 + 'Financial Data'!O10) / 'Financial Data'!O6)*O40 -> 1.3916829
B42: Потери в воронке (по стоимости на клиента) | D42: =D41*D6 -> 56.91 | E42: =E41*E6 -> 129.58407 | F42: =F41*F6 -> 311.50424 | G42: =G41*G6 -> 383.94391 | H42: =H41*H6 -> 415.13647 | I42: =I41*I6 -> 3854.4889 | J42: =J41*J6 -> 3328.0901 | K42: =K41*K6 -> 4083.6428 | ... O42: =O41*O6 -> 28660.659
D46: Корреляция заказчиков на одного повара и процента успешных доставок | E46: =CORREL(D13:O13,D17:O17) -> -0.90868396

Sheet Info
B2: Перед вами операционная и финансовая информация о стартапе. Компания разрабатывает сервис по доставке готовых обедов от домашних поваров. Лист Operational Data содержит ряд операционных метрик, которые являются основными драйверами бизнеса. Лист Financial Metrics содержит фактическую информацию о первых 12 месяцах работы компании
B4: Блок 1. Анализ. Проанализировать имеющиеся операционные и финансовые метрики, и на основании их осознать ключевые драйверы и достижения за первые 12 месяцев
B6: Что необходимо сделать:
B7: Проанализировать динамику пользователей и шефов
B8: Проанализировать количество успешно выполненных заказов
B9: Проанализировать динамику частотности заказов на 1 пользователя
B10: Проанализировать экономику работы бизнес-модели
B11: *Подсказка 1: при изменении драйверов в листе Operational Data, пересчитывается лист Financial Data. Тем самым можно посмотреть, как те или иные метрики влияют на бизнес **Подсказка 2: условное форматирование / помесячные графики по строчкам помогут выявить взаимосвязь метрик
B13: Какой результат необходимо получить:
B14: Понять работу бизнес-модели по драйверам
B15: Интерпретировать финансовые результаты за первые 12 месяцев
B16: Выдвинуть гипотезы о сильных/слабых местах компании (какие метрики и как можно улучшить)
... B33: Оценить, как изменятся NPV и IRR кейса
